Workbook
Name Actividad_fisica: 'Pediatría'!$L$55:$L$57
Name Actividad_fisica: 'Pediatría'!$L$55:$L$57
Name Z_EED67FAE_D7A7_442D_B29B_6BF40C688036_.wvu.Cols: 'Antropometría'!$E:$E

Sheet Inicio
B15: Bienvenid@, a continuación encontrará cada uno de los botones para ingresar a la sección de su interés. En caso de requerir ayuda comuníquese al correo evanut.app@gmail.com o a través de Whatsapp +57 300 2881395. Con la compra de EVANUT apoyas el sostenimiento estudiantil, te invitamos a ser una persona ética y honesta, evita compartir esta herramienta con otras personas.
H26: Evaluación de la composición corporal del adulto
H29: Evaluación del consumo de alimentos de un paciente, puede usar un R24h
H32: Fórmulas de requerimiento y planeación dietética del paciente adulto
H35: Evaluación de la composición corporal y planeación dietética del paciente pediátrico (0 a 18 años)
H38: Evaluación, seguimiento y planeación dietética de la gestante adulta
H41: Evaluación, seguimiento y planeación dietética de la gestante adolescente
H44: Estimación de peso y talla, determinación de requerimiento energético y de líquidos, fórmulas de nutrición parenteral en el adulto hospitalizado
H47: Evaluación de la composición corporal, somatocarta y planeación dietética del deportista
H50: Planeación dietética (solo fórmula desarrollada, fórmula sintética final, minuta patrón y ejemplo de menú) en pacientes de todas las edades
H53: Fórmulas de porcentaje de grasa de Durnin y Womersley, y Jackson y Pollock, de años anteriores y en diferentes grupos poblacionales
H56: Espacio para poner las notas que requiera frente al análisis del paciente que está tratando

Sheet Antropometría
B2: EVALUACIÓN ANTROPOMÉTRICA
B3: Nombre | E3: Hombre
B4: Apellido | E4: Mujer
B5: Identificación
B6: Sexo | C6: Hombre
B7: Edad años
B8: Peso kg
B9: Altura m
B10: Altura cm | C10: =C9*100 -> 0
B11: Perímetro cintura cm | F11: NOTA: El porcentaje de grasa se calcula automáticamente bajo la fórmula de Durnin y Womersley del 2011 para población hispana. En caso de requerir una diferente diríjase a la hoja "Otros".
B12: Perímetro abdomen cm
B13: Pliegue biceps mm
B14: Pliegue triceps mm
B15: Pliegue subescapular mm
B16: Pliegue ileocrestal mm | E16: =SUM(C13:C16) -> 0
B17: Pliegue muslo mm | F17: CLASIFICACIÓN % GRASA
G18: HOMBRES | H18: MUJERES
B19: RESULTADOS | F19: Normopeso | G19: 12-20 | H19: 20-30
B20: IMC | C20: =(C8/(C9*C9)) -> #DIV/0! | F20: Limite | G20: 21-25 | H20: 31-33
B21: IMC Clasificación | C21: =IF(C20<18.5,"Delgadez",IF(AND(C20>=18.5,C20<25),"Normal",IF(AND(C20>=25,C20<30),"Sobrepeso","obesidad"))) -> #DIV/0! | F21: Obesidad | G21: >25 | H21: >33
B22: IMC saludable | C22: 25
B23: Peso saludable IMC 25-30 | C23: =IF(C20>=25,(C22*(C9*C9)),"No aplica") -> #DIV/0! | F23: CLASIFICACIÓN IMG
B24: Peso ajustado IMC >30 | C24: =IF(C20>=30,(C23+(0.25*(C8-C23))),"No aplica") -> #DIV/0! | G24: HOMBRES | H24: MUJERES
B25: Cintura/Estatura | C25: =C11/C10 -> #DIV/0! | F25: Deficit | G25: <3 | H25: <5
B26: Clasificación | C26: =IF(C25>0.5,"Riesgo","Sin riesgo") -> #DIV/0! | F26: Normal | G26: 3-6 | H26: 5-9
B27: Cintura cm | C27: =C11 | F27: Exceso | G27: >6 | H27: >9
B28: Clasificación | C28: =IF(C6="Hombre",IF(C27>=90,"Obesidad abdominal","Adecuado"),IF(C27>=80,"Obesidad abdominal","Adecuado")) -> Adecuado
B29: %Grasa | C29: =IF(C6="Hombre",((23.66*(LOG10(E16)))+(0.04*C7)-(0.036*C8)-(0.109*C10)+(0.272*C12)-26.41),((23.871*(LOG10(E16)))+(0.019*C7)-(0.022*C8)-(0.118*C10)+(0.249*C12)-16.782)) -> #NUM! | F29: CLASIFICACIÓN IMLG
B30: Clasificación | C30: =IF(C6="Hombre",IF(C29<=20,"Normopeso",IF(AND(C29>20,C29<=25),"limite",IF(C29>25,"obesidad"))),IF(C29<=30,"Normopeso",IF(AND(C29>30,C29<=33),"limite",IF(C29>33,"obesidad")))) -> #NUM! | G30: HOMBRES | H30: MUJERES
B31: Masa grasa kg | C31: =C29%*C8 -> #NUM! | F31: Malnutricion | G31: <17 | H31: <15
B32: IMG | C32: =C31/(C9*C9) -> #NUM! | F32: Adecuada | G32: 17-21 | H32: 15-18 | J32: REFERENCIAS
B33: Clasificación | C33: =IF(C6="Hombre",IF(C32<2,"Deficit severo",IF(AND(C32>=2,C32<2.3),"Deficit moderado",IF(AND(C32>=2.3,C32<3),"Deficit leve",IF(AND(C32>=3,C32<=6),"Normal",IF(AND(C32>6,C32<=9),"Exceso",IF(AND(C32>9,C32<=12),"Obesidad I",IF(AND(C32>12,C32<=15),"Obesidad II","Obesidad III"))))))),IF(C32<3.5,"Deficit severo",IF(AND(C32>=3.5,C32<4),"Deficit moderado",IF(AND(C32>=4,C32<5),"Deficit leve",IF(AND(C32>=5,C32<=9),"Normal",IF(AND(C32>9,C32<=13),"Exceso",IF(AND(C32>13,C32<=17),"Obesidad I",IF(AND(C32>17,C32<=21),"Obesidad II","Obesidad III")))))))) -> #NUM! | F33: Muy buena | G33: >21 | H33: >18 | J33: IMC: Res 2465 de 2016 Ministerio de salud y proteccion social
B34: Masa libre de grasa kg | C34: =C8-C31 -> #NUM! | J34: Cintura/Estatura: Browning LM, Hsieh SD, Ashwell M. A systematic review of waist-to-height ratio as a screening tool for the prediction of cardiovascular disease and diabetes: 0·5 could be a suitable global boundary value. Nutr Res Rev. 2010;23(2):247-69. doi: 10.1017/S0954422410000144
B35: IMLG | C35: =C34/(C9*C9) -> #NUM! | J35: Cintura: Res 2465 de 2016 Ministerio de salud y proteccion social
B36: Clasificación | C36: =IF(C6="Hombre",IF(C35<17,"Malnutricion",IF(AND(C35>=17,C35<=21),"Adecuado","Muy buena")),IF(C35<15,"Malnutricion",IF(AND(C35>=15,C35<=18),"Adecuado","Muy buena"))) -> #NUM! | F36: En caso Malnutrición | J36: %Grasa: Davidson LE, Wang J, Thornton JC, Kaleem Z, Silva-Palacios F, Person RN, et al. Predicting fat percent by skinfolds in racial groups: Durnin and Womersley revisited. Medicine and science in sports and exercise. 2011; 43(3): 542-9
B37: %Grasa deseado | F37: %Grasa deseado | J37: Clasificación %Grasa: Consenso SEEDO 2000 para la evaluacion del sobrepeso y la obesidad y el establecimiento de criterios de intervencion terapeutica. Medicina clinica. 115 (15).
B38: Peso deseado %G kg | C38: =IF(C36="Malnutrición","Malnutrición",C34/(1-(C37/100))) -> #NUM! | F38: IMLG kg deseado | J38: Clasificación IMG: Kelly TL, Wilson KE, Heymsfield SB. Dual energy X-Ray absorptiometry body composition reference values from NHANES. PLoS One. 2009 Sep 15;4(9):e7038. doi: 10.1371/journal.pone.0007038.
B39: Distribucion Grasa | C39: =(C15+C16)/(C17+C14) -> #DIV/0! | E39: =(C15+C16)/(C17+C14) -> #DIV/0! | F39: MLG kg Adecuada | G39: =IF(C36="Malnutricion",G38*(C9*C9),"No aplica") -> #NUM! | J39: Clasificación IMLG: Cederholm, T., Jensen, G. L., Correia, M. I. T. D., Gonzalez, M. C., Fukushima, R., Higashiguchi, T., … Coats, A. (2018). GLIM criteria for the diagnosis of malnutrition – A consensus report from the global clinical nutrition community. Clinical Nutrition. doi:10.1016/j.clnu.2018.08.002
B40: Clasificación | C40: =IF(C39<1,"Acumulacion periferica",IF(C39=1,"Distribucion armonica","Acumulacion central")) -> #DIV/0! | F40: Peso deseado %G Kg | G40: =IF(C36="Malnutricion",G39/(1-(G37/100)),"No aplica") -> #NUM! | J40: Distribución de la grasa: Malina, R.M. (1996) Regional body composition: Age, sex and ethnic variation. In: Roche, A.F., Heymsfield, S.B. and Lohman, T.G., Eds., Human Body Composition, Human Kinetics, Champaign, 217-256.

Sheet Hoja1

Sheet Ev. Consumo
D3: EVALUACIÓN DE CONSUMO
B5: Tamaño de porción Aprox | D5: Grupo de alimentos | J5: Porciones | K5: Kcal | L5: Prot | M5: Grasa | N5: GS | O5: GM | P5: GP | Q5: COL | R5: CHOS | S5: FD | T5: Calcio (mg) | U5: P (mg) | V5: Fe (mg) | W5: Na (mg) | X5: K (mg) | Y5: Mg (mg) | Z5: Zn (mg) | AA5: Cu (mg) | AB5: Mn (mg) | AC5: Vit A (ER) | AD5: Tiamina (mg) | AE5: Riboflavina (mg) | AF5: Niacina (mg) | AG5: Ac, Pantotenico (mg) | AH5: Priridox. (mg) | AI5: Acido Folico (ug) | AJ5: Vit B12 (ug) | AK5: Vit C (mg)
B6: 200g | C6: 1 Vaso pequeño | D6: Leches enteras frescas y fermentadas | K6: =(L6*4)+(M6*9)+(R6*4) -> 139.1 | L6: 6.7 | M6: 6.7 | N6: 4.4 | O6: 1.95 | P6: 0.49 | Q6: 26 | R6: 13 | S6: 0 | T6: 236 | U6: 173 | V6: 0.2 | W6: 96 | X6: 330 | Y6: 25 | Z6: 0.89 | AA6: 0.03 | AB6: 0.01 | AC6: 73 | AD6: 0.08 | AE6: 0.34 | AF6: 0.3 | AG6: 0.67 | AH6: 0.08 | AI6: 10 | AJ6: 0.65 | AK6: 3
B7: 200g | C7: 1 Vaso pequeño | D7: Leches semidescremadas frescas y fermentadas | K7: =(L7*4)+(M7*9)+(R7*4) -> 94.5 | L7: 5.4 | M7: 2.1 | N7: 0.87 | O7: 0.54 | P7: 0.35 | Q7: 5 | R7: 13.5 | S7: 0.8 | T7: 153 | U7: 143 | V7: 0.4 | W7: 72 | X7: 268 | Y7: 25 | Z7: 1.24 | AA7: 0.06 | AB7: 0.11 | AC7: 76 | AD7: 0.12 | AE7: 0.25 | AF7: 0.2 | AG7: 0.41 | AH7: 0.06 | AI7: 8 | AJ7: 0.5 | AK7: 4
B8: 200g | C8: 1 Vaso pequeño | D8: Leches descremadas frescas y fermentadas | K8: =(L8*4)+(M8*9)+(R8*4) -> 82.3 | L8: 9 | M8: 0.7 | N8: 0.45 | O8: 0.18 | P8: 0.03 | Q8: 6 | R8: 10 | S8: 0 | T8: 256 | U8: 214 | V8: 0.1 | W8: 101 | X8: 340 | Y8: 24 | Z8: 1.05 | AA8: 0.02 | AB8: 0.01 | AC8: 89 | AD8: 0.08 | AE8: 0.33 | AF8: 0.2 | AG8: 0.79 | AH8: 0.08 | AI8: 14 | AJ8: 0.84 | AK8: 2
B9: 200g | C9: 1 Vaso pequeño | D9: Leches frescas y fermentadas enteras altas en calorías y azucares | K9: =(L9*4)+(M9*9)+(R9*4) -> 170.7 | L9: 6.4 | M9: 5.9 | N9: 3.8 | O9: 1.91 | P9: 0.63 | Q9: 22 | R9: 23 | S9: 0.4 | T9: 258 | U9: 169 | V9: 0.3 | W9: 115 | X9: 334 | Y9: 27 | Z9: 1.03 | AA9: 0.05 | AB9: 0.04 | AC9: 45 | AD9: 0.08 | AE9: 0.37 | AF9: 0.2 | AG9: 0.73 | AH9: 0.08 | AI9: 13 | AJ9: 0.76 | AK9: 3
B10: 60g | C10: 1/3 Vaso pequeño | D10: Leches frescas, fermentadas y productos lácteos menores de 2 años | K10: =(L10*4)+(M10*9)+(R10*4) -> 50.7 | L10: 2.9 | M10: 3.1 | N10: 2.01 | O10: 0.96 | P10: 0.18 | Q10: 12 | R10: 2.8 | S10: 0 | T10: 93 | U10: 62 | V10: 0.1 | W10: 57 | X10: 57 | Y10: 6 | Z10: 0.38 | AA10: 0.01 | AB10: 0 | AC10: 36 | AD10: 0.01 | AE10: 0.08 | AF10: 0.1 | AG10: 0.12 | AH10: 0.02 | AI10: 2 | AJ10: 0.2 | AK10: 0
B11: 100ml | C11: 1 toma | D11: Leche materna | K11: =(L11*4)+(M11*9)+(R11*4) -> 71.2 | L11: 1 | M11: 4.4 | N11: 2.01 | O11: 1.66 | P11: 0.5 | Q11: 14 | R11: 6.9 | S11: 0 | T11: 32 | U11: 14 | V11: 0 | W11: 17 | X11: 51 | Y11: 3 | Z11: 0.17 | AA11: 0.05 | AB11: 0.03 | AC11: 64 | AD11: 0.01 | AE11: 0.04 | AF11: 0.2 | AG11: 0.22 | AH11: 0.01 | AI11: 5 | AJ11: 0.05 | AK11: 5
B12: 30g | C12: 1 tajada/1 unidad mediana | D12: Sustitutos | K12: =(L12*4)+(M12*9)+(R12*4) -> 77.1 | L12: 5.8 | M12: 5.5 | N12: 2.91 | O12: 1.94 | P12: 0.41 | Q12: 40 | R12: 1.1 | S12: 0 | T12: 95 | U12: 85 | V12: 1.1 | W12: 211 | X12: 52 | Y12: 6 | Z12: 0.65 | AA12: 0.03 | AB12: 0.01 | AC12: 45 | AD12: 0.04 | AE12: 0.1 | AF12: 0.4 | AG12: 0.16 | AH12: 0.05 | AI12: 4 | AJ12: 0.72 | AK12: 0
B13: 30g | C13: 1 unidad | D13: Huevo menores de 2 años | K13: =(L13*4)+(M13*9)+(R13*4) -> 52.9 | L13: 4.5 | M13: 3.7 | N13: 1.15 | O13: 1.42 | P13: 0.49 | Q13: 180 | R13: 0.4 | S13: 0 | T13: 19 | U13: 64 | V13: 0.6 | W13: 46 | X13: 46 | Y13: 4 | Z13: 0.4 | AA13: 0.01 | AB13: 0.01 | AC13: 57 | AD13: 0.03 | AE13: 0.2 | AF13: 0 | AG13: 0.51 | AH13: 0.05 | AI13: 18 | AJ13: 0.43 | AK13: 0
B14: 100g | C14: 1/5 libra | D14: Carnes magras crudas y proteínas texturizada adultos y niños | K14: =(L14*4)+(M14*9)+(R14*4) -> 108.3 | L14: 19.1 | M14: 3.1 | N14: 0.92 | O14: 1.16 | P14: 0.53 | Q14: 50 | R14: 1 | S14: 0.3 | T14: 22 | U14: 191 | V14: 1.5 | W14: 72 | X14: 325 | Y14: 28 | Z14: 1.81 | AA14: 0.11 | AB14: 0.12 | AC14: 7 | AD14: 0.19 | AE14: 0.18 | AF14: 5.6 | AG14: 0.78 | AH14: 0.35 | AI14: 15 | AJ14: 2.39 | AK14: 1
B15: 25g | C15: 3 cucharas dulceras colmadas | D15: Carnes magras cocidas menores de 2 años | K15: =(L15*4)+(M15*9)+(R15*4) -> 49.2 | L15: 7.8 | M15: 2 | N15: 0.52 | O15: 0.84 | P15: 0.35 | Q15: 21 | R15: 0 | S15: 0 | T15: 7 | U15: 74 | V15: 0.4 | W15: 19 | X15: 108 | Y15: 8 | Z15: 0.55 | AA15: 0.04 | AB15: 0.09 | AC15: 5 | AD15: 0.1 | AE15: 0.07 | AF15: 1.9 | AG15: 0.33 | AH15: 0.09 | AI15: 2 | AJ15: 1 | AK15: 0
B16: 90g | C16: < 1/5 libra | D16: Carnes crudas altas en lípidos adultos y niños | K16: =(L16*4)+(M16*9)+(R16*4) -> 138.7 | L16: 15.6 | M16: 7.9 | N16: 2.51 | O16: 3.3 | P16: 1.25 | Q16: 137 | R16: 1.3 | S16: 0 | T16: 37 | U16: 186 | V16: 2.5 | W16: 101 | X16: 234 | Y16: 20 | Z16: 1.87 | AA16: 0.47 | AB16: 0.09 | AC16: 1515 | AD16: 0.07 | AE16: 0.53 | AF16: 4.4 | AG16: 1.67 | AH16: 0.27 | AI16: 87 | AJ16: 10.58 | AK16: 6
B17: 25g | C17: 3 cucharas dulceras colmadas | D17: Carnes cocidas altas en lípidos menores de 2 años | K17: =(L17*4)+(M17*9)+(R17*4) -> 46.8 | L17: 6.9 | M17: 2 | N17: 0.78 | O17: 0.86 | P17: 0.31 | Q17: 79 | R17: 0.3 | S17: 0 | T17: 3 | U17: 57 | V17: 3 | W17: 62 | X17: 55 | Y17: 6 | Z17: 1.21 | AA17: 0.25 | AB17: 0.04 | AC17: 620 | AD17: 0.02 | AE17: 0.29 | AF17: 1.1 | AG17: 0.55 | AH17: 0.09 | AI17: 39 | AJ17: 4.29 | AK17: 2
... B46: 3g | C46: 1 cuchara dulcera | D46: Promedio grasas menores de 2 años | K46: =(L46*4)+(M46*9)+(R46*4) -> 26.8 | L46: 0.2 | M46: 2.8 | N46: 0.81 | O46: 1.12 | P46: 0.76 | Q46: 2 | R46: 0.2 | S46: 0.1 | T46: 2 | U46: 3 | V46: 0 | W46: 3 | X46: 15 | Y46: 1 | Z46: 0.02 | AA46: 0.01 | AB46: 0.01 | AC46: 9 | AD46: 0 | AE46: 0.01 | AF46: 0.1 | AG46: 0.03 | AH46: 0.01 | AI46: 2 | AJ46: 0.01 | AK46: 0
B47: 1u | C47: 1 porción | D47: Suplemento (Introduzca manualmente los nutrientes por porción)
D50: Grupo de alimentos | J50: Porciones | K50: Kcal | L50: Prot | M50: Grasa | N50: GS | O50: GM | P50: GP | Q50: COL | R50: CHOS | S50: FD | T50: Calcio (mg) | U50: P (mg) | V50: Fe (mg) | W50: Na (mg) | X50: K (mg) | Y50: Mg (mg) | Z50: Zn (mg) | AA50: Cu (mg) | AB50: Mn (mg) | AC50: Vit A (ER) | AD50: Tiamina (mg) | AE50: Riboflavina (mg) | AF50: Niacina (mg) | AG50: Ac, Pantotenico (mg) | AH50: Priridox. (mg) | AI50: Acido Folico (ug) | AJ50: Vit B12 (ug) | AK50: Vit C (mg)
D51: Leches enteras frescas y fermentadas | J51: =J6 | K51: =(K6*J6) -> 0 | L51: =(L6*J6) -> 0 | M51: =(M6*J6) -> 0 | N51: =(N6*J6) -> 0 | O51: =(O6*J6) -> 0 | P51: =(P6*J6) -> 0 | Q51: =(Q6*J6) -> 0 | R51: =(R6*J6) -> 0 | S51: =(S6*J6) -> 0 | T51: =(T6*J6) -> 0 | U51: =(U6*J6) -> 0 | V51: =(V6*J6) -> 0 | W51: =(W6*J6) -> 0 | X51: =(X6*J6) -> 0 | Y51: =(Y6*J6) -> 0 | Z51: =(Z6*J6) -> 0 | AA51: =(AA6*J6) -> 0 | AB51: =(AB6*J6) -> 0 | AC51: =(AC6*J6) -> 0 | AD51: =(AD6*J6) -> 0 | AE51: =(AE6*J6) -> 0 | AF51: =(AF6*J6) -> 0 | AG51: =(AG6*J6) -> 0 | AH51: =(AH6*J6) -> 0 | AI51: =(AI6*J6) -> 0 | AJ51: =(AJ6*J6) -> 0 | AK51: =(AK6*J6) -> 0
D52: Leches semidescremadas frescas y fermentadas | J52: =J7 | K52: =(K7*J7) -> 0 | L52: =(L7*J7) -> 0 | M52: =(M7*J7) -> 0 | N52: =(N7*J7) -> 0 | O52: =(O7*J7) -> 0 | P52: =(P7*J7) -> 0 | Q52: =(Q7*J7) -> 0 | R52: =(R7*J7) -> 0 | S52: =(S7*J7) -> 0 | T52: =(T7*J7) -> 0 | U52: =(U7*J7) -> 0 | V52: =(V7*J7) -> 0 | W52: =(W7*J7) -> 0 | X52: =(X7*J7) -> 0 | Y52: =(Y7*J7) -> 0 | Z52: =(Z7*J7) -> 0 | AA52: =(AA7*J7) -> 0 | AB52: =(AB7*J7) -> 0 | AC52: =(AC7*J7) -> 0 | AD52: =(AD7*J7) -> 0 | AE52: =(AE7*J7) -> 0 | AF52: =(AF7*J7) -> 0 | AG52: =(AG7*J7) -> 0 | AH52: =(AH7*J7) -> 0 | AI52: =(AI7*J7) -> 0 | AJ52: =(AJ7*J7) -> 0 | AK52: =(AK7*J7) -> 0
D53: Leches descremadas frescas y fermentadas | J53: =J8 | K53: =(K8*J8) -> 0 | L53: =(L8*J8) -> 0 | M53: =(M8*J8) -> 0 | N53: =(N8*J8) -> 0 | O53: =(O8*J8) -> 0 | P53: =(P8*J8) -> 0 | Q53: =(Q8*J8) -> 0 | R53: =(R8*J8) -> 0 | S53: =(S8*J8) -> 0 | T53: =(T8*J8) -> 0 | U53: =(U8*J8) -> 0 | V53: =(V8*J8) -> 0 | W53: =(W8*J8) -> 0 | X53: =(X8*J8) -> 0 | Y53: =(Y8*J8) -> 0 | Z53: =(Z8*J8) -> 0 | AA53: =(AA8*J8) -> 0 | AB53: =(AB8*J8) -> 0 | AC53: =(AC8*J8) -> 0 | AD53: =(AD8*J8) -> 0 | AE53: =(AE8*J8) -> 0 | AF53: =(AF8*J8) -> 0 | AG53: =(AG8*J8) -> 0 | AH53: =(AH8*J8) -> 0 | AI53: =(AI8*J8) -> 0 | AJ53: =(AJ8*J8) -> 0 | AK53: =(AK8*J8) -> 0
D54: Leches frescas y fermentadas enteras altas en calorías y azucares | J54: =J9 | K54: =(K9*J9) -> 0 | L54: =(L9*J9) -> 0 | M54: =(M9*J9) -> 0 | N54: =(N9*J9) -> 0 | O54: =(O9*J9) -> 0 | P54: =(P9*J9) -> 0 | Q54: =(Q9*J9) -> 0 | R54: =(R9*J9) -> 0 | S54: =(S9*J9) -> 0 | T54: =(T9*J9) -> 0 | U54: =(U9*J9) -> 0 | V54: =(V9*J9) -> 0 | W54: =(W9*J9) -> 0 | X54: =(X9*J9) -> 0 | Y54: =(Y9*J9) -> 0 | Z54: =(Z9*J9) -> 0 | AA54: =(AA9*J9) -> 0 | AB54: =(AB9*J9) -> 0 | AC54: =(AC9*J9) -> 0 | AD54: =(AD9*J9) -> 0 | AE54: =(AE9*J9) -> 0 | AF54: =(AF9*J9) -> 0 | AG54: =(AG9*J9) -> 0 | AH54: =(AH9*J9) -> 0 | AI54: =(AI9*J9) -> 0 | AJ54: =(AJ9*J9) -> 0 | AK54: =(AK9*J9) -> 0
D55: Leches frescas, fermentadas y productos lácteos menores de 2 años | J55: =J10 | K55: =(K10*J10) -> 0 | L55: =(L10*J10) -> 0 | M55: =(M10*J10) -> 0 | N55: =(N10*J10) -> 0 | O55: =(O10*J10) -> 0 | P55: =(P10*J10) -> 0 | Q55: =(Q10*J10) -> 0 | R55: =(R10*J10) -> 0 | S55: =(S10*J10) -> 0 | T55: =(T10*J10) -> 0 | U55: =(U10*J10) -> 0 | V55: =(V10*J10) -> 0 | W55: =(W10*J10) -> 0 | X55: =(X10*J10) -> 0 | Y55: =(Y10*J10) -> 0 | Z55: =(Z10*J10) -> 0 | AA55: =(AA10*J10) -> 0 | AB55: =(AB10*J10) -> 0 | AC55: =(AC10*J10) -> 0 | AD55: =(AD10*J10) -> 0 | AE55: =(AE10*J10) -> 0 | AF55: =(AF10*J10) -> 0 | AG55: =(AG10*J10) -> 0 | AH55: =(AH10*J10) -> 0 | AI55: =(AI10*J10) -> 0 | AJ55: =(AJ10*J10) -> 0 | AK55: =(AK10*J10) -> 0
D56: Leche materna | J56: =J11 | K56: =(K11*J11) -> 0 | L56: =(L11*J11) -> 0 | M56: =(M11*J11) -> 0 | N56: =(N11*J11) -> 0 | O56: =(O11*J11) -> 0 | P56: =(P11*J11) -> 0 | Q56: =(Q11*J11) -> 0 | R56: =(R11*J11) -> 0 | S56: =(S11*J11) -> 0 | T56: =(T11*J11) -> 0 | U56: =(U11*J11) -> 0 | V56: =(V11*J11) -> 0 | W56: =(W11*J11) -> 0 | X56: =(X11*J11) -> 0 | Y56: =(Y11*J11) -> 0 | Z56: =(Z11*J11) -> 0 | AA56: =(AA11*J11) -> 0 | AB56: =(AB11*J11) -> 0 | AC56: =(AC11*J11) -> 0 | AD56: =(AD11*J11) -> 0 | AE56: =(AE11*J11) -> 0 | AF56: =(AF11*J11) -> 0 | AG56: =(AG11*J11) -> 0 | AH56: =(AH11*J11) -> 0 | AI56: =(AI11*J11) -> 0 | AJ56: =(AJ11*J11) -> 0 | AK56: =(AK11*J11) -> 0
D57: Sustitutos | J57: =J12 | K57: =(K12*J12) -> 0 | L57: =(L12*J12) -> 0 | M57: =(M12*J12) -> 0 | N57: =(N12*J12) -> 0 | O57: =(O12*J12) -> 0 | P57: =(P12*J12) -> 0 | Q57: =(Q12*J12) -> 0 | R57: =(R12*J12) -> 0 | S57: =(S12*J12) -> 0 | T57: =(T12*J12) -> 0 | U57: =(U12*J12) -> 0 | V57: =(V12*J12) -> 0 | W57: =(W12*J12) -> 0 | X57: =(X12*J12) -> 0 | Y57: =(Y12*J12) -> 0 | Z57: =(Z12*J12) -> 0 | AA57: =(AA12*J12) -> 0 | AB57: =(AB12*J12) -> 0 | AC57: =(AC12*J12) -> 0 | AD57: =(AD12*J12) -> 0 | AE57: =(AE12*J12) -> 0 | AF57: =(AF12*J12) -> 0 | AG57: =(AG12*J12) -> 0 | AH57: =(AH12*J12) -> 0 | AI57: =(AI12*J12) -> 0 | AJ57: =(AJ12*J12) -> 0 | AK57: =(AK12*J12) -> 0
D58: Huevo menores de 2 años | J58: =J13 | K58: =(K13*J13) -> 0 | L58: =(L13*J13) -> 0 | M58: =(M13*J13) -> 0 | N58: =(N13*J13) -> 0 | O58: =(O13*J13) -> 0 | P58: =(P13*J13) -> 0 | Q58: =(Q13*J13) -> 0 | R58: =(R13*J13) -> 0 | S58: =(S13*J13) -> 0 | T58: =(T13*J13) -> 0 | U58: =(U13*J13) -> 0 | V58: =(V13*J13) -> 0 | W58: =(W13*J13) -> 0 | X58: =(X13*J13) -> 0 | Y58: =(Y13*J13) -> 0 | Z58: =(Z13*J13) -> 0 | AA58: =(AA13*J13) -> 0 | AB58: =(AB13*J13) -> 0 | AC58: =(AC13*J13) -> 0 | AD58: =(AD13*J13) -> 0 | AE58: =(AE13*J13) -> 0 | AF58: =(AF13*J13) -> 0 | AG58: =(AG13*J13) -> 0 | AH58: =(AH13*J13) -> 0 | AI58: =(AI13*J13) -> 0 | AJ58: =(AJ13*J13) -> 0 | AK58: =(AK13*J13) -> 0
D59: Carnes magras crudas y proteínas texturizada adultos y niños | J59: =J14 | K59: =(K14*J14) -> 0 | L59: =(L14*J14) -> 0 | M59: =(M14*J14) -> 0 | N59: =(N14*J14) -> 0 | O59: =(O14*J14) -> 0 | P59: =(P14*J14) -> 0 | Q59: =(Q14*J14) -> 0 | R59: =(R14*J14) -> 0 | S59: =(S14*J14) -> 0 | T59: =(T14*J14) -> 0 | U59: =(U14*J14) -> 0 | V59: =(V14*J14) -> 0 | W59: =(W14*J14) -> 0 | X59: =(X14*J14) -> 0 | Y59: =(Y14*J14) -> 0 | Z59: =(Z14*J14) -> 0 | AA59: =(AA14*J14) -> 0 | AB59: =(AB14*J14) -> 0 | AC59: =(AC14*J14) -> 0 | AD59: =(AD14*J14) -> 0 | AE59: =(AE14*J14) -> 0 | AF59: =(AF14*J14) -> 0 | AG59: =(AG14*J14) -> 0 | AH59: =(AH14*J14) -> 0 | AI59: =(AI14*J14) -> 0 | AJ59: =(AJ14*J14) -> 0 | AK59: =(AK14*J14) -> 0
D60: Carnes magras cocidas menores de 2 años | J60: =J15 | K60: =(K15*J15) -> 0 | L60: =(L15*J15) -> 0 | M60: =(M15*J15) -> 0 | N60: =(N15*J15) -> 0 | O60: =(O15*J15) -> 0 | P60: =(P15*J15) -> 0 | Q60: =(Q15*J15) -> 0 | R60: =(R15*J15) -> 0 | S60: =(S15*J15) -> 0 | T60: =(T15*J15) -> 0 | U60: =(U15*J15) -> 0 | V60: =(V15*J15) -> 0 | W60: =(W15*J15) -> 0 | X60: =(X15*J15) -> 0 | Y60: =(Y15*J15) -> 0 | Z60: =(Z15*J15) -> 0 | AA60: =(AA15*J15) -> 0 | AB60: =(AB15*J15) -> 0 | AC60: =(AC15*J15) -> 0 | AD60: =(AD15*J15) -> 0 | AE60: =(AE15*J15) -> 0 | AF60: =(AF15*J15) -> 0 | AG60: =(AG15*J15) -> 0 | AH60: =(AH15*J15) -> 0 | AI60: =(AI15*J15) -> 0 | AJ60: =(AJ15*J15) -> 0 | AK60: =(AK15*J15) -> 0
D61: Carnes crudas altas en lípidos adultos y niños | J61: =J16 | K61: =(K16*J16) -> 0 | L61: =(L16*J16) -> 0 | M61: =(M16*J16) -> 0 | N61: =(N16*J16) -> 0 | O61: =(O16*J16) -> 0 | P61: =(P16*J16) -> 0 | Q61: =(Q16*J16) -> 0 | R61: =(R16*J16) -> 0 | S61: =(S16*J16) -> 0 | T61: =(T16*J16) -> 0 | U61: =(U16*J16) -> 0 | V61: =(V16*J16) -> 0 | W61: =(W16*J16) -> 0 | X61: =(X16*J16) -> 0 | Y61: =(Y16*J16) -> 0 | Z61: =(Z16*J16) -> 0 | AA61: =(AA16*J16) -> 0 | AB61: =(AB16*J16) -> 0 | AC61: =(AC16*J16) -> 0 | AD61: =(AD16*J16) -> 0 | AE61: =(AE16*J16) -> 0 | AF61: =(AF16*J16) -> 0 | AG61: =(AG16*J16) -> 0 | AH61: =(AH16*J16) -> 0 | AI61: =(AI16*J16) -> 0 | AJ61: =(AJ16*J16) -> 0 | AK61: =(AK16*J16) -> 0
D62: Carnes cocidas altas en lípidos menores de 2 años | J62: =J17 | K62: =(K17*J17) -> 0 | L62: =(L17*J17) -> 0 | M62: =(M17*J17) -> 0 | N62: =(N17*J17) -> 0 | O62: =(O17*J17) -> 0 | P62: =(P17*J17) -> 0 | Q62: =(Q17*J17) -> 0 | R62: =(R17*J17) -> 0 | S62: =(S17*J17) -> 0 | T62: =(T17*J17) -> 0 | U62: =(U17*J17) -> 0 | V62: =(V17*J17) -> 0 | W62: =(W17*J17) -> 0 | X62: =(X17*J17) -> 0 | Y62: =(Y17*J17) -> 0 | Z62: =(Z17*J17) -> 0 | AA62: =(AA17*J17) -> 0 | AB62: =(AB17*J17) -> 0 | AC62: =(AC17*J17) -> 0 | AD62: =(AD17*J17) -> 0 | AE62: =(AE17*J17) -> 0 | AF62: =(AF17*J17) -> 0 | AG62: =(AG17*J17) -> 0 | AH62: =(AH17*J17) -> 0 | AI62: =(AI17*J17) -> 0 | AJ62: =(AJ17*J17) -> 0 | AK62: =(AK17*J17) -> 0
... D92: suplemento | J92: =J47 | K92: =(K47*J47) -> 0 | L92: =(L47*J47) -> 0 | M92: =(M47*J47) -> 0 | N92: =(N47*J47) -> 0 | O92: =(O47*J47) -> 0 | P92: =(P47*J47) -> 0 | Q92: =(Q47*J47) -> 0 | R92: =(R47*J47) -> 0 | S92: =(S47*J47) -> 0 | T92: =(T47*J47) -> 0 | U92: =(U47*J47) -> 0 | V92: =(V47*J47) -> 0 | W92: =(W47*J47) -> 0 | X92: =(X47*J47) -> 0 | Y92: =(Y47*J47) -> 0 | Z92: =(Z47*J47) -> 0 | AA92: =(AA47*J47) -> 0 | AB92: =(AB47*J47) -> 0 | AC92: =(AC47*J47) -> 0 | AD92: =(AD47*J47) -> 0 | AE92: =(AE47*J47) -> 0 | AF92: =(AF47*J47) -> 0 | AG92: =(AG47*J47) -> 0 | AH92: =(AH47*J47) -> 0 | AI92: =(AI47*J47) -> 0 | AJ92: =(AJ47*J47) -> 0 | AK92: =(AK47*J47) -> 0
B93: TOTAL | K93: =SUM(K51:K92) -> 0 | L93: =SUM(L51:L92) -> 0 | M93: =SUM(M51:M92) -> 0 | N93: =SUM(N51:N92) -> 0 | O93: =SUM(O51:O92) -> 0 | P93: =SUM(P51:P92) -> 0 | Q93: =SUM(Q51:Q92) -> 0 | R93: =SUM(R51:R92) -> 0 | ... AK93: =SUM(AK51:AK92) -> 0
J94: REQUERIDO | K94: =D1 | L94: =E1 | M94: =F1 | N94: =G1 | O94: =H1 | P94: =I1 | Q94: =J1 | R94: =K1 | S94: =L1
J95: %ADECUACI | K95: =((100/K94)*K93) -> #DIV/0! | L95: =((100/L94)*L93) -> #DIV/0! | M95: =((100/M94)*M93) -> #DIV/0! | N95: =((100/N94)*N93) -> #DIV/0! | O95: =((100/O94)*O93) -> #DIV/0! | P95: =((100/P94)*P93) -> #DIV/0! | Q95: =((100/Q94)*Q93) -> #DIV/0! | R95: =((100/R94)*R93) -> #DIV/0! | ... AK95: =((100/AK94)*AK93) -> #DIV/0!
K96: Kcal | L96: Prot | M96: Grasa | N96: GS | O96: GM | P96: GP | Q96: COL | R96: CHOS | S96: FD | T96: Calcio (mg) | U96: P (mg) | V96: Fe (mg) | W96: Na (mg) | X96: K (mg) | Y96: Mg (mg) | Z96: Zn (mg) | AA96: Cu (mg) | AB96: Mn (mg) | AC96: Vit A (ER) | AD96: Tiamina (mg) | AE96: Riboflavina (mg) | AF96: Niacina (mg) | AG96: Ac, Pantotenico (mg) | AH96: Priridox. (mg) | AI96: Acido Folico (ug) | AJ96: Vit B12 (ug) | AK96: Vit C (mg)
D98: FÓRMULA SINTÉTICA DE CONSUMO
K100: FÓRMULA SINTÉTICA DE CONSUMO | Q100: Recomendaciones RIEN
K101: Nutrientes | L101: Gramos | M101: Calorías | N101: % AMDR | O101: Otros | Q101: Proteinas | S101: 14-20%
K102: Proteínas | L102: =(L93) -> 0 | M102: =(L102*4) -> 0 | N102: =((100/M114)*M102) -> #DIV/0! | O102: g AVB | P102: =SUM(L51:L62) -> 0 | Q102: Prote g/kg/peso | S102: 1,11-1,16
O103: % AVB | P103: =((100/L102)*P102) -> #DIV/0! | Q103: Prote AVB | S103: 60-80%
O104: g/kg/peso | P104: =(L102/L115) -> #DIV/0! | Q104: Carbohidratos totales | S104: 50-65%
K105: Grasas | L105: =(M93) -> 0 | M105: =(L105*9) -> 0 | N105: =((100/M114)*M105) -> #DIV/0! | O105: g GS | P105: =(N93) -> 0 | Q105: Carbohidratos simples | S105: <10%
O106: %AMDR GS | P106: =((100/M114)*(P105*9)) -> #DIV/0! | Q106: Grasa total | S106: 20-35%
O107: g GM | P107: =(O93) -> 0 | Q107: G saturada | S107: <10%
O108: %AMDR GM | P108: =((100/M114)*(P107*9)) -> #DIV/0! | Q108: G mono | S108: GS-GM
O109: g GP | P109: =(P93) -> 0 | Q109: G poli | S109: 5-10%
O110: %AMDR GP | P110: =((100/M114)*(P109*9)) -> #DIV/0! | Q110: G trans | S110: <1%
O111: Colesterol | P111: =(Q93) -> 0 | Q111: Colesterol | S111: <300mg
K112: CHOs | L112: =(R93) -> 0 | M112: =(L112*4) -> 0 | N112: =((100/M114)*M112) -> #DIV/0! | O112: g Concent | P112: =SUM(R81:R82) -> 0 | Q112: Colesterol enf.card | S112: <200mg
O113: %AMDR | P113: =((100/M114)*(P112*4)) -> #DIV/0! | Q113: Fibra | S113: 14/1000cal
K114: Total: | M114: =SUM(M102:M113) -> 0 | N114: =SUM(N102:N113) -> #DIV/0! | O114: Fibra | P114: =S93 -> 0 | Q114: Sodio | S114: <2300mg
K115: Kg Ref

Sheet Adulto
B3: REQUERIMIENTO ENERGÉTICO Y PESO SALUDABLE
B5: PESO SALUDABLE IMC | E5: TMR FAO/Schofield | H5: ACTIVIDAD FISICA | L5: REQUERIMIENTO DRI | O5: FACTOR ACTIVIDAD FISICA PAL
B6: Peso kg | C6: 63 | E6: Peso Ref | F6: 75 | H6: Sedentario | I6: 1.53 | J6: (1,4-1,69) | L6: Edad | P6: Hombres | Q6: Mujeres
B7: Talla m | C7: 1.73 | E7: TMR HOMBRES | H7: Moderado | I7: 1.76 | J7: (1,7-1,99) | L7: Peso kg | O7: Sedentario | P7: 1 | Q7: 1
B8: IMC | C8: =(C6/(C7*C7)) -> 21.049818 | E8: 18-30 años | F8: =((15.057*F6)+692.2) -> 1821.475 | H8: Vigoroso | I8: 2.25 | J8: (2,0-2,4) | L8: Talla m | O8: Poco activo | P8: 1.11 | Q8: 1.12
B9: IMC deseado | C9: 25 | E9: 31-60 años | F9: =((11.472*F6)+873.1) -> 1733.5 | L9: Factor act | O9: Activo | P9: 1.25 | Q9: 1.27
B10: Peso saludable IMC 25-30 | E10: >60 años | F10: =((11.711*F6)+587.7) -> 1466.025 | H10: REQUERIMIENTO | L10: HOMBRES | O10: Muy activo | P10: 1.48 | Q10: 1.45
B11: PS | C11: =(C9*(C7*C7)) -> 74.8225 | E11: TMR MUJERES | H11: TMR | I11: 1821 | L11: RDE | M11: =662-(9.53*M6)+(M9*((15.91*M7)+(539.6*M8))) -> 662
B12: Peso ajustado IMC >30 | E12: 18-30 años | F12: =((14.818*F6)+486.6) -> 1597.95 | H12: ACT FIS | I12: 1.5 | L12: MUJERES
B13: PA | C13: =(C11+(0.25*(C6-C11))) -> 71.866875 | E13: 31-60 años | F13: =((8.126*F6)+845.6) -> 1455.05 | H13: Calorias | I13: =(I11*I12) -> 2731.5 | L13: RDE | M13: =354-(6.91*M6)+(M9*((9.36*M7)+(726*M8))) -> 354
E14: >60 años | F14: =((9.082*F6)+658.5) -> 1339.65
B16: FÓRMULA SINTÉTICA DE CONSUMO Y PLANEADA
B18: FÓRMULA SINTÉTICA DE CONSUMO | I18: FÓRMULA SINTÉTICA PLANEADA | P18: Recomendaciones RIEN
B19: Nutrientes | C19: Gramos | D19: Calorias | E19: % AMDR | F19: Otros | I19: Nutrientes | J19: Gramos | K19: Calorías | L19: % AMDR | M19: Otros | P19: Proteínas | R19: 14-20% AMDR
B20: Proteínas | C20: ='Ev. Consumo'!L102 -> 0 | D20: =(C20*4) -> 0 | E20: =((100/D32)*D20) -> #DIV/0! | F20: g AVB | G20: ='Ev. Consumo'!P102 -> 0 | I20: Proteínas | J20: =(N22*J33) -> 127.5 | K20: =(J20*4) -> 510 | L20: =((100/K32)*K20) -> 18.67106 | M20: g AVB | N20: =((N21/100)*J20) -> 89.25 | P20: Prote g/kg/peso | R20: 1,11-1,16
F21: % AVB | G21: =((100/C20)*G20) -> #DIV/0! | M21: % AVB | N21: 70 | P21: Prote AVB | R21: 60-80%
F22: g/kg/peso | G22: =(C20/C33) -> #DIV/0! | M22: g/kg/peso | N22: 1.7 | P22: CHOs totales | R22: 50-65%
B23: Grasas | C23: ='Ev. Consumo'!L105 -> 0 | D23: =(C23*9) -> 0 | E23: =((100/D32)*D23) -> #DIV/0! | F23: g GS | G23: ='Ev. Consumo'!P105 -> 0 | I23: Grasas | J23: =(K23/9) -> 75.875 | K23: =((K32/100)*L23) -> 682.875 | L23: 25 | M23: g GS | N23: =(((K32/100)*N24)/9) -> 30.35 | P23: CHOs simples | R23: <10%
F24: %AMDR GS | G24: =((100/D32)*(G23*9)) -> #DIV/0! | M24: %AMDR GS | N24: 10 | P24: Grasa total 27,5 | R24: 20-35% AMDR
F25: g GM | G25: ='Ev. Consumo'!P107 -> 0 | M25: g GM | N25: =(((K32/100)*N26)/9) -> 15.175 | P25: G saturada | R25: <10%
F26: %AMDR GM | G26: =((100/D32)*(G25*9)) -> #DIV/0! | M26: %AMDR GM | N26: =(L23-N24)-N28 -> 5 | P26: G poli | R26: 5-10%
F27: g GP | G27: ='Ev. Consumo'!P109 -> 0 | M27: g GP | N27: =(((K32/100)*N28)/9) -> 30.35 | P27: G mono | R27: GS-GM
F28: %AMDR GP | G28: =((100/D32)*(G27*9)) -> #DIV/0! | M28: %AMDR GP | N28: 10 | P28: G trans | R28: <1%
F29: Colesterol | G29: ='Ev. Consumo'!P111 -> 0 | M29: Colesterol | N29: 200 | P29: Colesterol | R29: <300mg
B30: CHOs | C30: ='Ev. Consumo'!L112 -> 0 | D30: =(C30*4) -> 0 | E30: =((100/D32)*D30) -> #DIV/0! | F30: g Concent | G30: ='Ev. Consumo'!P112 -> 0 | I30: CHOs | J30: =(K30/4) -> 384.65625 | K30: =((K32/100)*L30) -> 1538.625 | L30: =(100-L33) -> 56.32894 | M30: g Concent | N30: =(((K32/100)*N31)/4) -> 184.37625 | P30: Colesterol enf.card | R30: <200mg
F31: %AMDR | G31: =((100/D32)*(G30*4)) -> #DIV/0! | M31: %AMDR | N31: 27 | P31: Fibra | R31: 14g/1000cal
B32: Total: | D32: =SUM(D20:D31) -> 0 | E32: =SUM(E20:E31) -> #DIV/0! | F32: Fibra | G32: ='Ev. Consumo'!P114 -> 0 | I32: Total: | K32: =I13 -> 2731.5 | L32: =SUM(L20:L31) -> 100 | M32: Fibra | N32: 14 | P32: Sodio | R32: <2300mg
B33: Kg Ref | I33: Kg Ref | J33: =F6 -> 75 | K33: =SUM(K20:K32) -> 5463 | L33: =SUM(L20:L29) -> 43.67106 | P33: Sodio hipertensos | R33: <1500mg
B35: REQUERIMIENTO FINAL
B37: Kcal | C37: Prot | D37: Grasa | E37: GS | F37: GM | G37: GP | H37: COL | I37: CHOS | J37: Fibra
B38: =K32 -> 2731.5 | C38: =J20 -> 127.5 | D38: =J23 -> 75.875 | E38: =N23 -> 30.35 | F38: =N25 -> 15.175 | G38: =N27 -> 30.35 | H38: =N29 -> 200 | I38: =J30 -> 384.65625 | J38: =N32 -> 14
B40: FÓRMULA SINTÉTICA DESARROLLADA
B42: Grupo de alimentos | H42: Porciones | I42: Kcal | J42: Prot | K42: Grasa | L42: GS | M42: GM | N42: GP | O42: COL | P42: CHOS | Q42: FD | R42: Calcio (mg) | S42: P (mg) | T42: Fe (mg) | U42: Na (mg) | V42: K (mg) | W42: Mg (mg) | X42: Zn (mg) | Y42: Cu (mg) | Z42: Mn (mg) | AA42: Vit A (ER) | AB42: Tiamina (mg) | AC42: Riboflavina (mg) | AD42: Niacina (mg) | AE42: Ac, Pantotenico (mg) | AF42: Priridox. (mg) | AG42: Acido Folico (ug) | AH42: Vit B12 (ug) | AI42: Vit C (mg)
B43: Leches enteras frescas y fermentadas | H43: 3 | I43: =(J43*4)+(K43*9)+(P43*4) -> 139.1 | J43: 6.7 | K43: 6.7 | L43: 4.4 | M43: 1.95 | N43: 0.49 | O43: 26 | P43: 13 | Q43: 0 | R43: 236 | S43: 173 | T43: 0.2 | U43: 96 | V43: 330 | W43: 25 | X43: 0.89 | Y43: 0.03 | Z43: 0.01 | AA43: 73 | AB43: 0.08 | AC43: 0.34 | AD43: 0.3 | AE43: 0.67 | AF43: 0.08 | AG43: 10 | AH43: 0.65 | AI43: 3
B44: Leches semidescremadas frescas y fermentadas | I44: =(J44*4)+(K44*9)+(P44*4) -> 94.5 | J44: 5.4 | K44: 2.1 | L44: 0.87 | M44: 0.54 | N44: 0.35 | O44: 5 | P44: 13.5 | Q44: 0.8 | R44: 153 | S44: 143 | T44: 0.4 | U44: 72 | V44: 268 | W44: 25 | X44: 1.24 | Y44: 0.06 | Z44: 0.11 | AA44: 76 | AB44: 0.12 | AC44: 0.25 | AD44: 0.2 | AE44: 0.41 | AF44: 0.06 | AG44: 8 | AH44: 0.5 | AI44: 4
B45: Leches descremadas frescas y fermentadas | I45: =(J45*4)+(K45*9)+(P45*4) -> 82.3 | J45: 9 | K45: 0.7 | L45: 0.45 | M45: 0.18 | N45: 0.03 | O45: 6 | P45: 10 | Q45: 0 | R45: 256 | S45: 214 | T45: 0.1 | U45: 101 | V45: 340 | W45: 24 | X45: 1.05 | Y45: 0.02 | Z45: 0.01 | AA45: 89 | AB45: 0.08 | AC45: 0.33 | AD45: 0.2 | AE45: 0.79 | AF45: 0.08 | AG45: 14 | AH45: 0.84 | AI45: 2
B46: Leches frescas y fermentadas enteras altas en calorías y azucares | I46: =(J46*4)+(K46*9)+(P46*4) -> 170.7 | J46: 6.4 | K46: 5.9 | L46: 3.8 | M46: 1.91 | N46: 0.63 | O46: 22 | P46: 23 | Q46: 0.4 | R46: 258 | S46: 169 | T46: 0.3 | U46: 115 | V46: 334 | W46: 27 | X46: 1.03 | Y46: 0.05 | Z46: 0.04 | AA46: 45 | AB46: 0.08 | AC46: 0.37 | AD46: 0.2 | AE46: 0.73 | AF46: 0.08 | AG46: 13 | AH46: 0.76 | AI46: 3
B47: Sustitutos | H47: 4 | I47: =(J47*4)+(K47*9)+(P47*4) -> 77.1 | J47: 5.8 | K47: 5.5 | L47: 2.91 | M47: 1.94 | N47: 0.41 | O47: 40 | P47: 1.1 | Q47: 0 | R47: 95 | S47: 85 | T47: 1.1 | U47: 211 | V47: 52 | W47: 6 | X47: 0.65 | Y47: 0.03 | Z47: 0.01 | AA47: 45 | AB47: 0.04 | AC47: 0.1 | AD47: 0.4 | AE47: 0.16 | AF47: 0.05 | AG47: 4 | AH47: 0.72 | AI47: 0
B48: Carnes magras crudas y proteínas texturizada | H48: 3 | I48: =(J48*4)+(K48*9)+(P48*4) -> 108.3 | J48: 19.1 | K48: 3.1 | L48: 0.92 | M48: 1.16 | N48: 0.53 | O48: 50 | P48: 1 | Q48: 0.3 | R48: 22 | S48: 191 | T48: 1.5 | U48: 72 | V48: 325 | W48: 28 | X48: 1.81 | Y48: 0.11 | Z48: 0.12 | AA48: 7 | AB48: 0.19 | AC48: 0.18 | AD48: 5.6 | AE48: 0.78 | AF48: 0.35 | AG48: 15 | AH48: 2.39 | AI48: 1
B49: Carnes crudas altas en lípidos | I49: =(J49*4)+(K49*9)+(P49*4) -> 138.7 | J49: 15.6 | K49: 7.9 | L49: 2.51 | M49: 3.3 | N49: 1.25 | O49: 137 | P49: 1.3 | Q49: 0 | R49: 37 | S49: 186 | T49: 2.5 | U49: 101 | V49: 234 | W49: 20 | X49: 1.87 | Y49: 0.47 | Z49: 0.09 | AA49: 1515 | AB49: 0.07 | AC49: 0.53 | AD49: 4.4 | AE49: 1.67 | AF49: 0.27 | AG49: 87 | AH49: 10.58 | AI49: 6
B50: Leguminosas adultos | H50: 3 | I50: =(J50*4)+(K50*9)+(P50*4) -> 158.1 | J50: 9.8 | K50: 1.7 | L50: 0.25 | M50: 0.32 | N50: 0.94 | O50: 0 | P50: 25.9 | Q50: 7.9 | R50: 50 | S50: 167 | T50: 3.1 | U50: 10 | V50: 534 | W50: 62 | X50: 1.22 | Y50: 0.28 | Z50: 0.6 | AA50: 10 | AB50: 0.2 | AC50: 0.09 | AD50: 0.9 | AE50: 0.42 | AF50: 0.16 | AG50: 142 | AH50: 0 | AI50: 4
B51: Cereales adultos | H51: 4 | I51: =(J51*4)+(K51*9)+(P51*4) -> 93.8 | J51: 2.5 | K51: 1 | L51: 0.24 | M51: 0.32 | N51: 0.33 | O51: 1 | P51: 18.7 | Q51: 1.2 | R51: 19 | S51: 47 | T51: 0.9 | U51: 82 | V51: 53 | W51: 13 | X51: 0.42 | Y51: 0.05 | Z51: 0.24 | AA51: 22 | AB51: 0.11 | AC51: 0.09 | AD51: 1.1 | AE51: 0.15 | AF51: 0.08 | AG51: 38 | AH51: 0 | AI51: 2
B52: Raíces, tubérculos y plátanos adultos | I52: =(J52*4)+(K52*9)+(P52*4) -> 95.7 | J52: 1.4 | K52: 0.1 | L52: 0.05 | M52: 0.01 | N52: 0.06 | O52: 0 | P52: 22.3 | Q52: 1.9 | R52: 11 | S52: 40 | T52: 0.5 | U52: 10 | V52: 376 | W52: 20 | X52: 0.23 | Y52: 0.13 | Z52: 0.25 | AA52: 156 | AB52: 0.05 | AC52: 0.04 | AD52: 0.9 | AE52: 0.29 | AF52: 0.21 | AG52: 13 | AH52: 0 | AI52: 28
B53: Promedio "Harinas" adultos | I53: =(J53*4)+(K53*9)+(P53*4) -> 95.4 | J53: 2 | K53: 0.6 | L53: 0.14 | M53: 0.16 | N53: 0.19 | O53: 0 | P53: 20.5 | Q53: 1.5 | R53: 15 | S53: 43 | T53: 0.7 | U53: 46 | V53: 214 | W53: 17 | X53: 0.33 | Y53: 0.09 | Z53: 0.24 | AA53: 89 | AB53: 0.08 | AC53: 0.07 | AD53: 1 | AE53: 0.22 | AF53: 0.15 | AG53: 26 | AH53: 0 | AI53: 15
B54: Verduras y hortalizas adultos y niños | H54: 5 | I54: =(J54*4)+(K54*9)+(P54*4) -> 29.5 | J54: 1.2 | K54: 0.3 | L54: 0.05 | M54: 0.03 | N54: 0.13 | O54: 0 | P54: 5.5 | Q54: 1.7 | R54: 15 | S54: 32 | T54: 0.7 | U54: 68 | V54: 187 | W54: 12 | X54: 0.29 | Y54: 0.1 | Z54: 0.16 | AA54: 136 | AB54: 0.05 | AC54: 0.06 | AD54: 0.8 | AE54: 0.37 | AF54: 0.09 | AG54: 23 | AH54: 0 | AI54: 19
B55: Frutas adultos y niños | H55: 2 | I55: =(J55*4)+(K55*9)+(P55*4) -> 59.9 | J55: 1 | K55: 0.3 | L55: 0.06 | M55: 0.09 | N55: 0.11 | O55: 0 | P55: 13.3 | Q55: 2.6 | R55: 21 | S55: 24 | T55: 0.5 | U55: 4 | V55: 244 | W55: 19 | X55: 0.14 | Y55: 0.07 | Z55: 0.17 | AA55: 74 | AB55: 0.06 | AC55: 0.06 | AD55: 0.9 | AE55: 0.27 | AF55: 0.1 | AG55: 20 | AH55: 0 | AI55: 52
B56: Nueces adultos y niños | H56: 2 | I56: =(J56*4)+(K56*9)+(P56*4) -> 56.4 | J56: 1.3 | K56: 4.8 | L56: 1.15 | M56: 2.44 | N56: 0.99 | O56: 0 | P56: 2 | Q56: 0.7 | R56: 8 | S56: 34 | T56: 0.3 | U56: 6 | V56: 55 | W56: 16 | X56: 0.28 | Y56: 0.1 | Z56: 0.18 | AA56: 1 | AB56: 0.03 | AC56: 0.02 | AD56: 0.2 | AE56: 0.08 | AF56: 0.02 | AG56: 5 | AH56: 0 | AI56: 0
B57: Semillas adultos y niños | I57: =(J57*4)+(K57*9)+(P57*4) -> 58.5 | J57: 2.3 | K57: 4.1 | L57: 0.5 | M57: 0.91 | N57: 2.48 | O57: 0 | P57: 3.1 | Q57: 2.1 | R57: 50 | S57: 74 | T57: 0.9 | U57: 2 | V57: 78 | W57: 37 | X57: 0.58 | Y57: 0.15 | Z57: 0.35 | AA57: 1 | AB57: 0.07 | AC57: 0.02 | AD57: 0.3 | AE57: 0.15 | AF57: 0.06 | AG57: 18 | AH57: 0 | AI57: 0
B58: Azucares y dulces adultos | H58: 3 | I58: =(J58*4)+(K58*9)+(P58*4) -> 89.9 | J58: 0.9 | K58: 1.1 | L58: 0.63 | M58: 0.33 | N58: 0.07 | O58: 2 | P58: 19.1 | Q58: 0.5 | R58: 20 | S58: 23 | T58: 0.3 | U58: 25 | V58: 67 | W58: 6 | X58: 0.16 | Y58: 0.05 | Z58: 0.16 | AA58: 10 | AB58: 0.04 | AC58: 0.07 | AD58: 0.2 | AE58: 0.08 | AF58: 0.02 | AG58: 5 | AH58: 0.04 | AI58: 2
B59: Grasas poliinsaturadas adultos y niños | H59: 4 | I59: =(J59*4)+(K59*9)+(P59*4) -> 41.7 | J59: 0 | K59: 4.5 | L59: 0.67 | M59: 1.39 | N59: 2.71 | O59: 1 | P59: 0.3 | Q59: 0 | R59: 1 | S59: 1 | T59: 0 | U59: 27 | V59: 2 | W59: 0 | X59: 0.01 | Y59: 0 | Z59: 0 | AA59: 2 | AB59: 0 | AC59: 0 | AD59: 0 | AE59: 0.01 | AF59: 0.01 | AG59: 0 | AH59: 0.01 | AI59: 0
B60: Grasas monoinsaturadas adultos y niños | I60: =(J60*4)+(K60*9)+(P60*4) -> 47 | J60: 0.4 | K60: 4.6 | L60: 0.66 | M60: 2.7 | N60: 0.96 | O60: 0 | P60: 1 | Q60: 0.6 | R60: 7 | S60: 7 | T60: 0.2 | U60: 55 | V60: 49 | W60: 5 | X60: 0.07 | Y60: 0.03 | Z60: 0.02 | AA60: 12 | AB60: 0.01 | AC60: 0.01 | AD60: 0.3 | AE60: 0.08 | AF60: 0.03 | AG60: 5 | AH60: 0 | AI60: 1
B61: Grasas saturadas adultos y niños | H61: 2 | I61: =(J61*4)+(K61*9)+(P61*4) -> 45.6 | J61: 0.3 | K61: 4.8 | L61: 2.66 | M61: 1.57 | N61: 0.28 | O61: 10 | P61: 0.3 | Q61: 0 | R61: 8 | S61: 7 | T61: 0 | U61: 9 | V61: 10 | W61: 1 | X61: 0.03 | Y61: 0 | Z61: 0 | AA61: 31 | AB61: 0 | AC61: 0.01 | AD61: 0 | AE61: 0.03 | AF61: 0 | AG61: 1 | AH61: 0.03 | AI61: 0
B62: Promedio grasas adultos y niños | I62: =(J62*4)+(K62*9)+(P62*4) -> 44.6 | J62: 0.3 | K62: 4.6 | L62: 1.33 | M62: 1.88 | N62: 1.32 | O62: 4 | P62: 0.5 | Q62: 0.2 | R62: 5 | S62: 5 | T62: 0.1 | U62: 30 | V62: 20 | W62: 2 | X62: 0.04 | Y62: 0.01 | Z62: 0.01 | AA62: 15 | AB62: 0 | AC62: 0.01 | AD62: 0.1 | AE62: 0.04 | AF62: 0.01 | AG62: 2 | AH62: 0.01 | AI62: 0
B63: Productos con reducción de grasa adultos y niños | I63: =(J63*4)+(K63*9)+(P63*4) -> 39.3 | J63: 1.3 | K63: 3.3 | L63: 1.16 | M63: 0.98 | N63: 0.89 | O63: 6 | P63: 1.1 | Q63: 0 | R63: 16 | S63: 37 | T63: 0 | U63: 125 | V63: 19 | W63: 2 | X63: 0.12 | Y63: 0 | Z63: 0 | AA63: 41 | AB63: 0 | AC63: 0.02 | AD63: 0 | AE63: 0.04 | AF63: 0.03 | AG63: 3 | AH63: 0.06 | AI63: 0
B66: Grupo de alimentos | H66: Porciones | I66: Kcal | J66: Prot | K66: Grasa | L66: GS | M66: GM | N66: GP | O66: COL | P66: CHOS | Q66: FD | R66: Calcio (mg) | S66: P (mg) | T66: Fe (mg) | U66: Na (mg) | V66: K (mg) | W66: Mg (mg) | X66: Zn (mg) | Y66: Cu (mg) | Z66: Mn (mg) | AA66: Vit A (ER) | AB66: Tiamina (mg) | AC66: Riboflavina (mg) | AD66: Niacina (mg) | AE66: Ac, Pantotenico (mg) | AF66: Priridox. (mg) | AG66: Acido Folico (ug) | AH66: Vit B12 (ug) | AI66: Vit C (mg)
B67: Leches enteras frescas y fermentadas | H67: =H43 -> 3 | I67: =(I43*H43) -> 417.3 | J67: =(J43*H43) -> 20.1 | K67: =(K43*H43) -> 20.1 | L67: =(L43*H43) -> 13.2 | M67: =(M43*H43) -> 5.85 | N67: =(N43*H43) -> 1.47 | O67: =(O43*H43) -> 78 | P67: =(P43*H43) -> 39 | Q67: =(Q43*H43) -> 0 | R67: =(R43*H43) -> 708 | S67: =(S43*H43) -> 519 | T67: =(T43*H43) -> 0.6 | U67: =(U43*H43) -> 288 | V67: =(V43*H43) -> 990 | W67: =(W43*H43) -> 75 | X67: =(X43*H43) -> 2.67 | Y67: =(Y43*H43) -> 0.09 | Z67: =(Z43*H43) -> 0.03 | AA67: =(AA43*H43) -> 219 | AB67: =(AB43*H43) -> 0.24 | AC67: =(AC43*H43) -> 1.02 | AD67: =(AD43*H43) -> 0.9 | AE67: =(AE43*H43) -> 2.01 | AF67: =(AF43*H43) -> 0.24 | AG67: =(AG43*H43) -> 30 | AH67: =(AH43*H43) -> 1.95 | AI67: =(AI43*H43) -> 9
B68: Leches semidescremadas frescas y fermentadas | H68: =H44 | I68: =(I44*H44) -> 0 | J68: =(J44*H44) -> 0 | K68: =(K44*H44) -> 0 | L68: =(L44*H44) -> 0 | M68: =(M44*H44) -> 0 | N68: =(N44*H44) -> 0 | O68: =(O44*H44) -> 0 | P68: =(P44*H44) -> 0 | Q68: =(Q44*H44) -> 0 | R68: =(R44*H44) -> 0 | S68: =(S44*H44) -> 0 | T68: =(T44*H44) -> 0 | U68: =(U44*H44) -> 0 | V68: =(V44*H44) -> 0 | W68: =(W44*H44) -> 0 | X68: =(X44*H44) -> 0 | Y68: =(Y44*H44) -> 0 | Z68: =(Z44*H44) -> 0 | AA68: =(AA44*H44) -> 0 | AB68: =(AB44*H44) -> 0 | AC68: =(AC44*H44) -> 0 | AD68: =(AD44*H44) -> 0 | AE68: =(AE44*H44) -> 0 | AF68: =(AF44*H44) -> 0 | AG68: =(AG44*H44) -> 0 | AH68: =(AH44*H44) -> 0 | AI68: =(AI44*H44) -> 0
B69: Leches descremadas frescas y fermentadas | H69: =H45 | I69: =(I45*H45) -> 0 | J69: =(J45*H45) -> 0 | K69: =(K45*H45) -> 0 | L69: =(L45*H45) -> 0 | M69: =(M45*H45) -> 0 | N69: =(N45*H45) -> 0 | O69: =(O45*H45) -> 0 | P69: =(P45*H45) -> 0 | Q69: =(Q45*H45) -> 0 | R69: =(R45*H45) -> 0 | S69: =(S45*H45) -> 0 | T69: =(T45*H45) -> 0 | U69: =(U45*H45) -> 0 | V69: =(V45*H45) -> 0 | W69: =(W45*H45) -> 0 | X69: =(X45*H45) -> 0 | Y69: =(Y45*H45) -> 0 | Z69: =(Z45*H45) -> 0 | AA69: =(AA45*H45) -> 0 | AB69: =(AB45*H45) -> 0 | AC69: =(AC45*H45) -> 0 | AD69: =(AD45*H45) -> 0 | AE69: =(AE45*H45) -> 0 | AF69: =(AF45*H45) -> 0 | AG69: =(AG45*H45) -> 0 | AH69: =(AH45*H45) -> 0 | AI69: =(AI45*H45) -> 0
B70: Leches frescas y fermentadas enteras altas en calorías y azucares | H70: =H46 | I70: =(I46*H46) -> 0 | J70: =(J46*H46) -> 0 | K70: =(K46*H46) -> 0 | L70: =(L46*H46) -> 0 | M70: =(M46*H46) -> 0 | N70: =(N46*H46) -> 0 | O70: =(O46*H46) -> 0 | P70: =(P46*H46) -> 0 | Q70: =(Q46*H46) -> 0 | R70: =(R46*H46) -> 0 | S70: =(S46*H46) -> 0 | T70: =(T46*H46) -> 0 | U70: =(U46*H46) -> 0 | V70: =(V46*H46) -> 0 | W70: =(W46*H46) -> 0 | X70: =(X46*H46) -> 0 | Y70: =(Y46*H46) -> 0 | Z70: =(Z46*H46) -> 0 | AA70: =(AA46*H46) -> 0 | AB70: =(AB46*H46) -> 0 | AC70: =(AC46*H46) -> 0 | AD70: =(AD46*H46) -> 0 | AE70: =(AE46*H46) -> 0 | AF70: =(AF46*H46) -> 0 | AG70: =(AG46*H46) -> 0 | AH70: =(AH46*H46) -> 0 | AI70: =(AI46*H46) -> 0
B71: Sustitutos | H71: =H47 -> 4 | I71: =(I47*H47) -> 308.4 | J71: =(J47*H47) -> 23.2 | K71: =(K47*H47) -> 22 | L71: =(L47*H47) -> 11.64 | M71: =(M47*H47) -> 7.76 | N71: =(N47*H47) -> 1.64 | O71: =(O47*H47) -> 160 | P71: =(P47*H47) -> 4.4 | Q71: =(Q47*H47) -> 0 | R71: =(R47*H47) -> 380 | S71: =(S47*H47) -> 340 | T71: =(T47*H47) -> 4.4 | U71: =(U47*H47) -> 844 | V71: =(V47*H47) -> 208 | W71: =(W47*H47) -> 24 | X71: =(X47*H47) -> 2.6 | Y71: =(Y47*H47) -> 0.12 | Z71: =(Z47*H47) -> 0.04 | AA71: =(AA47*H47) -> 180 | AB71: =(AB47*H47) -> 0.16 | AC71: =(AC47*H47) -> 0.4 | AD71: =(AD47*H47) -> 1.6 | AE71: =(AE47*H47) -> 0.64 | AF71: =(AF47*H47) -> 0.2 | AG71: =(AG47*H47) -> 16 | AH71: =(AH47*H47) -> 2.88 | AI71: =(AI47*H47) -> 0
B72: Carnes magras crudas y proteínas texturizada | H72: =H48 -> 3 | I72: =(I48*H48) -> 324.9 | J72: =(J48*H48) -> 57.3 | K72: =(K48*H48) -> 9.3 | L72: =(L48*H48) -> 2.76 | M72: =(M48*H48) -> 3.48 | N72: =(N48*H48) -> 1.59 | O72: =(O48*H48) -> 150 | P72: =(P48*H48) -> 3 | Q72: =(Q48*H48) -> 0.9 | R72: =(R48*H48) -> 66 | S72: =(S48*H48) -> 573 | T72: =(T48*H48) -> 4.5 | U72: =(U48*H48) -> 216 | V72: =(V48*H48) -> 975 | W72: =(W48*H48) -> 84 | X72: =(X48*H48) -> 5.43 | Y72: =(Y48*H48) -> 0.33 | Z72: =(Z48*H48) -> 0.36 | AA72: =(AA48*H48) -> 21 | AB72: =(AB48*H48) -> 0.57 | AC72: =(AC48*H48) -> 0.54 | AD72: =(AD48*H48) -> 16.8 | AE72: =(AE48*H48) -> 2.34 | AF72: =(AF48*H48) -> 1.05 | AG72: =(AG48*H48) -> 45 | AH72: =(AH48*H48) -> 7.17 | AI72: =(AI48*H48) -> 3
B73: Carnes crudas altas en lípidos | H73: =H49 | I73: =(I49*H49) -> 0 | J73: =(J49*H49) -> 0 | K73: =(K49*H49) -> 0 | L73: =(L49*H49) -> 0 | M73: =(M49*H49) -> 0 | N73: =(N49*H49) -> 0 | O73: =(O49*H49) -> 0 | P73: =(P49*H49) -> 0 | Q73: =(Q49*H49) -> 0 | R73: =(R49*H49) -> 0 | S73: =(S49*H49) -> 0 | T73: =(T49*H49) -> 0 | U73: =(U49*H49) -> 0 | V73: =(V49*H49) -> 0 | W73: =(W49*H49) -> 0 | X73: =(X49*H49) -> 0 | Y73: =(Y49*H49) -> 0 | Z73: =(Z49*H49) -> 0 | AA73: =(AA49*H49) -> 0 | AB73: =(AB49*H49) -> 0 | AC73: =(AC49*H49) -> 0 | AD73: =(AD49*H49) -> 0 | AE73: =(AE49*H49) -> 0 | AF73: =(AF49*H49) -> 0 | AG73: =(AG49*H49) -> 0 | AH73: =(AH49*H49) -> 0 | AI73: =(AI49*H49) -> 0
B74: Leguminosas adultos | H74: =H50 -> 3 | I74: =(I50*H50) -> 474.3 | J74: =(J50*H50) -> 29.4 | K74: =(K50*H50) -> 5.1 | L74: =(L50*H50) -> 0.75 | M74: =(M50*H50) -> 0.96 | N74: =(N50*H50) -> 2.82 | O74: =(O50*H50) -> 0 | P74: =(P50*H50) -> 77.7 | Q74: =(Q50*H50) -> 23.7 | R74: =(R50*H50) -> 150 | S74: =(S50*H50) -> 501 | T74: =(T50*H50) -> 9.3 | U74: =(U50*H50) -> 30 | V74: =(V50*H50) -> 1602 | W74: =(W50*H50) -> 186 | X74: =(X50*H50) -> 3.66 | Y74: =(Y50*H50) -> 0.84 | Z74: =(Z50*H50) -> 1.8 | AA74: =(AA50*H50) -> 30 | AB74: =(AB50*H50) -> 0.6 | AC74: =(AC50*H50) -> 0.27 | AD74: =(AD50*H50) -> 2.7 | AE74: =(AE50*H50) -> 1.26 | AF74: =(AF50*H50) -> 0.48 | AG74: =(AG50*H50) -> 426 | AH74: =(AH50*H50) -> 0 | AI74: =(AI50*H50) -> 12
B75: Cereales adultos | H75: =H51 -> 4 | I75: =(I51*H51) -> 375.2 | J75: =(J51*H51) -> 10 | K75: =(K51*H51) -> 4 | L75: =(L51*H51) -> 0.96 | M75: =(M51*H51) -> 1.28 | N75: =(N51*H51) -> 1.32 | O75: =(O51*H51) -> 4 | P75: =(P51*H51) -> 74.8 | Q75: =(Q51*H51) -> 4.8 | R75: =(R51*H51) -> 76 | S75: =(S51*H51) -> 188 | T75: =(T51*H51) -> 3.6 | U75: =(U51*H51) -> 328 | V75: =(V51*H51) -> 212 | W75: =(W51*H51) -> 52 | X75: =(X51*H51) -> 1.68 | Y75: =(Y51*H51) -> 0.2 | Z75: =(Z51*H51) -> 0.96 | AA75: =(AA51*H51) -> 88 | AB75: =(AB51*H51) -> 0.44 | AC75: =(AC51*H51) -> 0.36 | AD75: =(AD51*H51) -> 4.4 | AE75: =(AE51*H51) -> 0.6 | AF75: =(AF51*H51) -> 0.32 | AG75: =(AG51*H51) -> 152 | AH75: =(AH51*H51) -> 0 | AI75: =(AI51*H51) -> 8
B76: Raíces, tubérculos y plátanos adultos | H76: =H52 | I76: =(I52*H52) -> 0 | J76: =(J52*H52) -> 0 | K76: =(K52*H52) -> 0 | L76: =(L52*H52) -> 0 | M76: =(M52*H52) -> 0 | N76: =(N52*H52) -> 0 | O76: =(O52*H52) -> 0 | P76: =(P52*H52) -> 0 | Q76: =(Q52*H52) -> 0 | R76: =(R52*H52) -> 0 | S76: =(S52*H52) -> 0 | T76: =(T52*H52) -> 0 | U76: =(U52*H52) -> 0 | V76: =(V52*H52) -> 0 | W76: =(W52*H52) -> 0 | X76: =(X52*H52) -> 0 | Y76: =(Y52*H52) -> 0 | Z76: =(Z52*H52) -> 0 | AA76: =(AA52*H52) -> 0 | AB76: =(AB52*H52) -> 0 | AC76: =(AC52*H52) -> 0 | AD76: =(AD52*H52) -> 0 | AE76: =(AE52*H52) -> 0 | AF76: =(AF52*H52) -> 0 | AG76: =(AG52*H52) -> 0 | AH76: =(AH52*H52) -> 0 | AI76: =(AI52*H52) -> 0
B77: Promedio "Harinas" adultos | H77: =H53 | I77: =(I53*H53) -> 0 | J77: =(J53*H53) -> 0 | K77: =(K53*H53) -> 0 | L77: =(L53*H53) -> 0 | M77: =(M53*H53) -> 0 | N77: =(N53*H53) -> 0 | O77: =(O53*H53) -> 0 | P77: =(P53*H53) -> 0 | Q77: =(Q53*H53) -> 0 | R77: =(R53*H53) -> 0 | S77: =(S53*H53) -> 0 | T77: =(T53*H53) -> 0 | U77: =(U53*H53) -> 0 | V77: =(V53*H53) -> 0 | W77: =(W53*H53) -> 0 | X77: =(X53*H53) -> 0 | Y77: =(Y53*H53) -> 0 | Z77: =(Z53*H53) -> 0 | AA77: =(AA53*H53) -> 0 | AB77: =(AB53*H53) -> 0 | AC77: =(AC53*H53) -> 0 | AD77: =(AD53*H53) -> 0 | AE77: =(AE53*H53) -> 0 | AF77: =(AF53*H53) -> 0 | AG77: =(AG53*H53) -> 0 | AH77: =(AH53*H53) -> 0 | AI77: =(AI53*H53) -> 0
B78: Verduras y hortalizas adultos y niños | H78: =H54 -> 5 | I78: =(I54*H54) -> 147.5 | J78: =(J54*H54) -> 6 | K78: =(K54*H54) -> 1.5 | L78: =(L54*H54) -> 0.25 | M78: =(M54*H54) -> 0.15 | N78: =(N54*H54) -> 0.65 | O78: =(O54*H54) -> 0 | P78: =(P54*H54) -> 27.5 | Q78: =(Q54*H54) -> 8.5 | R78: =(R54*H54) -> 75 | S78: =(S54*H54) -> 160 | T78: =(T54*H54) -> 3.5 | U78: =(U54*H54) -> 340 | V78: =(V54*H54) -> 935 | W78: =(W54*H54) -> 60 | X78: =(X54*H54) -> 1.45 | Y78: =(Y54*H54) -> 0.5 | Z78: =(Z54*H54) -> 0.8 | AA78: =(AA54*H54) -> 680 | AB78: =(AB54*H54) -> 0.25 | AC78: =(AC54*H54) -> 0.3 | AD78: =(AD54*H54) -> 4 | AE78: =(AE54*H54) -> 1.85 | AF78: =(AF54*H54) -> 0.45 | AG78: =(AG54*H54) -> 115 | AH78: =(AH54*H54) -> 0 | AI78: =(AI54*H54) -> 95
... B87: Productos con reducción de grasa adultos y niños | H87: =H63 | I87: =(I63*H63) -> 0 | J87: =(J63*H63) -> 0 | K87: =(K63*H63) -> 0 | L87: =(L63*H63) -> 0 | M87: =(M63*H63) -> 0 | N87: =(N63*H63) -> 0 | O87: =(O63*H63) -> 0 | P87: =(P63*H63) -> 0 | Q87: =(Q63*H63) -> 0 | R87: =(R63*H63) -> 0 | S87: =(S63*H63) -> 0 | T87: =(T63*H63) -> 0 | U87: =(U63*H63) -> 0 | V87: =(V63*H63) -> 0 | W87: =(W63*H63) -> 0 | X87: =(X63*H63) -> 0 | Y87: =(Y63*H63) -> 0 | Z87: =(Z63*H63) -> 0 | AA87: =(AA63*H63) -> 0 | AB87: =(AB63*H63) -> 0 | AC87: =(AC63*H63) -> 0 | AD87: =(AD63*H63) -> 0 | AE87: =(AE63*H63) -> 0 | AF87: =(AF63*H63) -> 0 | AG87: =(AG63*H63) -> 0 | AH87: =(AH63*H63) -> 0 | AI87: =(AI63*H63) -> 0
H88: TOTAL | I88: =SUM(I67:I87) -> 2807.9 | J88: =SUM(J67:J87) -> 153.9 | K88: =SUM(K67:K87) -> 103.1 | L88: =SUM(L67:L87) -> 41.87 | M88: =SUM(M67:M87) -> 34.23 | N88: =SUM(N67:N87) -> 23.3 | O88: =SUM(O67:O87) -> 422 | P88: =SUM(P67:P87) -> 316.1 | ... AI88: =SUM(AI67:AI87) -> 237
H89: REQUERIDO | I89: =B38 -> 2731.5 | J89: =C38 -> 127.5 | K89: =D38 -> 75.875 | L89: =E38 -> 30.35 | M89: =F38 -> 15.175 | N89: =G38 -> 30.35 | O89: =H38 -> 200 | P89: =I38 -> 384.65625 | Q89: =J38 -> 14
H90: %ADECUACI | I90: =((100/I89)*I88) -> 102.797 | J90: =((100/J89)*J88) -> 120.70588 | K90: =((100/K89)*K88) -> 135.88138 | L90: =((100/L89)*L88) -> 137.95717 | M90: =((100/M89)*M88) -> 225.56837 | N90: =((100/N89)*N88) -> 76.771005 | O90: =((100/O89)*O88) -> 211 | P90: =((100/P89)*P88) -> 82.177269 | ... AI90: =((100/AI89)*AI88) -> #DIV/0!
I91: Kcal | J91: Prot | K91: Grasa | L91: GS | M91: GM | N91: GP | O91: COL | P91: CHOS | Q91: FD | R91: Calcio (mg) | S91: P (mg) | T91: Fe (mg) | U91: Na (mg) | V91: K (mg) | W91: Mg (mg) | X91: Zn (mg) | Y91: Cu (mg) | Z91: Mn (mg) | AA91: Vit A (ER) | AB91: Tiamina (mg) | AC91: Riboflavina (mg) | AD91: Niacina (mg) | AE91: Ac, Pantotenico (mg) | AF91: Priridox. (mg) | AG91: Acido Folico (ug) | AH91: Vit B12 (ug) | AI91: Vit C (mg)
B93: FÓRMULA SINTÉTICA PLANEADA FINAL
I95: FÓRMULA SINTÉTICA PLANEADA FINAL | O95: Recomendaciones RIEN | S95: Respaldo calórico no proteico
I96: Nutrientes | J96: Gramos | K96: Calorías | L96: % AMDR | M96: Otros | O96: Proteinas | Q96: 14-20% | S96: Gramos N | U96: =J97/6.25 -> 24.624
I97: Proteínas | J97: =(J88) -> 153.9 | K97: =(J97*4) -> 615.6 | L97: =((100/K109)*K97) -> 21.923858 | M97: g AVB | N97: =SUM(J67:J73) -> 100.6 | O97: Prote g/kg/peso | Q97: 1,11-1,16 | S97: Calorías no proteicas | U97: =K100+K107 -> 2192.3
M98: % AVB | N98: =((100/J97)*N97) -> 65.367122 | O98: Prote AVB | Q98: 60-80% | S98: Respaldo calórico | U98: =U97/U96 -> 89.031027
M99: g/kg/peso | N99: =(J97/J110) -> 2.052 | O99: Carbohidratos totales | Q99: 50-65% | S99: Clasificación | U99: =IF(U98>180,"Adecuado","Inadecuado") -> Inadecuado
I100: Grasas | J100: =(K88) -> 103.1 | K100: =(J100*9) -> 927.9 | L100: =((100/K109)*K100) -> 33.046049 | M100: g GS | N100: =(L88) -> 41.87 | O100: Carbohidratos simples | Q100: <10%
M101: %AMDR GS | N101: =((100/K109)*(N100*9)) -> 13.42035 | O101: Grasa total | Q101: 20-35%
M102: g GM | N102: =(M88) -> 34.23 | O102: G saturada | Q102: <10%
M103: %AMDR GM | N103: =((100/K109)*(N102*9)) -> 10.971545 | O103: G mono | Q103: GS-GM
M104: g GP | N104: =(N88) -> 23.3 | O104: G poli | Q104: 5-10%
M105: %AMDR GP | N105: =((100/K109)*(N104*9)) -> 7.4682147 | O105: G trans | Q105: <1%
M106: Colesterol | N106: =(O88) -> 422 | O106: Colesterol | Q106: <300mg
I107: CHOs | J107: =(P88) -> 316.1 | K107: =(J107*4) -> 1264.4 | L107: =((100/K109)*K107) -> 45.030094 | M107: g Concent | N107: =SUM(P82) -> 57.3 | O107: Colesterol enf.card | Q107: <200mg
M108: %AMDR | N108: =((100/K109)*(N107*4)) -> 8.1626839 | O108: Fibra | Q108: 14/1000cal
I109: Total: | K109: =SUM(K97:K108) -> 2807.9 | L109: =SUM(L97:L108) -> 100 | M109: Fibra | N109: =Q88 -> 46 | O109: Sodio | Q109: <2300mg
I110: Kg Ref | J110: =J33 -> 75 | O110: Sodio hipertensos | Q110: <1500mg
B112: MINUTA PATRÓN
B114: Grupo de alimentos | H114: Porciones | I114: D | J114: MM | K114: A | L114: MT | M114: C | N114: ME | P114: D: Desayuno
B115: Leches enteras frescas y fermentadas | H115: =H67 -> 3 | P115: MM: Media Mañana
B116: Leches semidescremadas frescas y fermentadas | H116: =H68 | P116: A: Almuerzo
B117: Leches descremadas frescas y fermentadas | H117: =H69 | P117: MT: Media Tarde
B118: Leches frescas y fermentadas enteras altas en calorías y azucares | H118: =H70 | P118: C: Cena
B119: Sustitutos | H119: =H71 -> 4 | P119: ME: Merienda
B120: Carnes magras crudas y proteínas texturizada | H120: =H72 -> 3
B121: Carnes crudas altas en lípidos | H121: =H73
B122: Leguminosas adultos | H122: =H74 -> 3
B123: Leguminosas niños y niñas | H123: =#REF! -> #REF!
...

Sheet Pediatría
B2: EVALUACIÓN Y PLANEACIÓN NUTRICIONAL DEL PACIENTE PEDIÁTRICO
B4: EVALUACIÓN ANTROPOMÉTRICA | E4: Área muscular y Área grasa HOMBRES | P4: Área muscular y Área grasa MUJERES
B5: Nombre | L5: Mujer
B6: Apellido
B7: Identificación | L7: Peso/talla
B8: Sexo | C8: Mujer | L8: Obesidad
B9: Edad años | L9: Sobrepeso
B10: Peso kg | L10: Riesgo sobrepeso
B11: Talla/Longitud cm | L11: Adecuado
B12: Talla/Longitud m | C12: =C11/100 -> 0 | L12: Riesgo desnutricion aguda
B13: Antropometria Braquial | L13: Desnutricion aguda moderada
B14: Perimetro brazo mm | L14: Desnutricion aguda severa
B15: Pliegue tricipital mm | L15: Talla/Edad <5
B16: Pliegue subescapular mm | L16: Adecuado
B17: Perímetro Muscular Brazo mm | C17: =C14-(3.14159*C15) -> 0 | L17: Riesgo talla baja
B18: Área Muscular del Brazo mm2 | C18: =(C17^2)/(4*3.14159) -> 0 | L18: Retraso en talla
B19: Percentil AMB
B20: Clasificación AMB mm2 | C20: =IF(C19=L35,"Franco agotamiento de la reserva muscular",IF(C19=L36,"Sugiere agotamiento de la reserva muscular",IF(C19=L37,"Adecuada reserva muscular",IF(C19=L38,"Buena reserva muscular","Introduzca percentil AMB")))) -> Introduzca percentil AMB | L20: Perimetro cef
B21: Area Total del Brazo mm2 | C21: =(3.14159/4)*((C14/3.14159)^2) -> 0 | L21: Riesgo neurodesarrollo
B22: Area Grasa del Brazo mm2 | C22: =C21-C18 -> 0 | L22: Adecuado
B23: Percentil AGB | E23: Adiposidad HOMBRES | P23: Adiposidad MUJERES
B24: Clasificación AGB mm2 | C24: =IF(C23=L40,"Franco agotamiento de la reserva energetica",IF(C23=L41,"Sugiere agotamiento de la reserva energetica",IF(C23=L42,"Reserva energetica adecuada",IF(C23=L43,"Alta reserva energetica asociada a sobrepeso",IF(C23=L44,"Sugiere obesidad","Introduzca percentil AGB"))))) -> Introduzca percentil AGB | L24: Talla/Edad >5
B25: Adiposidad | C25: =C15+C16 -> 0 | L25: Adecuado
B26: Percentil Adiposidad | L26: Riesgo retraso en talla
B27: Clasificación Adiposidad | C27: =IF(C26=L46,"Grasa muy baja",IF(C26=L47,"Grasa baja",IF(C26=L48,"Grasa adecuada",IF(C26=L49,"Exceso de grasa",IF(C26=L50,"Obesidad","Introduzca percentil de adiposidad"))))) -> Introduzca percentil de adiposidad | L27: Talla baja para edad
L28: IMC
B29: RESULTADOS < 5 AÑOS | L29: Obesidad
B30: Peso/Talla pZ | L30: Sobrepeso
B31: Peso/Talla Clasificación | C31: =IF(C30>3,"Obesidad",IF(AND(C30>2,C30<=3),"Sobrepeso",IF(AND(C30>1,C30<=2),"Riesgo de sobrepeso",IF(AND(C30>=-1,C30<=1),"Peso adecuado para la talla",IF(AND(C30>=-2,C30<-1),"Riesgo de desnutricion aguda",IF(AND(C30<-2,C30>=-3),"Desnutricion aguda moderada","Desnutricion aguda severa")))))) -> Peso adecuado para la talla | L31: Adecuado
B32: Talla/Edad pZ | L32: Riesgo delgadez
B33: Talla/Edad Clasificación | C33: =IF(C32>=-1,"Talla adecuada para la edad",IF(AND(C32>=-2,C32<-1),"Riesgo de talla baja","Retraso en talla")) -> Talla adecuada para la edad | L33: Delgadez
B34: Perim Cefalico pZ | L34: Percentiles
B35: Perim Cefalico Clasificación | C35: =IF(AND(C34>=-2,C34<=2),"Normal","Riesgo neurodesarrollo") -> Normal | L35: <5
B36: RESULTADOS 5-17 AÑOS | L36: 5-25
B37: Talla/Edad pZ | L37: 25-75
B38: Talla/Edad Clasificación | C38: =IF(C37>=-1,"Talla adecuada para la edad",IF(AND(C37>=-2,C37<-1),"Riesgo de retraso en talla","Retraso en talla")) -> Talla adecuada para la edad | L38: >75
B39: IMC | C39: =F56 -> #DIV/0!
B40: IMC/Edad pZ | L40: <5
B41: IMC/Edad Clasificación | C41: =IF(C40>2,"Obesidad",IF(AND(C40>1,C40<=2),"Sobrepeso",IF(AND(C40>=-1,C40<=1),"Adecuado",IF(AND(C40>=-2,C40<-1),"Riesgo delgadez","Delgadez")))) -> Adecuado | L41: 5-25
L42: 25-75
B43: REQUERIMIENTO ENERGÉTICO | L43: 75-95
L44: >95
B45: Peso de referencia kg | E45: Utilice el peso de referencia solo en caso de EXCESO de peso, para menores de 5 años Peso/Talla referencia y para mayores IMC/Edad | L45: Adiposidad
B46: Gasto energético en reposo | L46: <5
B47: 0-1 año leche materna | C47: =-152+(92.8*C45) -> -152 | L47: 5-15
B48: 0-1 año solo formula infantil | C48: =-29+(82.6*C45) -> -29 | L48: 15-85
B49: 0-1 año mixto | C49: =-95.4+(88.3*C45) -> -95.4 | L49: 85-95
B50: 1-18 años | C50: =IF(C8="Mujer",(263.4+(65.3*C45)-(0.454*(C45^2))),(310.2+(63.3*C45)-(0.263*(C45^2)))) -> 263.4 | L50: >95
B51: Calorías adicionales crecimiento
B52: Gasto energético
B53: Ganancia gramos/dia | E53: PESO SALUDABLE IMC
B54: Calorias x gramo | E54: Peso kg | F54: =C10 | L54: =IF(C56="Moderado",(L58),IF(C56="Sedentario",(L58*0.85),(L58*1.15))) -> 0
B55: Total adicionales | C55: =C54*C53 -> 0 | E55: Talla m | F55: =C12 -> 0 | L55: Moderado
B56: Actividad fisica | E56: IMC | F56: =(F54/(F55*F55)) -> #DIV/0! | L56: Sedentario
B57: Requerimiento | C57: =L54 -> 0 | E57: IMC deseado | L57: Activo
E58: Peso referencia IMC | L58: =SUM(C52,C55) -> 0
B59: En caso deficit de peso | E59: Peso Ref | F59: =(F57*(F55*F55)) -> 0 | L59: Duplicar
B60: Duplicar o triplicar ganancia | C60: Triplicar | L60: Triplicar
B61: Requerimiento | C61: =L63+L58 -> 0 | L61: =IF(C60="Duplicar",2,3) -> 3
L62: =C53*L61 -> 0
B63: Estos requerimientos son calculados a partir de las formulas de la FAO, OMS, 2005. Para el déficit de peso, el programa calcula la ganancia de 1g de tejido/día x 5 calorías. | L63: =L62*5 -> 0
B71: FÓRMULA SINTÉTICA PLANEADA
E73: FÓRMULA SINTÉTICA PLANEADA | M73: Recomendac RIEN | N73: 0-6 meses | O73: 7-12 meses | P73: 1-3 años | Q73: 4-13 años | R73: 14-18
E74: Nutrientes | F74: Gramos | G74: Calorías | H74: % AMDR | I74: Otros | M74: Proteína %AMDR | N74: - | O74: - | P74: 10-20% | Q74: 10-20% | R74: 10-20%
E75: Proteínas | F75: =(J77*F88) -> 0 | G75: =(F75*4) -> 0 | H75: =((100/G87)*G75) -> #DIV/0! | I75: g AVB | J75: =((J76/100)*F75) -> 0 | M75: Prote g/kg/peso | N75: 1.52 | O75: 1.67 | P75: 1.46 | Q75: 1.32 | R75: 1.18
I76: % AVB | M76: Prote AVB | N76: 60-80% | O76: 60-80% | P76: 60-80% | Q76: 60-80% | R76: 60-80%
I77: g/kg/peso | M77: CHOs totales | N77: 60g | O77: 95g | P77: 50-65% | Q77: 50-65% | R77: 50-65%
E78: Grasas | F78: =(G78/9) -> 0 | G78: =((G87/100)*H78) -> 0 | I78: g GS | J78: =(((G87/100)*J79)/9) -> 0 | M78: CHOs simples | N78: <10% | O78: <10% | P78: <10% | Q78: <10% | R78: <10%
I79: %AMDR GS | M79: Grasa total | N79: 31g | O79: 30g | P79: 30-40% | Q79: 25-35% | R79: 25-35%
I80: g GM | J80: =(((G87/100)*J81)/9) -> 0 | M80: G saturada | N80: - | O80: - | P80: - | Q80: <10% | R80: <10%
I81: %AMDR GM | J81: =(H78-J79)-J83 -> 0 | M81: G poli | N81: 4,4g | O81: 4,6g | P81: 5-10% | Q81: 5-10% | R81: 5-10%
I82: g GP | J82: =(((G87/100)*J83)/9) -> 0 | M82: G mono | N82: - | O82: - | P82: GS-GM | Q82: GS-GM | R82: GS-GM
I83: %AMDR GP | M83: G trans | N83: - | O83: - | P83: - | Q83: <1% | R83: <1%
I84: Colesterol | M84: Fibra | N84: - | O84: - | P84: 14g/1000cal | Q84: 14g/1000cal | R84: 14g/1000cal
E85: CHOs | F85: =(G85/4) -> #DIV/0! | G85: =((G87/100)*H85) -> #DIV/0! | H85: =(100-H88) -> #DIV/0! | I85: g Concent | J85: =(((G87/100)*J86)/4) -> 0 | M85: Sodio | N85: 120mg | O85: 370mg | P85: <1500mg | Q85: <1900mg | R85: <2300mg
I86: %AMDR
E87: Total: | H87: =SUM(H75:H86) -> #DIV/0! | I87: Fibra | J87: =0.014*G87 -> 0
E88: Kg Ref | F88: =C45 | G88: =SUM(G75:G86) -> #DIV/0! | H88: =SUM(H75:H84) -> #DIV/0!
E90: FÓRMULA SINTÉTICA DESARROLLADA
B92: Grupo de alimentos | F92: Porciones | G92: Kcal | H92: Prot | I92: Grasa | J92: GS | K92: GM | M92: GP | N92: COL | O92: CHOS | P92: FD | Q92: Calcio (mg) | R92: P (mg) | S92: Fe (mg) | T92: Na (mg) | U92: K (mg) | V92: Mg (mg) | W92: Zn (mg) | X92: Cu (mg) | Y92: Mn (mg) | Z92: Vit A (ER) | AA92: Tiamina (mg) | AB92: Riboflavina (mg) | AC92: Niacina (mg) | AD92: Ac, Pantotenico (mg) | AE92: Priridox. (mg) | AF92: Acido Folico (ug) | AG92: Vit B12 (ug) | AH92: Vit C (ug)
B93: Leches enteras frescas y fermentadas | G93: =(H93*4)+(I93*9)+(O93*4) -> 139.1 | H93: 6.7 | I93: 6.7 | J93: 4.4 | K93: 1.95 | M93: 0.49 | N93: 26 | O93: 13 | P93: 0 | Q93: 236 | R93: 173 | S93: 0.2 | T93: 96 | U93: 330 | V93: 25 | W93: 0.89 | X93: 0.03 | Y93: 0.01 | Z93: 73 | AA93: 0.08 | AB93: 0.34 | AC93: 0.3 | AD93: 0.67 | AE93: 0.08 | AF93: 10 | AG93: 0.65 | AH93: 3
B94: Leches semidescremadas frescas y fermentadas | G94: =(H94*4)+(I94*9)+(O94*4) -> 94.5 | H94: 5.4 | I94: 2.1 | J94: 0.87 | K94: 0.54 | M94: 0.35 | N94: 5 | O94: 13.5 | P94: 0.8 | Q94: 153 | R94: 143 | S94: 0.4 | T94: 72 | U94: 268 | V94: 25 | W94: 1.24 | X94: 0.06 | Y94: 0.11 | Z94: 76 | AA94: 0.12 | AB94: 0.25 | AC94: 0.2 | AD94: 0.41 | AE94: 0.06 | AF94: 8 | AG94: 0.5 | AH94: 4
B95: Leches descremadas frescas y fermentadas | G95: =(H95*4)+(I95*9)+(O95*4) -> 82.3 | H95: 9 | I95: 0.7 | J95: 0.45 | K95: 0.18 | M95: 0.03 | N95: 6 | O95: 10 | P95: 0 | Q95: 256 | R95: 214 | S95: 0.1 | T95: 101 | U95: 340 | V95: 24 | W95: 1.05 | X95: 0.02 | Y95: 0.01 | Z95: 89 | AA95: 0.08 | AB95: 0.33 | AC95: 0.2 | AD95: 0.79 | AE95: 0.08 | AF95: 14 | AG95: 0.84 | AH95: 2
B96: Leches frescas y fermentadas enteras altas en calorías y azucares | G96: =(H96*4)+(I96*9)+(O96*4) -> 170.7 | H96: 6.4 | I96: 5.9 | J96: 3.8 | K96: 1.91 | M96: 0.63 | N96: 22 | O96: 23 | P96: 0.4 | Q96: 258 | R96: 169 | S96: 0.3 | T96: 115 | U96: 334 | V96: 27 | W96: 1.03 | X96: 0.05 | Y96: 0.04 | Z96: 45 | AA96: 0.08 | AB96: 0.37 | AC96: 0.2 | AD96: 0.73 | AE96: 0.08 | AF96: 13 | AG96: 0.76 | AH96: 3
B97: Leches frescas, fermentadas y productos lácteos menores de 2 años | G97: =(H97*4)+(I97*9)+(O97*4) -> 50.7 | H97: 2.9 | I97: 3.1 | J97: 2.01 | K97: 0.96 | M97: 0.18 | N97: 12 | O97: 2.8 | P97: 0 | Q97: 93 | R97: 62 | S97: 0.1 | T97: 57 | U97: 57 | V97: 6 | W97: 0.38 | X97: 0.01 | Y97: 0 | Z97: 36 | AA97: 0.01 | AB97: 0.08 | AC97: 0.1 | AD97: 0.12 | AE97: 0.02 | AF97: 2 | AG97: 0.2 | AH97: 0
B98: Leche materna toma/100ml* | G98: =(H98*4)+(I98*9)+(O98*4) -> 71.2 | H98: 1 | I98: 4.4 | J98: 2.01 | K98: 1.66 | M98: 0.5 | N98: 14 | O98: 6.9 | P98: 0 | Q98: 32 | R98: 14 | S98: 0 | T98: 17 | U98: 51 | V98: 3 | W98: 0.17 | X98: 0.05 | Y98: 0.03 | Z98: 64 | AA98: 0.01 | AB98: 0.04 | AC98: 0.2 | AD98: 0.22 | AE98: 0.01 | AF98: 5 | AG98: 0.05 | AH98: 5
B99: Sustitutos | G99: =(H99*4)+(I99*9)+(O99*4) -> 77.1 | H99: 5.8 | I99: 5.5 | J99: 2.91 | K99: 1.94 | M99: 0.41 | N99: 40 | O99: 1.1 | P99: 0 | Q99: 95 | R99: 85 | S99: 1.1 | T99: 211 | U99: 52 | V99: 6 | W99: 0.65 | X99: 0.03 | Y99: 0.01 | Z99: 45 | AA99: 0.04 | AB99: 0.1 | AC99: 0.4 | AD99: 0.16 | AE99: 0.05 | AF99: 4 | AG99: 0.72 | AH99: 0
B100: Huevo menores de 2 años | G100: =(H100*4)+(I100*9)+(O100*4) -> 52.9 | H100: 4.5 | I100: 3.7 | J100: 1.15 | K100: 1.42 | M100: 0.49 | N100: 180 | O100: 0.4 | P100: 0 | Q100: 19 | R100: 64 | S100: 0.6 | T100: 46 | U100: 46 | V100: 4 | W100: 0.4 | X100: 0.01 | Y100: 0.01 | Z100: 57 | AA100: 0.03 | AB100: 0.2 | AC100: 0 | AD100: 0.51 | AE100: 0.05 | AF100: 18 | AG100: 0.43 | AH100: 0
B101: Carnes magras crudas y proteínas texturizada adultos y niños | G101: =(H101*4)+(I101*9)+(O101*4) -> 108.3 | H101: 19.1 | I101: 3.1 | J101: 0.92 | K101: 1.16 | M101: 0.53 | N101: 50 | O101: 1 | P101: 0.3 | Q101: 22 | R101: 191 | S101: 1.5 | T101: 72 | U101: 325 | V101: 28 | W101: 1.81 | X101: 0.11 | Y101: 0.12 | Z101: 7 | AA101: 0.19 | AB101: 0.18 | AC101: 5.6 | AD101: 0.78 | AE101: 0.35 | AF101: 15 | AG101: 2.39 | AH101: 1
B102: Carnes magras cocidas menores de 2 años | G102: =(H102*4)+(I102*9)+(O102*4) -> 49.2 | H102: 7.8 | I102: 2 | J102: 0.52 | K102: 0.84 | M102: 0.35 | N102: 21 | O102: 0 | P102: 0 | Q102: 7 | R102: 74 | S102: 0.4 | T102: 19 | U102: 108 | V102: 8 | W102: 0.55 | X102: 0.04 | Y102: 0.09 | Z102: 5 | AA102: 0.1 | AB102: 0.07 | AC102: 1.9 | AD102: 0.33 | AE102: 0.09 | AF102: 2 | AG102: 1 | AH102: 0
B103: Carnes crudas altas en lípidos adultos y niños | G103: =(H103*4)+(I103*9)+(O103*4) -> 138.7 | H103: 15.6 | I103: 7.9 | J103: 2.51 | K103: 3.3 | M103: 1.25 | N103: 137 | O103: 1.3 | P103: 0 | Q103: 37 | R103: 186 | S103: 2.5 | T103: 101 | U103: 234 | V103: 20 | W103: 1.87 | X103: 0.47 | Y103: 0.09 | Z103: 1515 | AA103: 0.07 | AB103: 0.53 | AC103: 4.4 | AD103: 1.67 | AE103: 0.27 | AF103: 87 | AG103: 10.58 | AH103: 6
B104: Carnes cocidas altas en lípidos menores de 2 años | G104: =(H104*4)+(I104*9)+(O104*4) -> 46.8 | H104: 6.9 | I104: 2 | J104: 0.78 | K104: 0.86 | M104: 0.31 | N104: 79 | O104: 0.3 | P104: 0 | Q104: 3 | R104: 57 | S104: 3 | T104: 62 | U104: 55 | V104: 6 | W104: 1.21 | X104: 0.25 | Y104: 0.04 | Z104: 620 | AA104: 0.02 | AB104: 0.29 | AC104: 1.1 | AD104: 0.55 | AE104: 0.09 | AF104: 39 | AG104: 4.29 | AH104: 2
... B133: Promedio grasas menores de 2 años | G133: =(H133*4)+(I133*9)+(O133*4) -> 26.8 | H133: 0.2 | I133: 2.8 | J133: 0.81 | K133: 1.12 | M133: 0.76 | N133: 2 | O133: 0.2 | P133: 0.1 | Q133: 2 | R133: 3 | S133: 0 | T133: 3 | U133: 15 | V133: 1 | W133: 0.02 | X133: 0.01 | Y133: 0.01 | Z133: 9 | AA133: 0 | AB133: 0.01 | AC133: 0.1 | AD133: 0.03 | AE133: 0.01 | AF133: 2 | AG133: 0.01 | AH133: 0
B135: *La información de la leche materna fue obtenida a través de la TCA del ICBF 2018
B137: Grupo de alimentos | F137: Porciones | G137: Kcal | H137: Prot | I137: Grasa | J137: GS | K137: GM | M137: GP | N137: COL | O137: CHOS | P137: FD | Q137: Calcio (mg) | R137: P (mg) | S137: Fe (mg) | T137: Na (mg) | U137: K (mg) | V137: Mg (mg) | W137: Zn (mg) | X137: Cu (mg) | Y137: Mn (mg) | Z137: Vit A (ER) | AA137: Tiamina (mg) | AB137: Riboflavina (mg) | AC137: Niacina (mg) | AD137: Ac, Pantotenico (mg) | AE137: Priridox. (mg) | AF137: Acido Folico (ug) | AG137: Vit B12 (ug) | AH137: Vit BC (ug)
B138: Leches enteras frescas y fermentadas | F138: =F93 | G138: =(G93*F93) -> 0 | H138: =(H93*F93) -> 0 | I138: =(I93*F93) -> 0 | J138: =(J93*F93) -> 0 | K138: =(K93*F93) -> 0 | M138: =(M93*F93) -> 0 | N138: =(N93*F93) -> 0 | O138: =(O93*F93) -> 0 | P138: =(P93*F93) -> 0 | Q138: =(Q93*F93) -> 0 | R138: =(R93*F93) -> 0 | S138: =(S93*F93) -> 0 | T138: =(T93*F93) -> 0 | U138: =(U93*F93) -> 0 | V138: =(V93*F93) -> 0 | W138: =(W93*F93) -> 0 | X138: =(X93*F93) -> 0 | Y138: =(Y93*F93) -> 0 | Z138: =(Z93*F93) -> 0 | AA138: =(AA93*F93) -> 0 | AB138: =(AB93*F93) -> 0 | AC138: =(AC93*F93) -> 0 | AD138: =(AD93*F93) -> 0 | AE138: =(AE93*F93) -> 0 | AF138: =(AF93*F93) -> 0 | AG138: =(AG93*F93) -> 0 | AH138: =(AH93*F93) -> 0
B139: Leches semidescremadas frescas y fermentadas | F139: =F94 | G139: =(G94*F94) -> 0 | H139: =(H94*F94) -> 0 | I139: =(I94*F94) -> 0 | J139: =(J94*F94) -> 0 | K139: =(K94*F94) -> 0 | M139: =(M94*F94) -> 0 | N139: =(N94*F94) -> 0 | O139: =(O94*F94) -> 0 | P139: =(P94*F94) -> 0 | Q139: =(Q94*F94) -> 0 | R139: =(R94*F94) -> 0 | S139: =(S94*F94) -> 0 | T139: =(T94*F94) -> 0 | U139: =(U94*F94) -> 0 | V139: =(V94*F94) -> 0 | W139: =(W94*F94) -> 0 | X139: =(X94*F94) -> 0 | Y139: =(Y94*F94) -> 0 | Z139: =(Z94*F94) -> 0 | AA139: =(AA94*F94) -> 0 | AB139: =(AB94*F94) -> 0 | AC139: =(AC94*F94) -> 0 | AD139: =(AD94*F94) -> 0 | AE139: =(AE94*F94) -> 0 | AF139: =(AF94*F94) -> 0 | AG139: =(AG94*F94) -> 0 | AH139: =(AH94*F94) -> 0
B140: Leches descremadas frescas y fermentadas | F140: =F95 | G140: =(G95*F95) -> 0 | H140: =(H95*F95) -> 0 | I140: =(I95*F95) -> 0 | J140: =(J95*F95) -> 0 | K140: =(K95*F95) -> 0 | M140: =(M95*F95) -> 0 | N140: =(N95*F95) -> 0 | O140: =(O95*F95) -> 0 | P140: =(P95*F95) -> 0 | Q140: =(Q95*F95) -> 0 | R140: =(R95*F95) -> 0 | S140: =(S95*F95) -> 0 | T140: =(T95*F95) -> 0 | U140: =(U95*F95) -> 0 | V140: =(V95*F95) -> 0 | W140: =(W95*F95) -> 0 | X140: =(X95*F95) -> 0 | Y140: =(Y95*F95) -> 0 | Z140: =(Z95*F95) -> 0 | AA140: =(AA95*F95) -> 0 | AB140: =(AB95*F95) -> 0 | AC140: =(AC95*F95) -> 0 | AD140: =(AD95*F95) -> 0 | AE140: =(AE95*F95) -> 0 | AF140: =(AF95*F95) -> 0 | AG140: =(AG95*F95) -> 0 | AH140: =(AH95*F95) -> 0
B141: Leches frescas y fermentadas enteras altas en calorías y azucares | F141: =F96 | G141: =(G96*F96) -> 0 | H141: =(H96*F96) -> 0 | I141: =(I96*F96) -> 0 | J141: =(J96*F96) -> 0 | K141: =(K96*F96) -> 0 | M141: =(M96*F96) -> 0 | N141: =(N96*F96) -> 0 | O141: =(O96*F96) -> 0 | P141: =(P96*F96) -> 0 | Q141: =(Q96*F96) -> 0 | R141: =(R96*F96) -> 0 | S141: =(S96*F96) -> 0 | T141: =(T96*F96) -> 0 | U141: =(U96*F96) -> 0 | V141: =(V96*F96) -> 0 | W141: =(W96*F96) -> 0 | X141: =(X96*F96) -> 0 | Y141: =(Y96*F96) -> 0 | Z141: =(Z96*F96) -> 0 | AA141: =(AA96*F96) -> 0 | AB141: =(AB96*F96) -> 0 | AC141: =(AC96*F96) -> 0 | AD141: =(AD96*F96) -> 0 | AE141: =(AE96*F96) -> 0 | AF141: =(AF96*F96) -> 0 | AG141: =(AG96*F96) -> 0 | AH141: =(AH96*F96) -> 0
B142: Leches frescas, fermentadas y productos lácteos menores de 2 años | F142: =F97 | G142: =(G97*F97) -> 0 | H142: =(H97*F97) -> 0 | I142: =(I97*F97) -> 0 | J142: =(J97*F97) -> 0 | K142: =(K97*F97) -> 0 | M142: =(M97*F97) -> 0 | N142: =(N97*F97) -> 0 | O142: =(O97*F97) -> 0 | P142: =(P97*F97) -> 0 | Q142: =(Q97*F97) -> 0 | R142: =(R97*F97) -> 0 | S142: =(S97*F97) -> 0 | T142: =(T97*F97) -> 0 | U142: =(U97*F97) -> 0 | V142: =(V97*F97) -> 0 | W142: =(W97*F97) -> 0 | X142: =(X97*F97) -> 0 | Y142: =(Y97*F97) -> 0 | Z142: =(Z97*F97) -> 0 | AA142: =(AA97*F97) -> 0 | AB142: =(AB97*F97) -> 0 | AC142: =(AC97*F97) -> 0 | AD142: =(AD97*F97) -> 0 | AE142: =(AE97*F97) -> 0 | AF142: =(AF97*F97) -> 0 | AG142: =(AG97*F97) -> 0 | AH142: =(AH97*F97) -> 0
...

Sheet Gestante
B2: ESTIMACIÓN Y EVALUACIÓN DE LA GANANCIA
B4: Ganancia de peso esperada según trimestre de gestación
C5: IMC Atalah | D5: Ganancia Total | E5: 1er trimestre | F5: Promedio | G5: 2do y 3er trim | H5: Promedio | I5: % Peso
E6: sem 0 - 13 | F6: g/semana | G6: sem 14 - 40 | H6: g/semana | I6: Total
B7: Bajo peso | C7: <20 | D7: 12kg - 18kg | E7: 2,5kg | F7: 192,3g | G7: 400g - 600g | H7: 500g | I7: 30%
B8: Normo peso | C8: 20-25 | D8: 10kg - 13kg | E8: 1,5kg | F8: 115,4g | G8: 330g - 430g | H8: 400g | I8: 20%
B9: Sobrepeso | C9: 25-30 | D9: 7kg - 10kg | E9: 0,9kg | F9: 69,2g | G9: 230g - 330g | H9: 300g | I9: 15%
B10: Obesidad | C10: >30 | D10: 6kg - 7kg | E10: - | F10: - | G10: 200g - 230g | H10: 200g | I10: 15%
B12: Nombre | E12: Evaluacion de la ganancia | H12: NOTA: Usar ajustes para semana >13
B13: Identificación | E13: Semana gestacional
B14: Edad | E14: Peso kg
B15: Peso preg kg | E15: Debió ganar Kg | F15: =IF(F13<14,((C20/13)*F13),(C20+((C21/27)*(F13-13)))) -> #DIV/0!
B16: Estatura m | E16: Ganancia presentada | F16: =F14-C15 -> 0
B17: IMC | C17: =(C15/(C16*C16)) -> #DIV/0! | E17: IMC gestacional | F17: =(F14/(C16*C16)) -> #DIV/0!
B18: Clasificacion | C18: =IF(C17<20,"Bajo",IF(AND(C17>=20,C17<25),"Normal",IF(AND(C17>=25,C17<30),"Sobrepeso","obesidad"))) -> #DIV/0!
B19: Estimacion de la ganancia | E19: Ajuste 1 | H19: Ajuste 1
B20: Kg Sem 0 - 13 | C20: =IF(C17<20,"2,5",IF(AND(C17>=18.5,C17<25),"1,5",IF(AND(C17>=25,C17<30),"0,9","0"))) -> #DIV/0! | E20: Objetivo x semana g | H20: Objetivo x semana g | I20: =F20
B21: Kg Sem 14 - 40 | C21: =IF(C17<20,"13,5",IF(AND(C17>=18.5,C17<25),"10,8",IF(AND(C17>=25,C17<30),"8,1","5,4"))) -> #DIV/0! | E21: Evaluacion de la ganancia | H21: Evaluac ganancia absoluta | K21: AJUSTE 1 RESULTADO en Kg | T21: =F13 | U21: =F17 -> #DIV/0!
B22: Total kg | C22: =(C21+C20) -> #DIV/0! | E22: Semana gestacional | H22: Semana gestacional | I22: =F22 | K22: Ganancia esperada entre semana | N22: =F13 | O22: y | P22: =F22 | Q22: : | R22: =F24 -> 0 | T22: =F22 | U22: =F26 -> #DIV/0!
B23: % Peso pregestacion | E23: Peso kg | H23: Peso kg | I23: =F23 | K23: Ganancia presentada entre semana | N23: =N22 | O23: y | P23: =P22 | Q23: : | R23: =F25 -> 0 | T23: =F31 | U23: =F35 -> #DIV/0!
B24: Total kg | C24: =IF(C17<20,(C15 *0.3),IF(AND(C17>=18.5,C17<25),(C15*0.2),IF(AND(C17>=25,C17<30),(C27*0.15),(C27*0.15)))) -> #DIV/0! | E24: Debió ganar Kg | F24: =(F20/1000)*(F22-F13) -> 0 | H24: Debió ganar Kg | I24: =IF(I22<14,(C20/13)*I22,C20+((C21/27)*(I22-13))) -> #DIV/0! | K24: Ganancia esperada hasta semana | N24: =P23 | O24: : | P24: =I24 -> #DIV/0! | T24: =F40 | U24: =F44 -> #DIV/0!
B25: En exceso de peso | E25: Ganancia presentada | F25: =F23-F14 -> 0 | H25: Ganancia presentada | I25: =F23-C15 -> 0 | K25: Ganancia absoluta hasta semana | N25: =P23 | O25: : | P25: =I25 -> 0
B26: IMC deseado | E26: IMC gestacional | F26: =(F23/(C16*C16)) -> #DIV/0! | H26: IMC gestacional | I26: =(F23/(C16*C16)) -> #DIV/0!
B27: Peso saludble | C27: =(C26*(C16*C16)) -> 0
B28: Antropometría Braquial | E28: Ajuste 2 | H28: Ajuste 2
B29: Perímetro brazo mm | E29: Objetivo x semana g | H29: Objetivo x semana g | I29: =F29
B30: Plig tricipital mm | E30: Evaluacion de la ganancia | H30: Evaluac ganancia absoluta | K30: AJUSTE 2 RESULTADO en Kg | T30: <5 | U30: <5
B31: Plig subescap mm | E31: Semana gestacional | H31: Semana gestacional | I31: =F31 | K31: Ganancia esperada entre semana | N31: =F22 | O31: y | P31: =F31 | Q31: : | R31: =F33 -> 0 | T31: 5-25 | U31: 5-25
B32: Perím Musc Brazo mm | C32: =C29-(3.14159*C30) -> 0 | E32: Peso kg | H32: Peso kg | I32: =F32 | K32: Ganancia presentada entre semana | N32: =N31 | O32: y | P32: =P31 | Q32: : | R32: =F34 -> 0 | T32: 25-75 | U32: 25-75
B33: Área Mus Brazo mm2 | C33: =(C32^2)/(4*3.14159) -> 0 | E33: Debió ganar Kg | F33: =(F29/1000)*(F31-F22) -> 0 | H33: Debió ganar Kg | I33: =IF(I31<14,(C20/13)*I31,C20+((C21/27)*(I31-13))) -> #DIV/0! | K33: Ganancia esperada hasta semana | N33: =P32 | O33: : | P33: =I33 -> #DIV/0! | T33: >75 | U33: 75-95
B34: Percentil AMB | E34: Ganancia presentada | F34: =F32-F23 -> 0 | H34: Ganancia presentada | I34: =F32-C15 -> 0 | K34: Ganancia absoluta hasta semana | N34: =P32 | O34: : | P34: =I34 -> 0 | U34: >95
B35: Clasificación AMB mm2 | C35: =IF(C34=T30,"Franco agotamiento de la reserva muscular",IF(C34=T31,"Sugiere agotamiento de la reserva muscular",IF(C34=T32,"Adecuada reserva muscular",IF(C34=T33,"Buena reserva muscular","Introduzca percentil AMB")))) -> Introduzca percentil AMB | E35: IMC gestacional | F35: =(F32/(C16*C16)) -> #DIV/0! | H35: IMC gestacional | I35: =(F32/(C16*C16)) -> #DIV/0!
B37: Área Total del Brazo mm2 | C37: =(3.14159/4)*((C29/3.14159)^2) -> 0 | E37: Ajuste 3 | H37: Ajuste 3
B38: Área Grasa del Brazo mm2 | C38: =C37-C33 -> 0 | E38: Objetivo x semana g | H38: Objetivo x semana g | I38: =F38
B39: Percentil AGB | E39: Evaluacion de la ganancia | H39: Evaluac ganancia absoluta | K39: AJUSTE 3 RESULTADO en Kg
B40: Clasificación AGB mm2 | C40: =IF(C39=U30,"Franco agotamiento de la reserva energetica",IF(C39=U31,"Sugiere agotamiento de la reserva energetica",IF(C39=U32,"Reserva energetica adecuada",IF(C39=U33,"Alta reserva energetica asociada a sobrepeso",IF(C39=U34,"Sugiere obesidad","Introduzca percentil AGB"))))) -> Introduzca percentil AGB | E40: Semana gestacional | H40: Semana gestacional | I40: =F40 | K40: Ganancia esperada entre semana | N40: =F31 | O40: y | P40: =F40 | Q40: : | R40: =F42 -> 0
E41: Peso kg | H41: Peso kg | I41: =F41 | K41: Ganancia presentada entre semana | N41: =N40 | O41: y | P41: =P40 | Q41: : | R41: =F43 -> 0
E42: Debió ganar Kg | F42: =(F38/1000)*(F40-F31) -> 0 | H42: Debió ganar Kg | I42: =IF(I40<14,(C20/13)*I40,C20+((C21/27)*(I40-13))) -> #DIV/0! | K42: Ganancia esperada hasta semana | N42: =P41 | O42: : | P42: =I42 -> #DIV/0!
E43: Ganancia presentada | F43: =F41-F32 -> 0 | H43: Ganancia presentada | I43: =F41-C15 -> 0 | K43: Ganancia absoluta hasta semana | N43: =P41 | O43: : | P43: =I43 -> 0
E44: IMC gestacional | F44: =(F41/(C16*C16)) -> #DIV/0! | H44: IMC gestacional | I44: =(F41/(C25*C25)) -> #DIV/0!
B46: Área muscular y Área grasa MUJERES
B48: REQUERIMIENTO CALORICO BRUTO | M48: GRÁFICA DE SEGUIMIENTO
B50: PESO SALUDABLE IMC | E50: TMR FAO/Schofield | H50: ACTIVIDAD FÍSICA
B51: Peso kg | E51: Peso Ref | H51: Sedentario | I51: 1.53 | J51: (1,4-1,69)
B52: Talla m | C52: =C16 | E52: TMR MUJERES | H52: Moderado | I52: 1.76 | J52: (1,7-1,99)
B53: IMC | C53: =(C51/(C52*C52)) -> #DIV/0! | E53: 18-30 años | F53: =((14.818*F51)+486.6) -> 486.6 | H53: Vigoroso | I53: 2.25 | J53: (2,0-2,4)
B54: IMC deseado | E54: >30 años | F54: =((8.126*F51)+845.6) -> 845.6
B55: Peso saludable IMC >25 | H55: REQUERIMIENTO
B56: PS | C56: =(C54*(C52*C52)) -> 0 | H56: TMR
H57: ACT FIS
H58: Calorias | I58: =(I56*I57) -> 0
B60: ADICIÓN DE CALORÍAS POR GESTACIÓN
B62: Adicionar | C62: 1er trimestre | D62: 2do trimestre | E62: 3er trimestre | G62: Requerimiento TOTAL
B63: Bajo peso | C63: 500 | D63: 500 | E63: 500 | G63: Calorías adicionales | I63: 285
B64: Normo peso | C64: 85 | D64: 285 | E64: 475 | G64: Calorías TMB | I64: =I58 -> 0
B65: Normo peso | C65: - | D65: 360 | E65: 475 | G65: Calorías totales | I65: =SUM(I63:I64) -> 285
B66: Sobrepeso | C66: - | D66: 200-250 | E66: 200-250
B67: Obesidad | C67: - | D67: 100 | E67: 100
B69: FÓRMULA SINTÉTICA PLANEADA
B71: FÓRMULA SINTÉTICA PLANEADA | I71: Recomendaciones RIEN
B72: Nutrientes | C72: Gramos | D72: CalorÍas | E72: % AMDR | F72: Otros | I72: Proteínas | K72: 14-20% AMDR
B73: Proteínas | C73: =(G75*C86) -> 0 | D73: =(C73*4) -> 0 | E73: =((100/D85)*D73) -> 0 | F73: g AVB | G73: =((G74/100)*C73) -> 0 | I73: Prote g/kg/peso | K73: 1.53
F74: % AVB | I74: Prote bajo peso g/kg | K74: 1.7
F75: g/kg/peso | I75: Prote AVB | K75: 60-80%
B76: Grasas | C76: =(D76/9) -> 0 | D76: =((D85/100)*E76) -> 0 | F76: g GS | G76: =(((D85/100)*G77)/9) -> 0 | I76: CHOs totales | K76: 50-65%
F77: %AMDR GS | I77: CHOs simples | K77: <10%
F78: g GM | G78: =(((D85/100)*G79)/9) -> 0 | I78: Grasa total 27,5 | K78: 20-35% AMDR
F79: %AMDR GM | G79: =(E76-G77)-G81 -> 0 | I79: G saturada | K79: <10%
F80: g GP | G80: =(((D85/100)*G81)/9) -> 0 | I80: G poli | K80: 5-10%
F81: %AMDR GP | I81: G mono | K81: GS-GM
F82: Colesterol | I82: G trans | K82: <1%
B83: CHOs | C83: =(D83/4) -> 71.25 | D83: =((D85/100)*E83) -> 285 | E83: =(100-E86) -> 100 | F83: g Concent | G83: =(((D85/100)*G84)/4) -> 0 | I83: Colesterol | K83: <300mg
F84: %AMDR | I84: Colesterol enf.card | K84: <200mg
B85: Total: | D85: =I65 -> 285 | E85: =SUM(E73:E84) -> 100 | F85: Fibra | I85: Fibra | K85: 28g
B86: Kg Ref | C86: =F51 | D86: =SUM(D73:D84) -> 285 | E86: =SUM(E73:E82) -> 0 | I86: Sodio | K86: <2300mg
B88: REQUERIMIENTO FINAL
B90: Kcal | C90: Prot | D90: Grasa | E90: GS | F90: GM | G90: GP | H90: COL | I90: CHOS | J90: Fibra
B91: =D85 -> 285 | C91: =C73 -> 0 | D91: =C76 -> 0 | E91: =G76 -> 0 | F91: =G78 -> 0 | G91: =G80 -> 0 | H91: =G82 | I91: =C83 -> 71.25 | J91: =G85
B93: FÓRMULA SINTÉTICA DESARROLLADA
B95: Grupo de alimentos | H95: Porciones | I95: Kcal | J95: Prot | K95: Grasa | L95: GS | M95: GM | N95: GP | O95: COL | P95: CHOS | Q95: FD | R95: Calcio (mg) | S95: P (mg) | T95: Fe (mg) | U95: Na (mg) | V95: K (mg) | W95: Mg (mg) | X95: Zn (mg) | Y95: Cu (mg) | Z95: Mn (mg) | AA95: Vit A (ER) | AB95: Tiamina (mg) | AC95: Riboflavina (mg) | AD95: Niacina (mg) | AE95: Ac, Pantotenico (mg) | AF95: Priridox. (mg) | AG95: Folato (ug) | AH95: Vit B12 (ug) | AI95: Vit C (mg)
B96: Leches enteras frescas y fermentadas | I96: =(J96*4)+(K96*9)+(P96*4) -> 139.1 | J96: 6.7 | K96: 6.7 | L96: 4.4 | M96: 1.95 | N96: 0.49 | O96: 26 | P96: 13 | Q96: 0 | R96: 236 | S96: 173 | T96: 0.2 | U96: 96 | V96: 330 | W96: 25 | X96: 0.89 | Y96: 0.03 | Z96: 0.01 | AA96: 73 | AB96: 0.08 | AC96: 0.34 | AD96: 0.3 | AE96: 0.67 | AF96: 0.08 | AG96: 10 | AH96: 0.65 | AI96: 3
B97: Leches semidescremadas frescas y fermentadas | I97: =(J97*4)+(K97*9)+(P97*4) -> 94.5 | J97: 5.4 | K97: 2.1 | L97: 0.87 | M97: 0.54 | N97: 0.35 | O97: 5 | P97: 13.5 | Q97: 0.8 | R97: 153 | S97: 143 | T97: 0.4 | U97: 72 | V97: 268 | W97: 25 | X97: 1.24 | Y97: 0.06 | Z97: 0.11 | AA97: 76 | AB97: 0.12 | AC97: 0.25 | AD97: 0.2 | AE97: 0.41 | AF97: 0.06 | AG97: 8 | AH97: 0.5 | AI97: 4
B98: Leches descremadas frescas y fermentadas | I98: =(J98*4)+(K98*9)+(P98*4) -> 82.3 | J98: 9 | K98: 0.7 | L98: 0.45 | M98: 0.18 | N98: 0.03 | O98: 6 | P98: 10 | Q98: 0 | R98: 256 | S98: 214 | T98: 0.1 | U98: 101 | V98: 340 | W98: 24 | X98: 1.05 | Y98: 0.02 | Z98: 0.01 | AA98: 89 | AB98: 0.08 | AC98: 0.33 | AD98: 0.2 | AE98: 0.79 | AF98: 0.08 | AG98: 14 | AH98: 0.84 | AI98: 2
B99: Leches frescas y fermentadas enteras altas en calorías y azucares | I99: =(J99*4)+(K99*9)+(P99*4) -> 170.7 | J99: 6.4 | K99: 5.9 | L99: 3.8 | M99: 1.91 | N99: 0.63 | O99: 22 | P99: 23 | Q99: 0.4 | R99: 258 | S99: 169 | T99: 0.3 | U99: 115 | V99: 334 | W99: 27 | X99: 1.03 | Y99: 0.05 | Z99: 0.04 | AA99: 45 | AB99: 0.08 | AC99: 0.37 | AD99: 0.2 | AE99: 0.73 | AF99: 0.08 | AG99: 13 | AH99: 0.76 | AI99: 3
B100: Sustitutos | I100: =(J100*4)+(K100*9)+(P100*4) -> 77.1 | J100: 5.8 | K100: 5.5 | L100: 2.91 | M100: 1.94 | N100: 0.41 | O100: 40 | P100: 1.1 | Q100: 0 | R100: 95 | S100: 85 | T100: 1.1 | U100: 211 | V100: 52 | W100: 6 | X100: 0.65 | Y100: 0.03 | Z100: 0.01 | AA100: 45 | AB100: 0.04 | AC100: 0.1 | AD100: 0.4 | AE100: 0.16 | AF100: 0.05 | AG100: 4 | AH100: 0.72 | AI100: 0
B101: Carnes magras crudas y proteínas texturizada | I101: =(J101*4)+(K101*9)+(P101*4) -> 108.3 | J101: 19.1 | K101: 3.1 | L101: 0.92 | M101: 1.16 | N101: 0.53 | O101: 50 | P101: 1 | Q101: 0.3 | R101: 22 | S101: 191 | T101: 1.5 | U101: 72 | V101: 325 | W101: 28 | X101: 1.81 | Y101: 0.11 | Z101: 0.12 | AA101: 7 | AB101: 0.19 | AC101: 0.18 | AD101: 5.6 | AE101: 0.78 | AF101: 0.35 | AG101: 15 | AH101: 2.39 | AI101: 1
B102: Carnes crudas altas en lípidos | I102: =(J102*4)+(K102*9)+(P102*4) -> 138.7 | J102: 15.6 | K102: 7.9 | L102: 2.51 | M102: 3.3 | N102: 1.25 | O102: 137 | P102: 1.3 | Q102: 0 | R102: 37 | S102: 186 | T102: 2.5 | U102: 101 | V102: 234 | W102: 20 | X102: 1.87 | Y102: 0.47 | Z102: 0.09 | AA102: 1515 | AB102: 0.07 | AC102: 0.53 | AD102: 4.4 | AE102: 1.67 | AF102: 0.27 | AG102: 87 | AH102: 10.58 | AI102: 6
B103: Leguminosas adultos | I103: =(J103*4)+(K103*9)+(P103*4) -> 158.1 | J103: 9.8 | K103: 1.7 | L103: 0.25 | M103: 0.32 | N103: 0.94 | O103: 0 | P103: 25.9 | Q103: 7.9 | R103: 50 | S103: 167 | T103: 3.1 | U103: 10 | V103: 534 | W103: 62 | X103: 1.22 | Y103: 0.28 | Z103: 0.6 | AA103: 10 | AB103: 0.2 | AC103: 0.09 | AD103: 0.9 | AE103: 0.42 | AF103: 0.16 | AG103: 142 | AH103: 0 | AI103: 4
B104: Cereales adultos | I104: =(J104*4)+(K104*9)+(P104*4) -> 93.8 | J104: 2.5 | K104: 1 | L104: 0.24 | M104: 0.32 | N104: 0.33 | O104: 1 | P104: 18.7 | Q104: 1.2 | R104: 19 | S104: 47 | T104: 0.9 | U104: 82 | V104: 53 | W104: 13 | X104: 0.42 | Y104: 0.05 | Z104: 0.24 | AA104: 22 | AB104: 0.11 | AC104: 0.09 | AD104: 1.1 | AE104: 0.15 | AF104: 0.08 | AG104: 38 | AH104: 0 | AI104: 2
B105: Raíces, tubérculos y plátanos adultos | I105: =(J105*4)+(K105*9)+(P105*4) -> 95.7 | J105: 1.4 | K105: 0.1 | L105: 0.05 | M105: 0.01 | N105: 0.06 | O105: 0 | P105: 22.3 | Q105: 1.9 | R105: 11 | S105: 40 | T105: 0.5 | U105: 10 | V105: 376 | W105: 20 | X105: 0.23 | Y105: 0.13 | Z105: 0.25 | AA105: 156 | AB105: 0.05 | AC105: 0.04 | AD105: 0.9 | AE105: 0.29 | AF105: 0.21 | AG105: 13 | AH105: 0 | AI105: 28
B106: Promedio "Harinas" adultos | I106: =(J106*4)+(K106*9)+(P106*4) -> 95.4 | J106: 2 | K106: 0.6 | L106: 0.14 | M106: 0.16 | N106: 0.19 | O106: 0 | P106: 20.5 | Q106: 1.5 | R106: 15 | S106: 43 | T106: 0.7 | U106: 46 | V106: 214 | W106: 17 | X106: 0.33 | Y106: 0.09 | Z106: 0.24 | AA106: 89 | AB106: 0.08 | AC106: 0.07 | AD106: 1 | AE106: 0.22 | AF106: 0.15 | AG106: 26 | AH106: 0 | AI106: 15
B107: Verduras y hortalizas adultos y niños | I107: =(J107*4)+(K107*9)+(P107*4) -> 29.5 | J107: 1.2 | K107: 0.3 | L107: 0.05 | M107: 0.03 | N107: 0.13 | O107: 0 | P107: 5.5 | Q107: 1.7 | R107: 15 | S107: 32 | T107: 0.7 | U107: 68 | V107: 187 | W107: 12 | X107: 0.29 | Y107: 0.1 | Z107: 0.16 | AA107: 136 | AB107: 0.05 | AC107: 0.06 | AD107: 0.8 | AE107: 0.37 | AF107: 0.09 | AG107: 23 | AH107: 0 | AI107: 19
... B116: Productos con reducción de grasa adultos y niños | I116: =(J116*4)+(K116*9)+(P116*4) -> 39.3 | J116: 1.3 | K116: 3.3 | L116: 1.16 | M116: 0.98 | N116: 0.89 | O116: 6 | P116: 1.1 | Q116: 0 | R116: 16 | S116: 37 | T116: 0 | U116: 125 | V116: 19 | W116: 2 | X116: 0.12 | Y116: 0 | Z116: 0 | AA116: 41 | AB116: 0 | AC116: 0.02 | AD116: 0 | AE116: 0.04 | AF116: 0.03 | AG116: 3 | AH116: 0.06 | AI116: 0
B119: Grupo de alimentos | H119: Porciones | I119: Kcal | J119: Prot | K119: Grasa | L119: GS | M119: GM | N119: GP | O119: COL | P119: CHOS | Q119: FD | R119: Calcio (mg) | S119: P (mg) | T119: Fe (mg) | U119: Na (mg) | V119: K (mg) | W119: Mg (mg) | X119: Zn (mg) | Y119: Cu (mg) | Z119: Mn (mg) | AA119: Vit A (ER) | AB119: Tiamina (mg) | AC119: Riboflavina (mg) | AD119: Niacina (mg) | AE119: Ac, Pantotenico (mg) | AF119: Priridox. (mg) | AG119: Folato (ug) | AH119: Vit B12 (ug) | AI119: Vit C (mg)
B120: Leches enteras frescas y fermentadas | H120: =H96 | I120: =(I96*H96) -> 0 | J120: =(J96*H96) -> 0 | K120: =(K96*H96) -> 0 | L120: =(L96*H96) -> 0 | M120: =(M96*H96) -> 0 | N120: =(N96*H96) -> 0 | O120: =(O96*H96) -> 0 | P120: =(P96*H96) -> 0 | Q120: =(Q96*H96) -> 0 | R120: =(R96*H96) -> 0 | S120: =(S96*H96) -> 0 | T120: =(T96*H96) -> 0 | U120: =(U96*H96) -> 0 | V120: =(V96*H96) -> 0 | W120: =(W96*H96) -> 0 | X120: =(X96*H96) -> 0 | Y120: =(Y96*H96) -> 0 | Z120: =(Z96*H96) -> 0 | AA120: =(AA96*H96) -> 0 | AB120: =(AB96*H96) -> 0 | AC120: =(AC96*H96) -> 0 | AD120: =(AD96*H96) -> 0 | AE120: =(AE96*H96) -> 0 | AF120: =(AF96*H96) -> 0 | AG120: =(AG96*H96) -> 0 | AH120: =(AH96*H96) -> 0 | AI120: =(AI96*H96) -> 0
B121: Leches semidescremadas frescas y fermentadas | H121: =H97 | I121: =(I97*H97) -> 0 | J121: =(J97*H97) -> 0 | K121: =(K97*H97) -> 0 | L121: =(L97*H97) -> 0 | M121: =(M97*H97) -> 0 | N121: =(N97*H97) -> 0 | O121: =(O97*H97) -> 0 | P121: =(P97*H97) -> 0 | Q121: =(Q97*H97) -> 0 | R121: =(R97*H97) -> 0 | S121: =(S97*H97) -> 0 | T121: =(T97*H97) -> 0 | U121: =(U97*H97) -> 0 | V121: =(V97*H97) -> 0 | W121: =(W97*H97) -> 0 | X121: =(X97*H97) -> 0 | Y121: =(Y97*H97) -> 0 | Z121: =(Z97*H97) -> 0 | AA121: =(AA97*H97) -> 0 | AB121: =(AB97*H97) -> 0 | AC121: =(AC97*H97) -> 0 | AD121: =(AD97*H97) -> 0 | AE121: =(AE97*H97) -> 0 | AF121: =(AF97*H97) -> 0 | AG121: =(AG97*H97) -> 0 | AH121: =(AH97*H97) -> 0 | AI121: =(AI97*H97) -> 0
B122: Leches descremadas frescas y fermentadas | H122: =H98 | I122: =(I98*H98) -> 0 | J122: =(J98*H98) -> 0 | K122: =(K98*H98) -> 0 | L122: =(L98*H98) -> 0 | M122: =(M98*H98) -> 0 | N122: =(N98*H98) -> 0 | O122: =(O98*H98) -> 0 | P122: =(P98*H98) -> 0 | Q122: =(Q98*H98) -> 0 | R122: =(R98*H98) -> 0 | S122: =(S98*H98) -> 0 | T122: =(T98*H98) -> 0 | U122: =(U98*H98) -> 0 | V122: =(V98*H98) -> 0 | W122: =(W98*H98) -> 0 | X122: =(X98*H98) -> 0 | Y122: =(Y98*H98) -> 0 | Z122: =(Z98*H98) -> 0 | AA122: =(AA98*H98) -> 0 | AB122: =(AB98*H98) -> 0 | AC122: =(AC98*H98) -> 0 | AD122: =(AD98*H98) -> 0 | AE122: =(AE98*H98) -> 0 | AF122: =(AF98*H98) -> 0 | AG122: =(AG98*H98) -> 0 | AH122: =(AH98*H98) -> 0 | AI122: =(AI98*H98) -> 0
B123: Leches frescas y fermentadas enteras altas en calorías y azucares | H123: =H99 | I123: =(I99*H99) -> 0 | J123: =(J99*H99) -> 0 | K123: =(K99*H99) -> 0 | L123: =(L99*H99) -> 0 | M123: =(M99*H99) -> 0 | N123: =(N99*H99) -> 0 | O123: =(O99*H99) -> 0 | P123: =(P99*H99) -> 0 | Q123: =(Q99*H99) -> 0 | R123: =(R99*H99) -> 0 | S123: =(S99*H99) -> 0 | T123: =(T99*H99) -> 0 | U123: =(U99*H99) -> 0 | V123: =(V99*H99) -> 0 | W123: =(W99*H99) -> 0 | X123: =(X99*H99) -> 0 | Y123: =(Y99*H99) -> 0 | Z123: =(Z99*H99) -> 0 | AA123: =(AA99*H99) -> 0 | AB123: =(AB99*H99) -> 0 | AC123: =(AC99*H99) -> 0 | AD123: =(AD99*H99) -> 0 | AE123: =(AE99*H99) -> 0 | AF123: =(AF99*H99) -> 0 | AG123: =(AG99*H99) -> 0 | AH123: =(AH99*H99) -> 0 | AI123: =(AI99*H99) -> 0
B124: Sustitutos | H124: =H100 | I124: =(I100*H100) -> 0 | J124: =(J100*H100) -> 0 | K124: =(K100*H100) -> 0 | L124: =(L100*H100) -> 0 | M124: =(M100*H100) -> 0 | N124: =(N100*H100) -> 0 | O124: =(O100*H100) -> 0 | P124: =(P100*H100) -> 0 | Q124: =(Q100*H100) -> 0 | R124: =(R100*H100) -> 0 | S124: =(S100*H100) -> 0 | T124: =(T100*H100) -> 0 | U124: =(U100*H100) -> 0 | V124: =(V100*H100) -> 0 | W124: =(W100*H100) -> 0 | X124: =(X100*H100) -> 0 | Y124: =(Y100*H100) -> 0 | Z124: =(Z100*H100) -> 0 | AA124: =(AA100*H100) -> 0 | AB124: =(AB100*H100) -> 0 | AC124: =(AC100*H100) -> 0 | AD124: =(AD100*H100) -> 0 | AE124: =(AE100*H100) -> 0 | AF124: =(AF100*H100) -> 0 | AG124: =(AG100*H100) -> 0 | AH124: =(AH100*H100) -> 0 | AI124: =(AI100*H100) -> 0
B125: Carnes magras crudas y proteínas texturizada | H125: =H101 | I125: =(I101*H101) -> 0 | J125: =(J101*H101) -> 0 | K125: =(K101*H101) -> 0 | L125: =(L101*H101) -> 0 | M125: =(M101*H101) -> 0 | N125: =(N101*H101) -> 0 | O125: =(O101*H101) -> 0 | P125: =(P101*H101) -> 0 | Q125: =(Q101*H101) -> 0 | R125: =(R101*H101) -> 0 | S125: =(S101*H101) -> 0 | T125: =(T101*H101) -> 0 | U125: =(U101*H101) -> 0 | V125: =(V101*H101) -> 0 | W125: =(W101*H101) -> 0 | X125: =(X101*H101) -> 0 | Y125: =(Y101*H101) -> 0 | Z125: =(Z101*H101) -> 0 | AA125: =(AA101*H101) -> 0 | AB125: =(AB101*H101) -> 0 | AC125: =(AC101*H101) -> 0 | AD125: =(AD101*H101) -> 0 | AE125: =(AE101*H101) -> 0 | AF125: =(AF101*H101) -> 0 | AG125: =(AG101*H101) -> 0 | AH125: =(AH101*H101) -> 0 | AI125: =(AI101*H101) -> 0
...

Sheet Ges Adoles
B2: ESTIMACIÓN Y EVALUACIÓN DE LA GANANCIA EN GESTANTE ADOLESCENTE
B4: Ganancia de peso esperada por trimestre
C5: Total | D5: 1er trimestre | E5: Promedio | F5: 2do y 3er trim | G5: % P, pregest
D6: sem 0 - 13 | E6: g/semana | F6: sem 14 - 40 | G6: Total
B7: Bajo peso | C7: 12,6kg - 18kg | D7: 2,25kg | E7: 173g | F7: >450g | G7: 35%
B8: Normo peso | C8: 11,2kg - 15,7kg | D8: 1,3kg | E8: 100g | F8: >450g | G8: 30%
B9: Sobrepeso | C9: 6,7kg - 11,3kg | D9: 0,9kg | E9: 69g | F9: >297g | G9: 20%
B10: Obesidad | C10: 6,7kg | D10: 0,675kg | E10: 52g | F10: >225g | G10: 20%
B12: Nombre
B13: Identificación | E13: Evaluación de la ganancia | H13: NOTA: Usar ajustes para semana >13
B14: Edad | E14: Semana gestacional
B15: Peso preg kg | E15: Peso kg
B16: Estatura m | E16: Debió ganar Kg | F16: =IF(F14<14,((C21/13)*F14),(C21+((C22/27)*(F14-13)))) -> 0
B17: IMC | C17: =(C15/(C16*C16)) -> #DIV/0! | E17: Ganancia presentada | F17: =F15-C15 -> 0
B18: Puntaje Z | E18: IMC gestacional | F18: =(F15/(C16*C16)) -> #DIV/0!
B19: Clasificación | C19: =IF(C18<-2,"Delgadez",IF(AND(C18>=-2,C18<-1),"Riesgo delgadez",IF(AND(C18>=-1,C18<=1),"Adecuado",IF(AND(C18>1,C18<=2),"Sobrepeso","obesidad")))) -> Adecuado
B20: Estimación de la ganancia | E20: Ajuste 1 | H20: Ajuste 1
B21: Kg Sem 0 - 13 | C21: =IF(C18<-1,"2,25",IF(AND(C18>=-1,C18<=1),"1,3",IF(AND(C18>1,C18<=2),"0,9","0,675"))) -> 1,3 | E21: Objetivo x semana g | H21: Objetivo x semana g | I21: =F21
B22: Kg Sem 14 - 40 | C22: =IF(C18<-1,"12,15",IF(AND(C18>=-1,C18<=1),"12,15",IF(AND(C18>1,C18<=2),"8","6"))) -> 12,15 | E22: Evaluación de la ganancia | H22: Evaluac ganancia absoluta | K22: AJUSTE 1 RESULTADO en Kg
B23: Total kg | C23: =(C22+C21) -> 13.45 | E23: Semana gestacional | H23: Semana gestacional | I23: =F23 | K23: Ganancia esperada entre semana | N23: =F14 | O23: y | P23: =F23 | Q23: : | R23: =F25 -> 0
B24: % Peso pregestación | E24: Peso kg | H24: Peso kg | I24: =F24 | K24: Ganancia presentada entre semana | N24: =N23 | O24: y | P24: =P23 | Q24: : | R24: =F26 -> 0
B25: Total kg | C25: =IF(C18<-1,(C15 *0.35),IF(AND(C18>=-1,C18<=1),(C15*0.3),IF(AND(C18>1,C18<=2),(C28*0.2),(C28*0.2)))) -> 0 | E25: Debió ganar Kg | F25: =(F21/1000)*(F23-F14) -> 0 | H25: Debió ganar Kg | I25: =IF(I23<14,(C21/13)*I23,C21+((C22/27)*(I23-13))) -> 0 | K25: Ganancia esperada hasta semana | N25: =P24 | O25: : | P25: =I25 -> 0
B26: En exceso de peso | E26: Ganancia presentada | F26: =F24-F15 -> 0 | H26: Ganancia presentada | I26: =F24-C15 -> 0 | K26: Ganancia absoluta hasta semana | N26: =P24 | O26: : | P26: =I26 -> 0
B27: IMC deseado | C27: 24 | E27: IMC gestacional | F27: =(F24/(C16*C16)) -> #DIV/0! | H27: IMC gestacional | I27: =(F24/(C16*C16)) -> #DIV/0!
B28: Peso saludble | C28: =(C27*(C16*C16)) -> 0
E29: Ajuste 2 | H29: Ajuste 2
E30: Objetivo x semana g | H30: Objetivo x semana g | I30: =F30
E31: Evaluación de la ganancia | H31: Evaluac ganancia absoluta | K31: AJUSTE 2 RESULTADO en Kg
E32: Semana gestacional | H32: Semana gestacional | I32: =F32 | K32: Ganancia esperada entre semana | N32: =F23 | O32: y | P32: =F32 | Q32: : | R32: =F34 -> 0
E33: Peso kg | H33: Peso kg | I33: =F33 | K33: Ganancia presentada entre semana | N33: =N32 | O33: y | P33: =P32 | Q33: : | R33: =F35 -> 0
E34: Debió ganar Kg | F34: =(F30/1000)*(F32-F23) -> 0 | H34: Debió ganar Kg | I34: =IF(I32<14,(C21/13)*I32,C21+((C22/27)*(I32-13))) -> 0 | K34: Ganancia esperada hasta semana | N34: =P33 | O34: : | P34: =I34 -> 0
E35: Ganancia presentada | F35: =F33-F24 -> 0 | H35: Ganancia presentada | I35: =F33-C15 -> 0 | K35: Ganancia absoluta hasta semana | N35: =P33 | O35: : | P35: =I35 -> 0
E36: IMC gestacional | F36: =(F33/(C16*C16)) -> #DIV/0! | H36: IMC gestacional | I36: =(F33/(C16*C16)) -> #DIV/0!
E38: Ajuste 3 | H38: Ajuste 3
E39: Objetivo x semana g | H39: Objetivo x semana g | I39: =F39
E40: Evaluación de la ganancia | H40: Evaluac ganancia absoluta | K40: AJUSTE 3 RESULTADO en Kg
E41: Semana gestacional | H41: Semana gestacional | I41: =F41 | K41: Ganancia esperada entre semana | N41: =F32 | O41: y | P41: =F41 | Q41: : | R41: =F43 -> 0
E42: Peso kg | H42: Peso kg | I42: =F42 | K42: Ganancia presentada entre semana | N42: =N41 | O42: y | P42: =P41 | Q42: : | R42: =F44 -> 0
E43: Debió ganar Kg | F43: =(F39/1000)*(F41-F32) -> 0 | H43: Debió ganar Kg | I43: =IF(I41<14,(C21/13)*I41,C21+((C22/27)*(I41-13))) -> 0 | K43: Ganancia esperada hasta semana | N43: =P42 | O43: : | P43: =I43 -> 0
E44: Ganancia presentada | F44: =F42-F33 -> 0 | H44: Ganancia presentada | I44: =F42-C24 -> 0 | K44: Ganancia absoluta hasta semana | N44: =P42 | O44: : | P44: =I44 -> 0
E45: IMC gestacional | F45: =(F42/(C25*C25)) -> #DIV/0! | H45: IMC gestacional | I45: =(F42/(C25*C25)) -> #DIV/0!
B47: REQUERIMIENTO CALÓRICO
B49: Peso preg | F49: Calorías adicionales x gestación | K49: Ganancia diaria
B50: GET | C50: =263.4+(65.3*C49)-(0.454*(C49*C49)) -> 263.4 | F50: Adicionar | G50: 1er trim | H50: 2do trim | I50: 3er trimestre | K50: Edad | L50: Gramos
B51: Gncia diaria | F51: Bajo peso | G51: 500 | H51: 500 | I51: 500 | K51: 10-11 | L51: 12,3 | U51: Moderado
B52: Actividad física | F52: Normo peso | G52: 85 | H52: 285 | I52: 475 | K52: 11-12 | L52: 12,3 | U52: Sedentario
B53: Requerimiento | C53: =U54 -> 302.91 | F53: Sobrepeso | G53: - | H53: 300 | I53: 300 | K53: 12-13 | L53: 12,6 | U53: Activo
B54: Calorías adicionales | F54: Obesidad | G54: - | H54: 200 | I54: 200 | K54: 13-14 | L54: 11,5 | U54: =IF(C52="Moderado",C50+(C51*2),IF(C52="Sedentario",(C50+(C51*2))*0.85,(C50+(C51*2))*1.15)) -> 302.91
B55: Calorías totales | D55: =SUM(D54,C53) -> 302.91 | K55: 14-15 | L55: 9,3
K56: 15-16 | L56: 6,0
K57: 16-17 | L57: 2,2
K58: 17-18 | L58: 0,0
B60: FÓRMULA SINTÉTICA PLANEADA
B62: FÓRMULA SINTÉTICA PLANEADA | I62: Recomendaciones RIEN
B63: Nutrientes | C63: Gramos | D63: Calorías | E63: % AMDR | F63: Otros | I63: Proteínas | K63: 14-20% AMDR
B64: Proteínas | C64: =(G66*C77) -> 0 | D64: =(C64*4) -> 0 | E64: =((100/D76)*D64) -> 0 | F64: g AVB | G64: =((G65/100)*C64) -> 0 | I64: Prote g/kg/peso | K64: 1.53
F65: % AVB | I65: Prote bajo peso g/kg | K65: 1.7
F66: g/kg/peso | I66: Prote AVB | K66: 60-80%
B67: Grasas | C67: =(D67/9) -> 0 | D67: =((D76/100)*E67) -> 0 | F67: g GS | G67: =(((D76/100)*G68)/9) -> 0 | I67: CHOs totales | K67: 50-65%
F68: %AMDR GS | I68: CHOs simples | K68: <10%
F69: g GM | G69: =(((D76/100)*G70)/9) -> 0 | I69: Grasa total 27,5 | K69: 20-35% AMDR
F70: %AMDR GM | G70: =(E67-G68)-G72 -> 0 | I70: G saturada | K70: <10%
F71: g GP | G71: =(((D76/100)*G72)/9) -> 0 | I71: G poli | K71: 5-10%
F72: %AMDR GP | I72: G mono | K72: GS-GM
F73: Colesterol | I73: G trans | K73: <1%
B74: CHOs | C74: =(D74/4) -> 75.7275 | D74: =((D76/100)*E74) -> 302.91 | E74: =(100-E77) -> 100 | F74: g Concent | G74: =(((D76/100)*G75)/4) -> 0 | I74: Colesterol | K74: <300mg
F75: %AMDR | I75: Colesterol enf.card | K75: <200mg
B76: Total: | D76: =D55 -> 302.91 | E76: =SUM(E64:E75) -> 100 | F76: Fibra | I76: Fibra | K76: 28g
B77: Kg Ref | C77: =C49 | D77: =SUM(D64:D75) -> 302.91 | E77: =SUM(E64:E73) -> 0 | I77: Sodio | K77: <2300mg
B79: REQUERIMIENTO FINAL
B81: Kcal | C81: Prot | D81: Grasa | E81: GS | F81: GM | G81: GP | H81: COL | I81: CHOS | J81: Fibra
B82: =D76 -> 302.91 | C82: =C64 -> 0 | D82: =C67 -> 0 | E82: =G67 -> 0 | F82: =G69 -> 0 | G82: =G71 -> 0 | H82: =G73 | I82: =C74 -> 75.7275 | J82: =G76
B84: FÓRMULA SINTÉTICA DESARROLLADA
B86: Grupo de alimentos | H86: Porciones | I86: Kcal | J86: Prot | K86: Grasa | L86: GS | M86: GM | N86: GP | O86: COL | P86: CHOS | Q86: FD | R86: Calcio (mg) | S86: P (mg) | T86: Fe (mg) | U86: Na (mg) | V86: K (mg) | W86: Mg (mg) | X86: Zn (mg) | Y86: Cu (mg) | Z86: Mn (mg) | AA86: Vit A (ER) | AB86: Tiamina (mg) | AC86: Riboflavina (mg) | AD86: Niacina (mg) | AE86: Ac, Pantotenico (mg) | AF86: Priridox. (mg) | AG86: Acido Folico (ug) | AH86: Vit B12 (ug) | AI86: Vit C (mg)
B87: Leches enteras frescas y fermentadas | I87: =(J87*4)+(K87*9)+(P87*4) -> 139.1 | J87: 6.7 | K87: 6.7 | L87: 4.4 | M87: 1.95 | N87: 0.49 | O87: 26 | P87: 13 | Q87: 0 | R87: 236 | S87: 173 | T87: 0.2 | U87: 96 | V87: 330 | W87: 25 | X87: 0.89 | Y87: 0.03 | Z87: 0.01 | AA87: 73 | AB87: 0.08 | AC87: 0.34 | AD87: 0.3 | AE87: 0.67 | AF87: 0.08 | AG87: 10 | AH87: 0.65 | AI87: 3
B88: Leches semidescremadas frescas y fermentadas | I88: =(J88*4)+(K88*9)+(P88*4) -> 94.5 | J88: 5.4 | K88: 2.1 | L88: 0.87 | M88: 0.54 | N88: 0.35 | O88: 5 | P88: 13.5 | Q88: 0.8 | R88: 153 | S88: 143 | T88: 0.4 | U88: 72 | V88: 268 | W88: 25 | X88: 1.24 | Y88: 0.06 | Z88: 0.11 | AA88: 76 | AB88: 0.12 | AC88: 0.25 | AD88: 0.2 | AE88: 0.41 | AF88: 0.06 | AG88: 8 | AH88: 0.5 | AI88: 4
B89: Leches descremadas frescas y fermentadas | I89: =(J89*4)+(K89*9)+(P89*4) -> 82.3 | J89: 9 | K89: 0.7 | L89: 0.45 | M89: 0.18 | N89: 0.03 | O89: 6 | P89: 10 | Q89: 0 | R89: 256 | S89: 214 | T89: 0.1 | U89: 101 | V89: 340 | W89: 24 | X89: 1.05 | Y89: 0.02 | Z89: 0.01 | AA89: 89 | AB89: 0.08 | AC89: 0.33 | AD89: 0.2 | AE89: 0.79 | AF89: 0.08 | AG89: 14 | AH89: 0.84 | AI89: 2
B90: Leches frescas y fermentadas enteras altas en calorías y azucares | I90: =(J90*4)+(K90*9)+(P90*4) -> 170.7 | J90: 6.4 | K90: 5.9 | L90: 3.8 | M90: 1.91 | N90: 0.63 | O90: 22 | P90: 23 | Q90: 0.4 | R90: 258 | S90: 169 | T90: 0.3 | U90: 115 | V90: 334 | W90: 27 | X90: 1.03 | Y90: 0.05 | Z90: 0.04 | AA90: 45 | AB90: 0.08 | AC90: 0.37 | AD90: 0.2 | AE90: 0.73 | AF90: 0.08 | AG90: 13 | AH90: 0.76 | AI90: 3
B91: Sustitutos | I91: =(J91*4)+(K91*9)+(P91*4) -> 77.1 | J91: 5.8 | K91: 5.5 | L91: 2.91 | M91: 1.94 | N91: 0.41 | O91: 40 | P91: 1.1 | Q91: 0 | R91: 95 | S91: 85 | T91: 1.1 | U91: 211 | V91: 52 | W91: 6 | X91: 0.65 | Y91: 0.03 | Z91: 0.01 | AA91: 45 | AB91: 0.04 | AC91: 0.1 | AD91: 0.4 | AE91: 0.16 | AF91: 0.05 | AG91: 4 | AH91: 0.72 | AI91: 0
B92: Carnes magras crudas y proteínas texturizada | I92: =(J92*4)+(K92*9)+(P92*4) -> 108.3 | J92: 19.1 | K92: 3.1 | L92: 0.92 | M92: 1.16 | N92: 0.53 | O92: 50 | P92: 1 | Q92: 0.3 | R92: 22 | S92: 191 | T92: 1.5 | U92: 72 | V92: 325 | W92: 28 | X92: 1.81 | Y92: 0.11 | Z92: 0.12 | AA92: 7 | AB92: 0.19 | AC92: 0.18 | AD92: 5.6 | AE92: 0.78 | AF92: 0.35 | AG92: 15 | AH92: 2.39 | AI92: 1
B93: Carnes crudas altas en lípidos | I93: =(J93*4)+(K93*9)+(P93*4) -> 138.7 | J93: 15.6 | K93: 7.9 | L93: 2.51 | M93: 3.3 | N93: 1.25 | O93: 137 | P93: 1.3 | Q93: 0 | R93: 37 | S93: 186 | T93: 2.5 | U93: 101 | V93: 234 | W93: 20 | X93: 1.87 | Y93: 0.47 | Z93: 0.09 | AA93: 1515 | AB93: 0.07 | AC93: 0.53 | AD93: 4.4 | AE93: 1.67 | AF93: 0.27 | AG93: 87 | AH93: 10.58 | AI93: 6
B94: Leguminosas adultos | I94: =(J94*4)+(K94*9)+(P94*4) -> 158.1 | J94: 9.8 | K94: 1.7 | L94: 0.25 | M94: 0.32 | N94: 0.94 | O94: 0 | P94: 25.9 | Q94: 7.9 | R94: 50 | S94: 167 | T94: 3.1 | U94: 10 | V94: 534 | W94: 62 | X94: 1.22 | Y94: 0.28 | Z94: 0.6 | AA94: 10 | AB94: 0.2 | AC94: 0.09 | AD94: 0.9 | AE94: 0.42 | AF94: 0.16 | AG94: 142 | AH94: 0 | AI94: 4
B95: Cereales adultos | I95: =(J95*4)+(K95*9)+(P95*4) -> 93.8 | J95: 2.5 | K95: 1 | L95: 0.24 | M95: 0.32 | N95: 0.33 | O95: 1 | P95: 18.7 | Q95: 1.2 | R95: 19 | S95: 47 | T95: 0.9 | U95: 82 | V95: 53 | W95: 13 | X95: 0.42 | Y95: 0.05 | Z95: 0.24 | AA95: 22 | AB95: 0.11 | AC95: 0.09 | AD95: 1.1 | AE95: 0.15 | AF95: 0.08 | AG95: 38 | AH95: 0 | AI95: 2
B96: Raíces, tubérculos y plátanos adultos | I96: =(J96*4)+(K96*9)+(P96*4) -> 95.7 | J96: 1.4 | K96: 0.1 | L96: 0.05 | M96: 0.01 | N96: 0.06 | O96: 0 | P96: 22.3 | Q96: 1.9 | R96: 11 | S96: 40 | T96: 0.5 | U96: 10 | V96: 376 | W96: 20 | X96: 0.23 | Y96: 0.13 | Z96: 0.25 | AA96: 156 | AB96: 0.05 | AC96: 0.04 | AD96: 0.9 | AE96: 0.29 | AF96: 0.21 | AG96: 13 | AH96: 0 | AI96: 28
B97: Promedio "Harinas" adultos | I97: =(J97*4)+(K97*9)+(P97*4) -> 95.4 | J97: 2 | K97: 0.6 | L97: 0.14 | M97: 0.16 | N97: 0.19 | O97: 0 | P97: 20.5 | Q97: 1.5 | R97: 15 | S97: 43 | T97: 0.7 | U97: 46 | V97: 214 | W97: 17 | X97: 0.33 | Y97: 0.09 | Z97: 0.24 | AA97: 89 | AB97: 0.08 | AC97: 0.07 | AD97: 1 | AE97: 0.22 | AF97: 0.15 | AG97: 26 | AH97: 0 | AI97: 15
B98: Verduras y hortalizas adultos y niños | I98: =(J98*4)+(K98*9)+(P98*4) -> 29.5 | J98: 1.2 | K98: 0.3 | L98: 0.05 | M98: 0.03 | N98: 0.13 | O98: 0 | P98: 5.5 | Q98: 1.7 | R98: 15 | S98: 32 | T98: 0.7 | U98: 68 | V98: 187 | W98: 12 | X98: 0.29 | Y98: 0.1 | Z98: 0.16 | AA98: 136 | AB98: 0.05 | AC98: 0.06 | AD98: 0.8 | AE98: 0.37 | AF98: 0.09 | AG98: 23 | AH98: 0 | AI98: 19
... B107: Productos con reducción de grasa adultos y niños | I107: =(J107*4)+(K107*9)+(P107*4) -> 39.3 | J107: 1.3 | K107: 3.3 | L107: 1.16 | M107: 0.98 | N107: 0.89 | O107: 6 | P107: 1.1 | Q107: 0 | R107: 16 | S107: 37 | T107: 0 | U107: 125 | V107: 19 | W107: 2 | X107: 0.12 | Y107: 0 | Z107: 0 | AA107: 41 | AB107: 0 | AC107: 0.02 | AD107: 0 | AE107: 0.04 | AF107: 0.03 | AG107: 3 | AH107: 0.06 | AI107: 0
B108: Grasas saturadas | I108: =((J108*4)+(K108*9)+(P108*4)) -> 45.6 | J108: 0.3 | K108: 4.8 | L108: 2.66 | M108: 1.57 | N108: 0.28 | O108: 10 | P108: 0.3 | Q108: 0 | R108: 8 | S108: 7 | T108: 0 | U108: 9 | V108: 10 | W108: 1 | X108: 0.03 | Y108: 0 | Z108: 0 | AA108: 31 | AB108: 0 | AC108: 0.01 | AD108: 0 | AE108: 0.03 | AF108: 0 | AG108: 1 | AH108: 0.03 | AI108: 0
B109: Productos con reducción de grasa | I109: =((J109*4)+(K109*9)+(P109*4)) -> 45.1 | J109: 0.9 | K109: 4.3 | L109: 1.88 | M109: 0.99 | N109: 1.73 | O109: 22 | P109: 0.7 | Q109: 0 | R109: 22 | S109: 37 | T109: 0 | U109: 99 | V109: 17 | W109: 2 | X109: 0.07 | Y109: 0 | Z109: 0 | AA109: 144 | AB109: 0 | AC109: 0.02 | AD109: 0 | AE109: 0.04 | AF109: 0 | AG109: 3 | AH109: 0.06 | AI109: 0
B112: Grupo de alimentos | H112: Porciones | I112: Kcal | J112: Prot | K112: Grasa | L112: GS | M112: GM | N112: GP | O112: COL | P112: CHOS | Q112: FD | R112: Calcio (mg) | S112: P (mg) | T112: Fe (mg) | U112: Na (mg) | V112: K (mg) | W112: Mg (mg) | X112: Zn (mg) | Y112: Cu (mg) | Z112: Mn (mg) | AA112: Vit A (ER) | AB112: Tiamina (mg) | AC112: Riboflavina (mg) | AD112: Niacina (mg) | AE112: Ac, Pantotenico (mg) | AF112: Priridox. (mg) | AG112: Acido Folico (ug) | AH112: Vit B12 (ug) | AI112: Vit C (mg)
B113: Leches enteras frescas y fermentadas | H113: =H87 | I113: =(I87*H87) -> 0 | J113: =(J87*H87) -> 0 | K113: =(K87*H87) -> 0 | L113: =(L87*H87) -> 0 | M113: =(M87*H87) -> 0 | N113: =(N87*H87) -> 0 | O113: =(O87*H87) -> 0 | P113: =(P87*H87) -> 0 | Q113: =(Q87*H87) -> 0 | R113: =(R87*H87) -> 0 | S113: =(S87*H87) -> 0 | T113: =(T87*H87) -> 0 | U113: =(U87*H87) -> 0 | V113: =(V87*H87) -> 0 | W113: =(W87*H87) -> 0 | X113: =(X87*H87) -> 0 | Y113: =(Y87*H87) -> 0 | Z113: =(Z87*H87) -> 0 | AA113: =(AA87*H87) -> 0 | AB113: =(AB87*H87) -> 0 | AC113: =(AC87*H87) -> 0 | AD113: =(AD87*H87) -> 0 | AE113: =(AE87*H87) -> 0 | AF113: =(AF87*H87) -> 0 | AG113: =(AG87*H87) -> 0 | AH113: =(AH87*H87) -> 0 | AI113: =(AI87*H87) -> 0
B114: Leches semidescremadas frescas y fermentadas | H114: =H88 | I114: =(I88*H88) -> 0 | J114: =(J88*H88) -> 0 | K114: =(K88*H88) -> 0 | L114: =(L88*H88) -> 0 | M114: =(M88*H88) -> 0 | N114: =(N88*H88) -> 0 | O114: =(O88*H88) -> 0 | P114: =(P88*H88) -> 0 | Q114: =(Q88*H88) -> 0 | R114: =(R88*H88) -> 0 | S114: =(S88*H88) -> 0 | T114: =(T88*H88) -> 0 | U114: =(U88*H88) -> 0 | V114: =(V88*H88) -> 0 | W114: =(W88*H88) -> 0 | X114: =(X88*H88) -> 0 | Y114: =(Y88*H88) -> 0 | Z114: =(Z88*H88) -> 0 | AA114: =(AA88*H88) -> 0 | AB114: =(AB88*H88) -> 0 | AC114: =(AC88*H88) -> 0 | AD114: =(AD88*H88) -> 0 | AE114: =(AE88*H88) -> 0 | AF114: =(AF88*H88) -> 0 | AG114: =(AG88*H88) -> 0 | AH114: =(AH88*H88) -> 0 | AI114: =(AI88*H88) -> 0
B115: Leches descremadas frescas y fermentadas | H115: =H89 | I115: =(I89*H89) -> 0 | J115: =(J89*H89) -> 0 | K115: =(K89*H89) -> 0 | L115: =(L89*H89) -> 0 | M115: =(M89*H89) -> 0 | N115: =(N89*H89) -> 0 | O115: =(O89*H89) -> 0 | P115: =(P89*H89) -> 0 | Q115: =(Q89*H89) -> 0 | R115: =(R89*H89) -> 0 | S115: =(S89*H89) -> 0 | T115: =(T89*H89) -> 0 | U115: =(U89*H89) -> 0 | V115: =(V89*H89) -> 0 | W115: =(W89*H89) -> 0 | X115: =(X89*H89) -> 0 | Y115: =(Y89*H89) -> 0 | Z115: =(Z89*H89) -> 0 | AA115: =(AA89*H89) -> 0 | AB115: =(AB89*H89) -> 0 | AC115: =(AC89*H89) -> 0 | AD115: =(AD89*H89) -> 0 | AE115: =(AE89*H89) -> 0 | AF115: =(AF89*H89) -> 0 | AG115: =(AG89*H89) -> 0 | AH115: =(AH89*H89) -> 0 | AI115: =(AI89*H89) -> 0
B116: Leches frescas y fermentadas enteras altas en calorías y azucares | H116: =H90 | I116: =(I90*H90) -> 0 | J116: =(J90*H90) -> 0 | K116: =(K90*H90) -> 0 | L116: =(L90*H90) -> 0 | M116: =(M90*H90) -> 0 | N116: =(N90*H90) -> 0 | O116: =(O90*H90) -> 0 | P116: =(P90*H90) -> 0 | Q116: =(Q90*H90) -> 0 | R116: =(R90*H90) -> 0 | S116: =(S90*H90) -> 0 | T116: =(T90*H90) -> 0 | U116: =(U90*H90) -> 0 | V116: =(V90*H90) -> 0 | W116: =(W90*H90) -> 0 | X116: =(X90*H90) -> 0 | Y116: =(Y90*H90) -> 0 | Z116: =(Z90*H90) -> 0 | AA116: =(AA90*H90) -> 0 | AB116: =(AB90*H90) -> 0 | AC116: =(AC90*H90) -> 0 | AD116: =(AD90*H90) -> 0 | AE116: =(AE90*H90) -> 0 | AF116: =(AF90*H90) -> 0 | AG116: =(AG90*H90) -> 0 | AH116: =(AH90*H90) -> 0 | AI116: =(AI90*H90) -> 0
B117: Sustitutos | H117: =H91 | I117: =(I91*H91) -> 0 | J117: =(J91*H91) -> 0 | K117: =(K91*H91) -> 0 | L117: =(L91*H91) -> 0 | M117: =(M91*H91) -> 0 | N117: =(N91*H91) -> 0 | O117: =(O91*H91) -> 0 | P117: =(P91*H91) -> 0 | Q117: =(Q91*H91) -> 0 | R117: =(R91*H91) -> 0 | S117: =(S91*H91) -> 0 | T117: =(T91*H91) -> 0 | U117: =(U91*H91) -> 0 | V117: =(V91*H91) -> 0 | W117: =(W91*H91) -> 0 | X117: =(X91*H91) -> 0 | Y117: =(Y91*H91) -> 0 | Z117: =(Z91*H91) -> 0 | AA117: =(AA91*H91) -> 0 | AB117: =(AB91*H91) -> 0 | AC117: =(AC91*H91) -> 0 | AD117: =(AD91*H91) -> 0 | AE117: =(AE91*H91) -> 0 | AF117: =(AF91*H91) -> 0 | AG117: =(AG91*H91) -> 0 | AH117: =(AH91*H91) -> 0 | AI117: =(AI91*H91) -> 0
B118: Carnes magras crudas y proteínas texturizada | H118: =H92 | I118: =(I92*H92) -> 0 | J118: =(J92*H92) -> 0 | K118: =(K92*H92) -> 0 | L118: =(L92*H92) -> 0 | M118: =(M92*H92) -> 0 | N118: =(N92*H92) -> 0 | O118: =(O92*H92) -> 0 | P118: =(P92*H92) -> 0 | Q118: =(Q92*H92) -> 0 | R118: =(R92*H92) -> 0 | S118: =(S92*H92) -> 0 | T118: =(T92*H92) -> 0 | U118: =(U92*H92) -> 0 | V118: =(V92*H92) -> 0 | W118: =(W92*H92) -> 0 | X118: =(X92*H92) -> 0 | Y118: =(Y92*H92) -> 0 | Z118: =(Z92*H92) -> 0 | AA118: =(AA92*H92) -> 0 | AB118: =(AB92*H92) -> 0 | AC118: =(AC92*H92) -> 0 | AD118: =(AD92*H92) -> 0 | AE118: =(AE92*H92) -> 0 | AF118: =(AF92*H92) -> 0 | AG118: =(AG92*H92) -> 0 | AH118: =(AH92*H92) -> 0 | AI118: =(AI92*H92) -> 0
B119: Carnes crudas altas en lípidos | H119: =H93 | I119: =(I93*H93) -> 0 | J119: =(J93*H93) -> 0 | K119: =(K93*H93) -> 0 | L119: =(L93*H93) -> 0 | M119: =(M93*H93) -> 0 | N119: =(N93*H93) -> 0 | O119: =(O93*H93) -> 0 | P119: =(P93*H93) -> 0 | Q119: =(Q93*H93) -> 0 | R119: =(R93*H93) -> 0 | S119: =(S93*H93) -> 0 | T119: =(T93*H93) -> 0 | U119: =(U93*H93) -> 0 | V119: =(V93*H93) -> 0 | W119: =(W93*H93) -> 0 | X119: =(X93*H93) -> 0 | Y119: =(Y93*H93) -> 0 | Z119: =(Z93*H93) -> 0 | AA119: =(AA93*H93) -> 0 | AB119: =(AB93*H93) -> 0 | AC119: =(AC93*H93) -> 0 | AD119: =(AD93*H93) -> 0 | AE119: =(AE93*H93) -> 0 | AF119: =(AF93*H93) -> 0 | AG119: =(AG93*H93) -> 0 | AH119: =(AH93*H93) -> 0 | AI119: =(AI93*H93) -> 0
B120: Leguminosas adultos | H120: =H94 | I120: =(I94*H94) -> 0 | J120: =(J94*H94) -> 0 | K120: =(K94*H94) -> 0 | L120: =(L94*H94) -> 0 | M120: =(M94*H94) -> 0 | N120: =(N94*H94) -> 0 | O120: =(O94*H94) -> 0 | P120: =(P94*H94) -> 0 | Q120: =(Q94*H94) -> 0 | R120: =(R94*H94) -> 0 | S120: =(S94*H94) -> 0 | T120: =(T94*H94) -> 0 | U120: =(U94*H94) -> 0 | V120: =(V94*H94) -> 0 | W120: =(W94*H94) -> 0 | X120: =(X94*H94) -> 0 | Y120: =(Y94*H94) -> 0 | Z120: =(Z94*H94) -> 0 | AA120: =(AA94*H94) -> 0 | AB120: =(AB94*H94) -> 0 | AC120: =(AC94*H94) -> 0 | AD120: =(AD94*H94) -> 0 | AE120: =(AE94*H94) -> 0 | AF120: =(AF94*H94) -> 0 | AG120: =(AG94*H94) -> 0 | AH120: =(AH94*H94) -> 0 | AI120: =(AI94*H94) -> 0
B121: Cereales adultos | H121: =H95 | I121: =(I95*H95) -> 0 | J121: =(J95*H95) -> 0 | K121: =(K95*H95) -> 0 | L121: =(L95*H95) -> 0 | M121: =(M95*H95) -> 0 | N121: =(N95*H95) -> 0 | O121: =(O95*H95) -> 0 | P121: =(P95*H95) -> 0 | Q121: =(Q95*H95) -> 0 | R121: =(R95*H95) -> 0 | S121: =(S95*H95) -> 0 | T121: =(T95*H95) -> 0 | U121: =(U95*H95) -> 0 | V121: =(V95*H95) -> 0 | W121: =(W95*H95) -> 0 | X121: =(X95*H95) -> 0 | Y121: =(Y95*H95) -> 0 | Z121: =(Z95*H95) -> 0 | AA121: =(AA95*H95) -> 0 | AB121: =(AB95*H95) -> 0 | AC121: =(AC95*H95) -> 0 | AD121: =(AD95*H95) -> 0 | AE121: =(AE95*H95) -> 0 | AF121: =(AF95*H95) -> 0 | AG121: =(AG95*H95) -> 0 | AH121: =(AH95*H95) -> 0 | AI121: =(AI95*H95) -> 0
B122: Raíces, tubérculos y plátanos adultos | H122: =H96 | I122: =(I96*H96) -> 0 | J122: =(J96*H96) -> 0 | K122: =(K96*H96) -> 0 | L122: =(L96*H96) -> 0 | M122: =(M96*H96) -> 0 | N122: =(N96*H96) -> 0 | O122: =(O96*H96) -> 0 | P122: =(P96*H96) -> 0 | Q122: =(Q96*H96) -> 0 | R122: =(R96*H96) -> 0 | S122: =(S96*H96) -> 0 | T122: =(T96*H96) -> 0 | U122: =(U96*H96) -> 0 | V122: =(V96*H96) -> 0 | W122: =(W96*H96) -> 0 | X122: =(X96*H96) -> 0 | Y122: =(Y96*H96) -> 0 | Z122: =(Z96*H96) -> 0 | AA122: =(AA96*H96) -> 0 | AB122: =(AB96*H96) -> 0 | AC122: =(AC96*H96) -> 0 | AD122: =(AD96*H96) -> 0 | AE122: =(AE96*H96) -> 0 | AF122: =(AF96*H96) -> 0 | AG122: =(AG96*H96) -> 0 | AH122: =(AH96*H96) -> 0 | AI122: =(AI96*H96) -> 0
...

Sheet Hospitalizado
B2: PACIENTE HOSPITALIZADO
B4: EVALUACIÓN ANTROPOMÉTRICA | E4: GASTO ENERGÉTICO | I4: FACTOR DE ACTIVIDAD
B5: Nombre | E5: Sexo | G5: Hombre | H5: =IF(G5="Hombre",1,0) -> 1 | I5: Inconsciente/Coma | K5: 1
B6: Apellido | E6: Peso Kg | I6: En cama | K6: 1,1 - 1,2
B7: Identificación | E7: Altura cm | I7: Ambulatorio | K7: 1.3
B8: Sexo | C8: Hombre | E8: Edad años | I8: FACTOR DE ESTRÉS
B9: Edad años | E9: Factor actividad | G9: 1 | I9: Cirugía mayor | K9: 1.2
B10: Peso kg | E10: Factor estrés | G10: 1 | I10: Cirugía menor | K10: 1.1
B11: Altura m | E11: Harris y Benedict | I11: Infección leve | K11: 1.2
B12: Altura cm | C12: =C11*100 -> 0 | E12: Requerimiento total | G12: =IF(G5="Hombre",((67.47+(13.75*(G6))+(5*(G7))-(6.78*(G8)))*G9*G10),((655.1+(9.56*(G6))+(1.85*(G7))-(4.68*(G8)))*G9*G10)) -> 67.47 | I12: Infección moderada | K12: 1.5
B13: Estimación Talla | E13: Mifflin y St Jeor | I13: Infección severa | K13: 1.8
B14: Talón rodilla cm | E14: Requerimiento total | G14: =IF(G5="Hombre",(((10*(G6))+(6.25*(G7))-(5*(G8))+5)*G9*G10),(((10*(G6))+(6.25*(G7))-(5*(G8))-161)*G9*G10)) -> 5 | I14: Trauma esqueleto | K14: 1.35
B15: Talla estimada cm | C15: =IF(C8="Hombre",((2.02*C14)-(0.04*C9)+64.19),((1.83*C14)-(0.24*C9)+84.88)) -> 64.19 | E15: Ireton y Jones | I15: Trauma contusión | K15: 1.35
B16: Estimación Peso | E16: Soporte ventilatorio | G16: No | I16: Lesión de cabeza | K16: 1.6
B17: Talón rodilla cm | E17: Obesidad | G17: No | H17: =IF(G17="Sí",1,0) -> 0 | I17: Quemadura 40% | K17: 1.5
B18: Perimetro brazo cm | E18: Trauma | G18: No | H18: =IF(G18="Sí",1,0) -> 0 | I18: Quemadura 100% | K18: 1.96
B19: Perimetro pantorrilla cm | E19: Quemadura | G19: No | H19: =IF(G19="Sí",1,0) -> 0 | I19: Peritonitis | K19: 1,05 - 1,25
B20: Pliegue subescapular mm | E20: Requerimiento total | G20: =IF(G16="Sí",(1925-(10*(G8))+(5*(G6))+(28*H5)+(292*H18)+(851*H19)),(629-(11*(G8))+(25*(G6))-(609*H17))) -> 629 | I20: Cáncer | K20: 1,1 - 1,45
B21: Estimación del peso Kg | C21: =IF(C8="Hombre",((C18*1.73)+(C19*0.98)+(C20*0.37)+(C17*1.16)-81.69),((C18*0.98)+(C19*1.27)+(C20*0.4)+(C17*0.87)-62.35)) -> -81.69 | E21: Método del pulgar
E22: Kcal/kg/Día
B23: PESO SALUDABLE IMC | E23: Requerimiento total | G23: =G22*G6 -> 0 | I23: Para el cálculo de requerimiento SIEMPRE debe colocar factor de actividad y estrés. Calcule el requerimiento con el peso actual en caso de desnutrición; con peso ideal en sobrepeso; y con peso ajustado en obesidad.
B24: Peso kg
B25: Talla m | E25: LÍQUIDOS
B26: IMC | C26: =(C24/(C25*C25)) -> #DIV/0! | E26: cc/kg/día | M26: Referencias
B27: IMC deseado | E27: ml totales | G27: =G26*G6 -> 0 | M27: Estimación talla: Chumlea W, Roche A, Steinbaugh M. Estimating stature from knee height for persons 60-90 years of age. J Am Geriatr Soc 1985; 33: 116-120.
B28: Peso saludable IMC 25-30 | E28: Calcule los líquidos con peso actual idealmente con 30cc a 40cc | M28: Estimación peso: Chumlea WC, Guo S, Roche AF, Steinbaugh ML. Prediction of body weight for the nonambulatory elderly from anthropo – metry. J Am Diet Assoc 1988; 88 (5): 564-568
B29: PS | C29: =(C27*(C25*C25)) -> 0 | M29: Ec Harris y Benedict: Banta, A. M. (1918). Sex and Sex Intergrades in Cladocera. Proceedings of the National Academy of Sciences, 4(12), 373–379. doi:10.1073/pnas.4.12.373
B30: Peso ajustado IMC >30 | M30: Ec Miflin y St Jeor: Am J Clin Nutr 1990; 51: 241-7.
B31: PA | C31: =(C29+(0.25*(C24-C29))) -> 0
B33: NUTRICIÓN PARENTERAL ADULTO
B35: 1. Introduzca las calorías y la cantidad de líquido que va a suministrar al paciente
B37: Peso del paciente (kg)
B38: Calorías totales
B39: Líquidos totales (ml)
B41: 2. Defina el aporte de macro y micronutrientes, guiese por la tabla adjunta
B43: Proteína (g/kg/día) | D43: =F65*4 -> 0 | E43: Requerimientos usuales | K43: =IF(AND(C45<>0, OR(C45<2,C45>5)),"La admon de CHOs debe hacerse con un flujo de 2 – 5 mg/kg/min, un valor menor favorece la gluconeogénesis; un valor mayor excede la capacidad de oxidación lo que causa hiperglicemia, diuresis osmótica y coma hiperosmolar no cetósico","") | O43: La cantidad de lípidos es el resultado de la diferencia del total de calorias, con las calorias de (CHOs + proteína), que se requieren para completar el total de calorias programadas
B44: CHOs (g/kg/día) | D44: =F66*3.4 -> 0 | E44: Proteína (g/kg/día) | G44: 0,8 - 1,8
B45: Flujo metabolico(mg/kg/min) | C45: =(C44*1000)/1440 -> 0 | D45: =C38-(D43+D44) -> 0 | E45: CHOs (g/kg/día) | G45: 3,0 - 7,0
B46: Lípidos (g/kg/día) | C46: =D46/C37 -> #DIV/0! | D46: =D45/(IF(G57="Omegaven 10%",11,10)) -> 0 | E46: Lípidos (g/kg/día) | G46: Estable | I46: 0,7 - 1,3
B47: Sodio (mEq/kg) | G47: Alta demanda energética | I47: 1,5 - 2,5
B48: Potasio (mEq/kg) | E48: Sodio (mEq/kg) | G48: 1 - 2
B49: Calcio (mEq/día) | E49: Potasio (mEq/kg) | G49: 1 - 2
B50: Fósforo (mMol/día) | E50: Calcio (mEq/día) | G50: 10 - 15
B51: Magnesio (mEq/día) | E51: Fósforo (mMol/día) | G51: 20 - 40
E52: Magnesio (mEq/día) | G52: 8 - 20
B54: 3. Defina los productos que va a usar en la nutrición parenteral
B56: Nutriente | C56: Aminoácidos | E56: Dextrosa | G56: Lípidos | I56: Sodio | K56: Potasio | M56: Calcio | O56: Magnesio | Q56: Fósforo
B57: Producto
B59: Nutriente | C59: Vitaminas | E59: Oligoelementos | H59: *S.E Sin electrólitos; C.E Con electrólitos
B60: Producto
B62: 4. De acuerdo a lo anterior la siguiente tabla presenta el resumen de la NPT
B64: Producto | C64: Nutriente | D64: Cantidad en producto | F64: Necesidad | H64: Volumen ml | I64: mOsml/L | J64: mOsml total
B65: =C57 | C65: =C56 -> Aminoácidos | D65: =IF(OR(C57="Aminoven adultos 15%", C57="Travasol plus 15%"), 0.15, 0.1) -> 0.1 | E65: g/ml | F65: =C43*C37 -> 0 | G65: g/día | H65: =F65/D65 -> 0 | I65: =IF(C57="Aminoven adultos 10%",E82,(IF(C57="Aminoven adultos 15%",E83,(IF(C57="Trophamine 10%",E84,(IF(C57="Aminoplasmal 10%",E85,(IF(C57="Primene 10%",E86,(IF(C57="Travasol 10% S.E",E87,(IF(C57="Travasol 10% C.E",E88,(IF(C57="Travasol plus 15%",E89,0))))))))))))))) -> 0 | J65: =(H65*I65)/1000 -> 0 | L65: Tenga en cuenta que el programa resta automaticamente el excedente de sodio o potasio aportado por el Glicerol fosfato de sodio o Fosfato de potasio respectivamente
B66: =E57 | C66: =E56 -> Dextrosa | D66: =IF(E57="Baxter 20%", 0.2, IF(E57="Baxter 70%",0.7,0.5)) -> 0.5 | E66: g/ml | F66: =C44*C37 -> 0 | G66: g/día | H66: =F66/D66 -> 0 | I66: =IF(E57="Baxter 20%",E90,(IF(E57="Baxter 70%",E92,(IF(E57="Corpaul 50%",E93,(IF(E57="Baxter 50%",E91,(IF(E57="FreseniusKabi 50%",E94,0))))))))) -> 0 | J66: =(H66*I66)/1000 -> 0
B67: =G57 | C67: =G56 -> Lípidos | D67: =IF(G57="Omegaven 10%", 0.1,0.2 ) -> 0.2 | E67: g/ml | F67: =C46*C37 -> #DIV/0! | G67: g/día | H67: =F67/D67 -> #DIV/0! | I67: =IF(G57="Smoflipid 20%",E95,(IF(G57="Lipovenos 20%",E96,(IF(G57="Clinoleic 20%",E97,(IF(G57="Lipofundin 20%",E98,(IF(G57="Omegaven 10%",E99,0))))))))) -> 0 | J67: =(H67*I67)/1000 -> #DIV/0!
B68: =I57 | C68: =I56 -> Sodio | D68: 2 | E68: mEq/ml | F68: =IF(C73="Sodio",((C47*C37)-F73),(C47*C37)) -> 0 | G68: mEq/día | H68: =F68/D68 -> 0 | I68: =IF(I57="Cloruro de sodio (Natrol)",4000,0) -> 0 | J68: =(H68*I68)/1000 -> 0
B69: =K57 | C69: =K56 -> Potasio | D69: 2 | E69: mEq/ml | F69: =IF(C73="Potasio",((C48*C37)-F73),(C48*C37)) -> 0 | G69: mEq/día | H69: =F69/D69 -> 0 | I69: =IF(K57="Cloruro de potasio (katrol)",4000,0) -> 0 | J69: =(H69*I69)/1000 -> 0
B70: =M57 | C70: =M56 -> Calcio | D70: 0.46 | E70: mEq/ml | F70: =C49 | G70: mEq/día | H70: =F70/D70 -> 0 | I70: =IF(M57="Gluconato de calcio 10%",703,0) -> 0 | J70: =(H70*I70)/1000 -> 0
B71: =O57 | C71: =O56 -> Magnesio | D71: 1.62 | E71: mEq/ml | F71: =C51 | G71: mEq/día | H71: =F71/D71 -> 0 | I71: =IF(O57="Sulfato de magnesio 20%",1626,0) -> 0 | J71: =(H71*I71)/1000 -> 0
B72: =Q57 | C72: =Q56 -> Fósforo | D72: =IF(Q57="Fosfato de potasio Corpaul",2.5,1) -> 1 | E72: mMol/ml | F72: =C50 | G72: mMol/día | H72: =F72/D72 -> 0 | I72: =IF(Q57="Fosfato de potasio Corpaul",E104,(IF(Q57="Glicerol fosfato de sodio",E105,0))) -> 0 | J72: =(H72*I72)/1000 -> 0
C73: =IF(Q57="Fosfato de potasio Corpaul","Potasio","Sodio") -> Sodio | D73: =IF(Q57="Fosfato de potasio Corpaul",3.8,2) -> 2 | E73: mEq/ml | F73: =D73*H72 -> 0 | G73: mEq/día
B74: =C60 | C74: Vitaminas | D74: No aplica | F74: No aplica | H74: =IF(B74="Cernevit",5,(IF(C60="Soluvit+Vitalipid",20,0))) -> 0 | I74: =IF(C60="Cernevit",E107,(IF(C60="Soluvit+Vitalipid",E106,0))) -> 0 | J74: =(H74*I74)/1000 -> 0
B75: =E60 | C75: Oligoelementos | D75: No aplica | F75: No aplica | H75: =IF(OR(E60="Nulanza",E60="Addaven"),10,0) -> 0 | I75: =IF(OR(E60="Nulanza",E60="Addaven"),E108,0) -> 0 | J75: =(H75*I75)/1000 -> 0 | L75: =IF(C60="Cernevit","Cernevit no contiene Vit K, aplique 10mg/ml semanalmente","")
B76: Agua estéril | C76: Agua | D76: No aplica | F76: No aplica | H76: =H77-SUM(H65:H75) -> #DIV/0! | I76: 0 | J76: =(H76*I76)/1000 -> #DIV/0! | K76: =SUM(J65:J75) -> #DIV/0!
B77: TOTAL | H77: =C39 | I77: No aplica | J77: =(K76/H77)*1000 -> #DIV/0!
B79: 5. Tenga en cuenta la osmolaridad de cada uno de los productos relacionados, si usa un producto de marca u osmolaridad diferente se podrán presentar errores
B81: Producto | C81: Nombre | D81: Marca | E81: Osmolaridad/L
B82: Aminoacidos 10% | C82: Aminoven 10% | D82: Fresenius | E82: 990
B83: Aminoacidos 15% | C83: Aminoven 15% | D83: Fresenius | E83: 1505
B84: Aminoacidos 10% | C84: Trophamine | D84: Bbraun | E84: 875
B85: Aminoacidos 10% | C85: Aminoplasmal | D85: Bbraun | E85: 1030
B86: Aminoacidos 10% | C86: Primene 10% | D86: Baxter | E86: 780
B87: Aminoacidos 10% | C87: Travasol 10% S.E | D87: Baxter | E87: 996
B88: Aminoacidos 10% | C88: Travasol 10% C.E | D88: Baxter | E88: 1300
B89: Aminoacidos 15% | C89: Travasol plus | D89: Baxter | E89: 1357
B90: Dextrosa 20% | C90: Dextrosa 20% | D90: Baxter | E90: 1100
B91: Dextrosa 50% | C91: Dextrosa 50% | D91: Baxter | E91: 2775
B92: Dextrosa 70% | C92: Dextrosa 70% | D92: Baxter | E92: 3885
B93: Dextrosa 50% | C93: Dextrosa 50% | D93: Corpaul | E93: 2780
... B109: Elementos traza | C109: Nulanza | D109: Fresenius | E109: 3100

Sheet Deportista
B2: SOMATOCARTA
B4: SOMATOTIPO
B5: Peso kg | N5: CLASIFICACIÓN | R5: =SUM(C30:C35) -> 0
B6: Triceps mm | N6: A. Mesomorfo balanceado
B7: Subescapular mm | N7: B. Endomorfo balanceado
B8: Supraespinal mm | N8: C. Ectomorfo balanceado
B9: Sumatoria | C9: =SUM(C6:C8) -> 0 | N9: D. Mesomorfo-Endomorfo
B10: Corrección proporcionalidad | C10: =C9*(170.18/C11) -> #DIV/0! | N10: E. Mesomorfo-Ectomorfo
B11: Estatura cm | N11: F. Endomorfo-Ectomorfo
B12: Diámetro humero cm | N12: G. Endo-Mesomorfo
B13: Diámetro femur cm | N13: H. Meso-Endomorfo
B14: Perímetro brazo tenso cm | N14: I. Meso-Ectomorfo
B15: Perímetro brazo corregido | C15: =C14-(C6/10) -> 0 | N15: J. Ecto-Mesomorfo
B16: Perímetro pantorrilla cm | N16: K. Ecto-Endomorfo
B17: Pliegue pantorrilla mm | N17: L. Endo-Ectomorfo
B18: Perímetro pantorrilla corregido | C18: =C16-(C17/10) -> 0
B19: HWR | C19: =C11/(C5^0.333) -> #DIV/0!
B20: Componentes
B21: ENDOMORFIA | C21: =(0.1451*C10)-(0.00068*(C10^2))+(0.0000014*(C10^3))-0.7182 -> #DIV/0!
B22: MESOMORFIA | C22: =(0.858*C12)+(0.601*C13)+(0.188*C15)+(0.161*C18)-(0.131*C11)+4.5 -> 4.5
B23: ECTOMORFIA | C23: =IF(C19>=40.75,((C19*0.732)-28.58),IF(AND(C19>38.25,C19<40.75),((C19*0.463)-17.63),0.1)) -> #DIV/0!
B24: Coordenadas
B25: X | C25: =C23-C21 -> #DIV/0!
B26: Y | C26: =(2*C22)-(C23+C21) -> #DIV/0!
B28: % Grasa Yuhasz
B29: Sexo | C29: Hombre
B30: Triceps mm | C30: =C6
B31: Subescapular mm | C31: =C7
B32: Supraespinal mm | C32: =C8
B33: Pantorrilla mm | C33: =C17
B34: Abdominal mm
B35: Muslo medio mm
B36: % Grasa | C36: =IF(C29="Hombre",((0.1051*R5)+2.585),((0.1548*R5)+3.588)) -> 2.585
B37: Peso graso kg | C37: =((C5*C36)/100) -> 0
B38: Masa libre de grasa kg | C38: =C5-C37 -> 0
B39: Índice Sustancia Corporal Activa | C39: =(C38*100000)/(C11^3) -> #DIV/0!
B40: Clasificación AKS | C40: =IF(C39<0.99,"Deficiente masa muscular",IF(AND(C39>=1,C39<=1.12),"Adecuada masa muscular","Excelente masa muscular")) -> #DIV/0!
B41: Peso optimo
B42: % grasa esperado
B43: Peso optimo Kg | C43: =C38/(1-(C42/100)) -> 0
B50: FÓRMULA SINTÉTICA DE CONSUMO Y PLANEADA
I52: FÓRMULA SINTÉTICA PLANEADA | P52: Recomendaciones
I53: Nutrientes | J53: Gramos | K53: Calorías | L53: % AMDR | M53: Otros | P53: Proteínas | R53: 14-20% AMDR
C54: NOTA: Para definir la calorías totales utilice las fórmulas de requerimientos generales o el cálculo de METs | I54: Proteínas | J54: =(N56*J67) -> 0 | K54: =(J54*4) -> 0 | L54: =((100/K66)*K54) -> #DIV/0! | M54: g AVB | N54: =((N55/100)*J54) -> 0 | P54: Prote g/kg/peso | R54: 1,11-2,00
M55: % AVB | P55: Prote AVB | R55: 60-80%
M56: g/kg/peso | P56: CHOs totales | R56: 50-65%
I57: Grasas | J57: =(K57/9) -> 0 | K57: =((K66/100)*L57) -> 0 | M57: g GS | N57: =(((K66/100)*N58)/9) -> 0 | P57: CHOs simples | R57: <10%
M58: %AMDR GS | P58: Grasa total 27,5 | R58: 20-35% AMDR
M59: g GM | N59: =(((K66/100)*N60)/9) -> 0 | P59: G saturada | R59: <10%
M60: %AMDR GM | N60: =(L57-N58)-N62 -> 0 | P60: G poli | R60: 5-10%
M61: g GP | N61: =(((K66/100)*N62)/9) -> 0 | P61: G mono | R61: GS-GM
M62: %AMDR GP | P62: G trans | R62: <1%
M63: Colesterol | P63: Colesterol | R63: <300mg
I64: CHOs | J64: =(K64/4) -> #DIV/0! | K64: =((K66/100)*L64) -> #DIV/0! | L64: =(100-L67) -> #DIV/0! | M64: g Concent | N64: =(((K66/100)*N65)/4) -> 0 | P64: Colesterol enf.card | R64: <200mg
M65: %AMDR | P65: Fibra | R65: 14g/1000cal
I66: Total: | L66: =SUM(L54:L65) -> #DIV/0! | M66: Fibra | P66: Sodio | R66: <2300mg
I67: Kg Ref | K67: =SUM(K54:K65) -> #DIV/0! | L67: =SUM(L54:L63) -> #DIV/0! | P67: Sodio hipertensos | R67: <1500mg
B69: REQUERIMIENTO FINAL
B71: Kcal | C71: Prot | D71: Grasa | E71: GS | F71: GM | G71: GP | H71: COL | I71: CHOS | J71: Fibra
B72: =K66 | C72: =J54 -> 0 | D72: =J57 -> 0 | E72: =N57 -> 0 | F72: =N59 -> 0 | G72: =N61 -> 0 | H72: =N63 | I72: =J64 -> #DIV/0! | J72: =N66
B74: FÓRMULA SINTÉTICA DESARROLLADA
B76: NOTA: Puede introducir manualmente cada uno de los nutrientes por porción del suplemento especifico que el deportista este usando o que usted recomiende
B78: Grupo de alimentos | H78: Porciones | I78: Kcal | J78: Prot | K78: Grasa | L78: GS | M78: GM | N78: GP | O78: COL | P78: CHOS | Q78: FD | R78: Calcio (mg) | S78: P (mg) | T78: Fe (mg) | U78: Na (mg) | V78: K (mg) | W78: Mg (mg) | X78: Zn (mg) | Y78: Cu (mg) | Z78: Mn (mg) | AA78: Vit A (ER) | AB78: Tiamina (mg) | AC78: Riboflavina (mg) | AD78: Niacina (mg) | AE78: Ac, Pantotenico (mg) | AF78: Priridox. (mg) | AG78: Acido Folico (ug) | AH78: Vit B12 (ug) | AI78: Vit C (mg)
B79: Leches enteras frescas y fermentadas | I79: =(J79*4)+(K79*9)+(P79*4) -> 139.1 | J79: 6.7 | K79: 6.7 | L79: 4.4 | M79: 1.95 | N79: 0.49 | O79: 26 | P79: 13 | Q79: 0 | R79: 236 | S79: 173 | T79: 0.2 | U79: 96 | V79: 330 | W79: 25 | X79: 0.89 | Y79: 0.03 | Z79: 0.01 | AA79: 73 | AB79: 0.08 | AC79: 0.34 | AD79: 0.3 | AE79: 0.67 | AF79: 0.08 | AG79: 10 | AH79: 0.65 | AI79: 3
B80: Leches semidescremadas frescas y fermentadas | I80: =(J80*4)+(K80*9)+(P80*4) -> 94.5 | J80: 5.4 | K80: 2.1 | L80: 0.87 | M80: 0.54 | N80: 0.35 | O80: 5 | P80: 13.5 | Q80: 0.8 | R80: 153 | S80: 143 | T80: 0.4 | U80: 72 | V80: 268 | W80: 25 | X80: 1.24 | Y80: 0.06 | Z80: 0.11 | AA80: 76 | AB80: 0.12 | AC80: 0.25 | AD80: 0.2 | AE80: 0.41 | AF80: 0.06 | AG80: 8 | AH80: 0.5 | AI80: 4
B81: Leches descremadas frescas y fermentadas | I81: =(J81*4)+(K81*9)+(P81*4) -> 82.3 | J81: 9 | K81: 0.7 | L81: 0.45 | M81: 0.18 | N81: 0.03 | O81: 6 | P81: 10 | Q81: 0 | R81: 256 | S81: 214 | T81: 0.1 | U81: 101 | V81: 340 | W81: 24 | X81: 1.05 | Y81: 0.02 | Z81: 0.01 | AA81: 89 | AB81: 0.08 | AC81: 0.33 | AD81: 0.2 | AE81: 0.79 | AF81: 0.08 | AG81: 14 | AH81: 0.84 | AI81: 2
B82: Leches frescas y fermentadas enteras altas en calorías y azucares | I82: =(J82*4)+(K82*9)+(P82*4) -> 170.7 | J82: 6.4 | K82: 5.9 | L82: 3.8 | M82: 1.91 | N82: 0.63 | O82: 22 | P82: 23 | Q82: 0.4 | R82: 258 | S82: 169 | T82: 0.3 | U82: 115 | V82: 334 | W82: 27 | X82: 1.03 | Y82: 0.05 | Z82: 0.04 | AA82: 45 | AB82: 0.08 | AC82: 0.37 | AD82: 0.2 | AE82: 0.73 | AF82: 0.08 | AG82: 13 | AH82: 0.76 | AI82: 3
B83: Suplementos (Introduzca la información nutricional de 1 porción de suplemento)
B84: Sustitutos | I84: =(J84*4)+(K84*9)+(P84*4) -> 77.1 | J84: 5.8 | K84: 5.5 | L84: 2.91 | M84: 1.94 | N84: 0.41 | O84: 40 | P84: 1.1 | Q84: 0 | R84: 95 | S84: 85 | T84: 1.1 | U84: 211 | V84: 52 | W84: 6 | X84: 0.65 | Y84: 0.03 | Z84: 0.01 | AA84: 45 | AB84: 0.04 | AC84: 0.1 | AD84: 0.4 | AE84: 0.16 | AF84: 0.05 | AG84: 4 | AH84: 0.72 | AI84: 0
B85: Carnes magras crudas y proteínas texturizada | I85: =(J85*4)+(K85*9)+(P85*4) -> 108.3 | J85: 19.1 | K85: 3.1 | L85: 0.92 | M85: 1.16 | N85: 0.53 | O85: 50 | P85: 1 | Q85: 0.3 | R85: 22 | S85: 191 | T85: 1.5 | U85: 72 | V85: 325 | W85: 28 | X85: 1.81 | Y85: 0.11 | Z85: 0.12 | AA85: 7 | AB85: 0.19 | AC85: 0.18 | AD85: 5.6 | AE85: 0.78 | AF85: 0.35 | AG85: 15 | AH85: 2.39 | AI85: 1
B86: Carnes crudas altas en lípidos | I86: =(J86*4)+(K86*9)+(P86*4) -> 138.7 | J86: 15.6 | K86: 7.9 | L86: 2.51 | M86: 3.3 | N86: 1.25 | O86: 137 | P86: 1.3 | Q86: 0 | R86: 37 | S86: 186 | T86: 2.5 | U86: 101 | V86: 234 | W86: 20 | X86: 1.87 | Y86: 0.47 | Z86: 0.09 | AA86: 1515 | AB86: 0.07 | AC86: 0.53 | AD86: 4.4 | AE86: 1.67 | AF86: 0.27 | AG86: 87 | AH86: 10.58 | AI86: 6
B87: Leguminosas adultos | I87: =(J87*4)+(K87*9)+(P87*4) -> 158.1 | J87: 9.8 | K87: 1.7 | L87: 0.25 | M87: 0.32 | N87: 0.94 | O87: 0 | P87: 25.9 | Q87: 7.9 | R87: 50 | S87: 167 | T87: 3.1 | U87: 10 | V87: 534 | W87: 62 | X87: 1.22 | Y87: 0.28 | Z87: 0.6 | AA87: 10 | AB87: 0.2 | AC87: 0.09 | AD87: 0.9 | AE87: 0.42 | AF87: 0.16 | AG87: 142 | AH87: 0 | AI87: 4
B88: Cereales adultos | I88: =(J88*4)+(K88*9)+(P88*4) -> 93.8 | J88: 2.5 | K88: 1 | L88: 0.24 | M88: 0.32 | N88: 0.33 | O88: 1 | P88: 18.7 | Q88: 1.2 | R88: 19 | S88: 47 | T88: 0.9 | U88: 82 | V88: 53 | W88: 13 | X88: 0.42 | Y88: 0.05 | Z88: 0.24 | AA88: 22 | AB88: 0.11 | AC88: 0.09 | AD88: 1.1 | AE88: 0.15 | AF88: 0.08 | AG88: 38 | AH88: 0 | AI88: 2
B89: Raíces, tubérculos y plátanos adultos | I89: =(J89*4)+(K89*9)+(P89*4) -> 95.7 | J89: 1.4 | K89: 0.1 | L89: 0.05 | M89: 0.01 | N89: 0.06 | O89: 0 | P89: 22.3 | Q89: 1.9 | R89: 11 | S89: 40 | T89: 0.5 | U89: 10 | V89: 376 | W89: 20 | X89: 0.23 | Y89: 0.13 | Z89: 0.25 | AA89: 156 | AB89: 0.05 | AC89: 0.04 | AD89: 0.9 | AE89: 0.29 | AF89: 0.21 | AG89: 13 | AH89: 0 | AI89: 28
B90: Promedio "Harinas" adultos | I90: =(J90*4)+(K90*9)+(P90*4) -> 95.4 | J90: 2 | K90: 0.6 | L90: 0.14 | M90: 0.16 | N90: 0.19 | O90: 0 | P90: 20.5 | Q90: 1.5 | R90: 15 | S90: 43 | T90: 0.7 | U90: 46 | V90: 214 | W90: 17 | X90: 0.33 | Y90: 0.09 | Z90: 0.24 | AA90: 89 | AB90: 0.08 | AC90: 0.07 | AD90: 1 | AE90: 0.22 | AF90: 0.15 | AG90: 26 | AH90: 0 | AI90: 15
B91: Verduras y hortalizas adultos y niños | I91: =(J91*4)+(K91*9)+(P91*4) -> 29.5 | J91: 1.2 | K91: 0.3 | L91: 0.05 | M91: 0.03 | N91: 0.13 | O91: 0 | P91: 5.5 | Q91: 1.7 | R91: 15 | S91: 32 | T91: 0.7 | U91: 68 | V91: 187 | W91: 12 | X91: 0.29 | Y91: 0.1 | Z91: 0.16 | AA91: 136 | AB91: 0.05 | AC91: 0.06 | AD91: 0.8 | AE91: 0.37 | AF91: 0.09 | AG91: 23 | AH91: 0 | AI91: 19
B92: Frutas adultos y niños | I92: =(J92*4)+(K92*9)+(P92*4) -> 59.9 | J92: 1 | K92: 0.3 | L92: 0.06 | M92: 0.09 | N92: 0.11 | O92: 0 | P92: 13.3 | Q92: 2.6 | R92: 21 | S92: 24 | T92: 0.5 | U92: 4 | V92: 244 | W92: 19 | X92: 0.14 | Y92: 0.07 | Z92: 0.17 | AA92: 74 | AB92: 0.06 | AC92: 0.06 | AD92: 0.9 | AE92: 0.27 | AF92: 0.1 | AG92: 20 | AH92: 0 | AI92: 52
B93: Nueces adultos y niños | I93: =(J93*4)+(K93*9)+(P93*4) -> 56.4 | J93: 1.3 | K93: 4.8 | L93: 1.15 | M93: 2.44 | N93: 0.99 | O93: 0 | P93: 2 | Q93: 0.7 | R93: 8 | S93: 34 | T93: 0.3 | U93: 6 | V93: 55 | W93: 16 | X93: 0.28 | Y93: 0.1 | Z93: 0.18 | AA93: 1 | AB93: 0.03 | AC93: 0.02 | AD93: 0.2 | AE93: 0.08 | AF93: 0.02 | AG93: 5 | AH93: 0 | AI93: 0
B94: Semillas adultos y niños | I94: =(J94*4)+(K94*9)+(P94*4) -> 58.5 | J94: 2.3 | K94: 4.1 | L94: 0.5 | M94: 0.91 | N94: 2.48 | O94: 0 | P94: 3.1 | Q94: 2.1 | R94: 50 | S94: 74 | T94: 0.9 | U94: 2 | V94: 78 | W94: 37 | X94: 0.58 | Y94: 0.15 | Z94: 0.35 | AA94: 1 | AB94: 0.07 | AC94: 0.02 | AD94: 0.3 | AE94: 0.15 | AF94: 0.06 | AG94: 18 | AH94: 0 | AI94: 0
B95: Azucares y dulces adultos | I95: =(J95*4)+(K95*9)+(P95*4) -> 89.9 | J95: 0.9 | K95: 1.1 | L95: 0.63 | M95: 0.33 | N95: 0.07 | O95: 2 | P95: 19.1 | Q95: 0.5 | R95: 20 | S95: 23 | T95: 0.3 | U95: 25 | V95: 67 | W95: 6 | X95: 0.16 | Y95: 0.05 | Z95: 0.16 | AA95: 10 | AB95: 0.04 | AC95: 0.07 | AD95: 0.2 | AE95: 0.08 | AF95: 0.02 | AG95: 5 | AH95: 0.04 | AI95: 2
... B100: Productos con reducción de grasa adultos y niños | I100: =(J100*4)+(K100*9)+(P100*4) -> 39.3 | J100: 1.3 | K100: 3.3 | L100: 1.16 | M100: 0.98 | N100: 0.89 | O100: 6 | P100: 1.1 | Q100: 0 | R100: 16 | S100: 37 | T100: 0 | U100: 125 | V100: 19 | W100: 2 | X100: 0.12 | Y100: 0 | Z100: 0 | AA100: 41 | AB100: 0 | AC100: 0.02 | AD100: 0 | AE100: 0.04 | AF100: 0.03 | AG100: 3 | AH100: 0.06 | AI100: 0
B103: Grupo de alimentos | H103: Porciones | I103: Kcal | J103: Prot | K103: Grasa | L103: GS | M103: GM | N103: GP | O103: COL | P103: CHOS | Q103: FD | R103: Calcio (mg) | S103: P (mg) | T103: Fe (mg) | U103: Na (mg) | V103: K (mg) | W103: Mg (mg) | X103: Zn (mg) | Y103: Cu (mg) | Z103: Mn (mg) | AA103: Vit A (ER) | AB103: Tiamina (mg) | AC103: Riboflavina (mg) | AD103: Niacina (mg) | AE103: Ac, Pantotenico (mg) | AF103: Priridox. (mg) | AG103: Acido Folico (ug) | AH103: Vit B12 (ug) | AI103: Vit C (mg)
B104: Leches enteras frescas y fermentadas | H104: =H79 | I104: =(I79*H79) -> 0 | J104: =(J79*H79) -> 0 | K104: =(K79*H79) -> 0 | L104: =(L79*H79) -> 0 | M104: =(M79*H79) -> 0 | N104: =(N79*H79) -> 0 | O104: =(O79*H79) -> 0 | P104: =(P79*H79) -> 0 | Q104: =(Q79*H79) -> 0 | R104: =(R79*H79) -> 0 | S104: =(S79*H79) -> 0 | T104: =(T79*H79) -> 0 | U104: =(U79*H79) -> 0 | V104: =(V79*H79) -> 0 | W104: =(W79*H79) -> 0 | X104: =(X79*H79) -> 0 | Y104: =(Y79*H79) -> 0 | Z104: =(Z79*H79) -> 0 | AA104: =(AA79*H79) -> 0 | AB104: =(AB79*H79) -> 0 | AC104: =(AC79*H79) -> 0 | AD104: =(AD79*H79) -> 0 | AE104: =(AE79*H79) -> 0 | AF104: =(AF79*H79) -> 0 | AG104: =(AG79*H79) -> 0 | AH104: =(AH79*H79) -> 0 | AI104: =(AI79*H79) -> 0
B105: Leches semidescremadas frescas y fermentadas | H105: =H80 | I105: =(I80*H80) -> 0 | J105: =(J80*H80) -> 0 | K105: =(K80*H80) -> 0 | L105: =(L80*H80) -> 0 | M105: =(M80*H80) -> 0 | N105: =(N80*H80) -> 0 | O105: =(O80*H80) -> 0 | P105: =(P80*H80) -> 0 | Q105: =(Q80*H80) -> 0 | R105: =(R80*H80) -> 0 | S105: =(S80*H80) -> 0 | T105: =(T80*H80) -> 0 | U105: =(U80*H80) -> 0 | V105: =(V80*H80) -> 0 | W105: =(W80*H80) -> 0 | X105: =(X80*H80) -> 0 | Y105: =(Y80*H80) -> 0 | Z105: =(Z80*H80) -> 0 | AA105: =(AA80*H80) -> 0 | AB105: =(AB80*H80) -> 0 | AC105: =(AC80*H80) -> 0 | AD105: =(AD80*H80) -> 0 | AE105: =(AE80*H80) -> 0 | AF105: =(AF80*H80) -> 0 | AG105: =(AG80*H80) -> 0 | AH105: =(AH80*H80) -> 0 | AI105: =(AI80*H80) -> 0
B106: Leches descremadas frescas y fermentadas | H106: =H81 | I106: =(I81*H81) -> 0 | J106: =(J81*H81) -> 0 | K106: =(K81*H81) -> 0 | L106: =(L81*H81) -> 0 | M106: =(M81*H81) -> 0 | N106: =(N81*H81) -> 0 | O106: =(O81*H81) -> 0 | P106: =(P81*H81) -> 0 | Q106: =(Q81*H81) -> 0 | R106: =(R81*H81) -> 0 | S106: =(S81*H81) -> 0 | T106: =(T81*H81) -> 0 | U106: =(U81*H81) -> 0 | V106: =(V81*H81) -> 0 | W106: =(W81*H81) -> 0 | X106: =(X81*H81) -> 0 | Y106: =(Y81*H81) -> 0 | Z106: =(Z81*H81) -> 0 | AA106: =(AA81*H81) -> 0 | AB106: =(AB81*H81) -> 0 | AC106: =(AC81*H81) -> 0 | AD106: =(AD81*H81) -> 0 | AE106: =(AE81*H81) -> 0 | AF106: =(AF81*H81) -> 0 | AG106: =(AG81*H81) -> 0 | AH106: =(AH81*H81) -> 0 | AI106: =(AI81*H81) -> 0
B107: Leches frescas y fermentadas enteras altas en calorías y azucares | H107: =H82 | I107: =(I82*H82) -> 0 | J107: =(J82*H82) -> 0 | K107: =(K82*H82) -> 0 | L107: =(L82*H82) -> 0 | M107: =(M82*H82) -> 0 | N107: =(N82*H82) -> 0 | O107: =(O82*H82) -> 0 | P107: =(P82*H82) -> 0 | Q107: =(Q82*H82) -> 0 | R107: =(R82*H82) -> 0 | S107: =(S82*H82) -> 0 | T107: =(T82*H82) -> 0 | U107: =(U82*H82) -> 0 | V107: =(V82*H82) -> 0 | W107: =(W82*H82) -> 0 | X107: =(X82*H82) -> 0 | Y107: =(Y82*H82) -> 0 | Z107: =(Z82*H82) -> 0 | AA107: =(AA82*H82) -> 0 | AB107: =(AB82*H82) -> 0 | AC107: =(AC82*H82) -> 0 | AD107: =(AD82*H82) -> 0 | AE107: =(AE82*H82) -> 0 | AF107: =(AF82*H82) -> 0 | AG107: =(AG82*H82) -> 0 | AH107: =(AH82*H82) -> 0 | AI107: =(AI82*H82) -> 0
B108: Suplementos | H108: =H83 | I108: =(I83*H83) -> 0 | J108: =(J83*H83) -> 0 | K108: =(K83*H83) -> 0 | L108: =(L83*H83) -> 0 | M108: =(M83*H83) -> 0 | N108: =(N83*H83) -> 0 | O108: =(O83*H83) -> 0 | P108: =(P83*H83) -> 0 | Q108: =(Q83*H83) -> 0 | R108: =(R83*H83) -> 0 | S108: =(S83*H83) -> 0 | T108: =(T83*H83) -> 0 | U108: =(U83*H83) -> 0 | V108: =(V83*H83) -> 0 | W108: =(W83*H83) -> 0 | X108: =(X83*H83) -> 0 | Y108: =(Y83*H83) -> 0 | Z108: =(Z83*H83) -> 0 | AA108: =(AA83*H83) -> 0 | AB108: =(AB83*H83) -> 0 | AC108: =(AC83*H83) -> 0 | AD108: =(AD83*H83) -> 0 | AE108: =(AE83*H83) -> 0 | AF108: =(AF83*H83) -> 0 | AG108: =(AG83*H83) -> 0 | AH108: =(AH83*H83) -> 0 | AI108: =(AI83*H83) -> 0
B109: Sustitutos | H109: =H84 | I109: =(I84*H84) -> 0 | J109: =(J84*H84) -> 0 | K109: =(K84*H84) -> 0 | L109: =(L84*H84) -> 0 | M109: =(M84*H84) -> 0 | N109: =(N84*H84) -> 0 | O109: =(O84*H84) -> 0 | P109: =(P84*H84) -> 0 | Q109: =(Q84*H84) -> 0 | R109: =(R84*H84) -> 0 | S109: =(S84*H84) -> 0 | T109: =(T84*H84) -> 0 | U109: =(U84*H84) -> 0 | V109: =(V84*H84) -> 0 | W109: =(W84*H84) -> 0 | X109: =(X84*H84) -> 0 | Y109: =(Y84*H84) -> 0 | Z109: =(Z84*H84) -> 0 | AA109: =(AA84*H84) -> 0 | AB109: =(AB84*H84) -> 0 | AC109: =(AC84*H84) -> 0 | AD109: =(AD84*H84) -> 0 | AE109: =(AE84*H84) -> 0 | AF109: =(AF84*H84) -> 0 | AG109: =(AG84*H84) -> 0 | AH109: =(AH84*H84) -> 0 | AI109: =(AI84*H84) -> 0
B110: Carnes magras crudas y proteínas texturizada | H110: =H85 | I110: =(I85*H85) -> 0 | J110: =(J85*H85) -> 0 | K110: =(K85*H85) -> 0 | L110: =(L85*H85) -> 0 | M110: =(M85*H85) -> 0 | N110: =(N85*H85) -> 0 | O110: =(O85*H85) -> 0 | P110: =(P85*H85) -> 0 | Q110: =(Q85*H85) -> 0 | R110: =(R85*H85) -> 0 | S110: =(S85*H85) -> 0 | T110: =(T85*H85) -> 0 | U110: =(U85*H85) -> 0 | V110: =(V85*H85) -> 0 | W110: =(W85*H85) -> 0 | X110: =(X85*H85) -> 0 | Y110: =(Y85*H85) -> 0 | Z110: =(Z85*H85) -> 0 | AA110: =(AA85*H85) -> 0 | AB110: =(AB85*H85) -> 0 | AC110: =(AC85*H85) -> 0 | AD110: =(AD85*H85) -> 0 | AE110: =(AE85*H85) -> 0 | AF110: =(AF85*H85) -> 0 | AG110: =(AG85*H85) -> 0 | AH110: =(AH85*H85) -> 0 | AI110: =(AI85*H85) -> 0
B111: Carnes crudas altas en lípidos | H111: =H86 | I111: =(I86*H86) -> 0 | J111: =(J86*H86) -> 0 | K111: =(K86*H86) -> 0 | L111: =(L86*H86) -> 0 | M111: =(M86*H86) -> 0 | N111: =(N86*H86) -> 0 | O111: =(O86*H86) -> 0 | P111: =(P86*H86) -> 0 | Q111: =(Q86*H86) -> 0 | R111: =(R86*H86) -> 0 | S111: =(S86*H86) -> 0 | T111: =(T86*H86) -> 0 | U111: =(U86*H86) -> 0 | V111: =(V86*H86) -> 0 | W111: =(W86*H86) -> 0 | X111: =(X86*H86) -> 0 | Y111: =(Y86*H86) -> 0 | Z111: =(Z86*H86) -> 0 | AA111: =(AA86*H86) -> 0 | AB111: =(AB86*H86) -> 0 | AC111: =(AC86*H86) -> 0 | AD111: =(AD86*H86) -> 0 | AE111: =(AE86*H86) -> 0 | AF111: =(AF86*H86) -> 0 | AG111: =(AG86*H86) -> 0 | AH111: =(AH86*H86) -> 0 | AI111: =(AI86*H86) -> 0
B112: Leguminosas adultos | H112: =H87 | I112: =(I87*H87) -> 0 | J112: =(J87*H87) -> 0 | K112: =(K87*H87) -> 0 | L112: =(L87*H87) -> 0 | M112: =(M87*H87) -> 0 | N112: =(N87*H87) -> 0 | O112: =(O87*H87) -> 0 | P112: =(P87*H87) -> 0 | Q112: =(Q87*H87) -> 0 | R112: =(R87*H87) -> 0 | S112: =(S87*H87) -> 0 | T112: =(T87*H87) -> 0 | U112: =(U87*H87) -> 0 | V112: =(V87*H87) -> 0 | W112: =(W87*H87) -> 0 | X112: =(X87*H87) -> 0 | Y112: =(Y87*H87) -> 0 | Z112: =(Z87*H87) -> 0 | AA112: =(AA87*H87) -> 0 | AB112: =(AB87*H87) -> 0 | AC112: =(AC87*H87) -> 0 | AD112: =(AD87*H87) -> 0 | AE112: =(AE87*H87) -> 0 | AF112: =(AF87*H87) -> 0 | AG112: =(AG87*H87) -> 0 | AH112: =(AH87*H87) -> 0 | AI112: =(AI87*H87) -> 0
B113: Cereales adultos | H113: =H88 | I113: =(I88*H88) -> 0 | J113: =(J88*H88) -> 0 | K113: =(K88*H88) -> 0 | L113: =(L88*H88) -> 0 | M113: =(M88*H88) -> 0 | N113: =(N88*H88) -> 0 | O113: =(O88*H88) -> 0 | P113: =(P88*H88) -> 0 | Q113: =(Q88*H88) -> 0 | R113: =(R88*H88) -> 0 | S113: =(S88*H88) -> 0 | T113: =(T88*H88) -> 0 | U113: =(U88*H88) -> 0 | V113: =(V88*H88) -> 0 | W113: =(W88*H88) -> 0 | X113: =(X88*H88) -> 0 | Y113: =(Y88*H88) -> 0 | Z113: =(Z88*H88) -> 0 | AA113: =(AA88*H88) -> 0 | AB113: =(AB88*H88) -> 0 | AC113: =(AC88*H88) -> 0 | AD113: =(AD88*H88) -> 0 | AE113: =(AE88*H88) -> 0 | AF113: =(AF88*H88) -> 0 | AG113: =(AG88*H88) -> 0 | AH113: =(AH88*H88) -> 0 | AI113: =(AI88*H88) -> 0
B114: Raíces, tubérculos y plátanos adultos | H114: =H89 | I114: =(I89*H89) -> 0 | J114: =(J89*H89) -> 0 | K114: =(K89*H89) -> 0 | L114: =(L89*H89) -> 0 | M114: =(M89*H89) -> 0 | N114: =(N89*H89) -> 0 | O114: =(O89*H89) -> 0 | P114: =(P89*H89) -> 0 | Q114: =(Q89*H89) -> 0 | R114: =(R89*H89) -> 0 | S114: =(S89*H89) -> 0 | T114: =(T89*H89) -> 0 | U114: =(U89*H89) -> 0 | V114: =(V89*H89) -> 0 | W114: =(W89*H89) -> 0 | X114: =(X89*H89) -> 0 | Y114: =(Y89*H89) -> 0 | Z114: =(Z89*H89) -> 0 | AA114: =(AA89*H89) -> 0 | AB114: =(AB89*H89) -> 0 | AC114: =(AC89*H89) -> 0 | AD114: =(AD89*H89) -> 0 | AE114: =(AE89*H89) -> 0 | AF114: =(AF89*H89) -> 0 | AG114: =(AG89*H89) -> 0 | AH114: =(AH89*H89) -> 0 | AI114: =(AI89*H89) -> 0
B115: Promedio "Harinas" adultos | H115: =H90 | I115: =(I90*H90) -> 0 | J115: =(J90*H90) -> 0 | K115: =(K90*H90) -> 0 | L115: =(L90*H90) -> 0 | M115: =(M90*H90) -> 0 | N115: =(N90*H90) -> 0 | O115: =(O90*H90) -> 0 | P115: =(P90*H90) -> 0 | Q115: =(Q90*H90) -> 0 | R115: =(R90*H90) -> 0 | S115: =(S90*H90) -> 0 | T115: =(T90*H90) -> 0 | U115: =(U90*H90) -> 0 | V115: =(V90*H90) -> 0 | W115: =(W90*H90) -> 0 | X115: =(X90*H90) -> 0 | Y115: =(Y90*H90) -> 0 | Z115: =(Z90*H90) -> 0 | AA115: =(AA90*H90) -> 0 | AB115: =(AB90*H90) -> 0 | AC115: =(AC90*H90) -> 0 | AD115: =(AD90*H90) -> 0 | AE115: =(AE90*H90) -> 0 | AF115: =(AF90*H90) -> 0 | AG115: =(AG90*H90) -> 0 | AH115: =(AH90*H90) -> 0 | AI115: =(AI90*H90) -> 0
... B125: Productos con reducción de grasa adultos y niños | H125: =H100 | I125: =(I100*H100) -> 0 | J125: =(J100*H100) -> 0 | K125: =(K100*H100) -> 0 | L125: =(L100*H100) -> 0 | M125: =(M100*H100) -> 0 | N125: =(N100*H100) -> 0 | O125: =(O100*H100) -> 0 | P125: =(P100*H100) -> 0 | Q125: =(Q100*H100) -> 0 | R125: =(R100*H100) -> 0 | S125: =(S100*H100) -> 0 | T125: =(T100*H100) -> 0 | U125: =(U100*H100) -> 0 | V125: =(V100*H100) -> 0 | W125: =(W100*H100) -> 0 | X125: =(X100*H100) -> 0 | Y125: =(Y100*H100) -> 0 | Z125: =(Z100*H100) -> 0 | AA125: =(AA100*H100) -> 0 | AB125: =(AB100*H100) -> 0 | AC125: =(AC100*H100) -> 0 | AD125: =(AD100*H100) -> 0 | AE125: =(AE100*H100) -> 0 | AF125: =(AF100*H100) -> 0 | AG125: =(AG100*H100) -> 0 | AH125: =(AH100*H100) -> 0 | AI125: =(AI100*H100) -> 0
H126: TOTAL | I126: =SUM(I104:I125) -> 0 | J126: =SUM(J104:J125) -> 0 | K126: =SUM(K104:K125) -> 0 | L126: =SUM(L104:L125) -> 0 | M126: =SUM(M104:M125) -> 0 | N126: =SUM(N104:N125) -> 0 | O126: =SUM(O104:O125) -> 0 | P126: =SUM(P104:P125) -> 0 | ... AI126: =SUM(AI104:AI125) -> 0
H127: REQUERIDO | I127: =B72 | J127: =C72 -> 0 | K127: =D72 -> 0 | L127: =E72 -> 0 | M127: =F72 -> 0 | N127: =G72 -> 0 | O127: =H72 | P127: =I72 -> #DIV/0! | Q127: =J72
H128: %ADECUACI | I128: =((100/I127)*I126) -> #DIV/0! | J128: =((100/J127)*J126) -> #DIV/0! | K128: =((100/K127)*K126) -> #DIV/0! | L128: =((100/L127)*L126) -> #DIV/0! | M128: =((100/M127)*M126) -> #DIV/0! | N128: =((100/N127)*N126) -> #DIV/0! | O128: =((100/O127)*O126) -> #DIV/0! | P128: =((100/P127)*P126) -> #DIV/0! | ... AI128: =((100/AI127)*AI126) -> #DIV/0!
I129: Kcal | J129: Prot | K129: Grasa | L129: GS | M129: GM | N129: GP | O129: COL | P129: CHOS | Q129: FD | R129: Calcio (mg) | S129: P (mg) | T129: Fe (mg) | U129: Na (mg) | V129: K (mg) | W129: Mg (mg) | X129: Zn (mg) | Y129: Cu (mg) | Z129: Mn (mg) | AA129: Vit A (ER) | AB129: Tiamina (mg) | AC129: Riboflavina (mg) | AD129: Niacina (mg) | AE129: Ac, Pantotenico (mg) | AF129: Priridox. (mg) | AG129: Acido Folico (ug) | AH129: Vit B12 (ug) | AI129: Vit C (mg)
B131: FÓRMULA SINTÉTICA PLANEADA FINAL
...

Sheet F. Desarrollada
B2: FÓRMULA SINTÉTICA DESARROLLADA
B4: Grupo de alimentos | C4: Porciones | D4: Kcal | E4: Prot | F4: Grasa | G4: GS | H4: GM | I4: GP | J4: COL | K4: CHOS | L4: FD | M4: Calcio (mg) | N4: P (mg) | O4: Fe (mg) | P4: Na (mg) | Q4: K (mg) | R4: Mg (mg) | S4: Zn (mg) | T4: Cu (mg) | U4: Mn (mg) | V4: Vit A (ER) | W4: Tiamina (mg) | X4: Riboflavina (mg) | Y4: Niacina (mg) | Z4: Ac, Pantotenico (mg) | AA4: Priridox. (mg) | AB4: Acido Folico (ug) | AC4: Vit B12 (ug) | AD4: Vit C (ug)
B5: Leches enteras frescas y fermentadas | D5: =(E5*4)+(F5*9)+(K5*4) -> 139.1 | E5: 6.7 | F5: 6.7 | G5: 4.4 | H5: 1.95 | I5: 0.49 | J5: 26 | K5: 13 | L5: 0 | M5: 236 | N5: 173 | O5: 0.2 | P5: 96 | Q5: 330 | R5: 25 | S5: 0.89 | T5: 0.03 | U5: 0.01 | V5: 73 | W5: 0.08 | X5: 0.34 | Y5: 0.3 | Z5: 0.67 | AA5: 0.08 | AB5: 10 | AC5: 0.65 | AD5: 3
B6: Leches semidescremadas frescas y fermentadas | D6: =(E6*4)+(F6*9)+(K6*4) -> 94.5 | E6: 5.4 | F6: 2.1 | G6: 0.87 | H6: 0.54 | I6: 0.35 | J6: 5 | K6: 13.5 | L6: 0.8 | M6: 153 | N6: 143 | O6: 0.4 | P6: 72 | Q6: 268 | R6: 25 | S6: 1.24 | T6: 0.06 | U6: 0.11 | V6: 76 | W6: 0.12 | X6: 0.25 | Y6: 0.2 | Z6: 0.41 | AA6: 0.06 | AB6: 8 | AC6: 0.5 | AD6: 4
B7: Leches descremadas frescas y fermentadas | D7: =(E7*4)+(F7*9)+(K7*4) -> 82.3 | E7: 9 | F7: 0.7 | G7: 0.45 | H7: 0.18 | I7: 0.03 | J7: 6 | K7: 10 | L7: 0 | M7: 256 | N7: 214 | O7: 0.1 | P7: 101 | Q7: 340 | R7: 24 | S7: 1.05 | T7: 0.02 | U7: 0.01 | V7: 89 | W7: 0.08 | X7: 0.33 | Y7: 0.2 | Z7: 0.79 | AA7: 0.08 | AB7: 14 | AC7: 0.84 | AD7: 2
B8: Leches frescas y fermentadas enteras altas en calorías y azucares | D8: =(E8*4)+(F8*9)+(K8*4) -> 170.7 | E8: 6.4 | F8: 5.9 | G8: 3.8 | H8: 1.91 | I8: 0.63 | J8: 22 | K8: 23 | L8: 0.4 | M8: 258 | N8: 169 | O8: 0.3 | P8: 115 | Q8: 334 | R8: 27 | S8: 1.03 | T8: 0.05 | U8: 0.04 | V8: 45 | W8: 0.08 | X8: 0.37 | Y8: 0.2 | Z8: 0.73 | AA8: 0.08 | AB8: 13 | AC8: 0.76 | AD8: 3
B9: Leches frescas, fermentadas y productos lácteos menores de 2 años | D9: =(E9*4)+(F9*9)+(K9*4) -> 50.7 | E9: 2.9 | F9: 3.1 | G9: 2.01 | H9: 0.96 | I9: 0.18 | J9: 12 | K9: 2.8 | L9: 0 | M9: 93 | N9: 62 | O9: 0.1 | P9: 57 | Q9: 57 | R9: 6 | S9: 0.38 | T9: 0.01 | U9: 0 | V9: 36 | W9: 0.01 | X9: 0.08 | Y9: 0.1 | Z9: 0.12 | AA9: 0.02 | AB9: 2 | AC9: 0.2 | AD9: 0
B10: Sustitutos | D10: =(E10*4)+(F10*9)+(K10*4) -> 77.1 | E10: 5.8 | F10: 5.5 | G10: 2.91 | H10: 1.94 | I10: 0.41 | J10: 40 | K10: 1.1 | L10: 0 | M10: 95 | N10: 85 | O10: 1.1 | P10: 211 | Q10: 52 | R10: 6 | S10: 0.65 | T10: 0.03 | U10: 0.01 | V10: 45 | W10: 0.04 | X10: 0.1 | Y10: 0.4 | Z10: 0.16 | AA10: 0.05 | AB10: 4 | AC10: 0.72 | AD10: 0
B11: Huevo menores de 2 años | D11: =(E11*4)+(F11*9)+(K11*4) -> 52.9 | E11: 4.5 | F11: 3.7 | G11: 1.15 | H11: 1.42 | I11: 0.49 | J11: 180 | K11: 0.4 | L11: 0 | M11: 19 | N11: 64 | O11: 0.6 | P11: 46 | Q11: 46 | R11: 4 | S11: 0.4 | T11: 0.01 | U11: 0.01 | V11: 57 | W11: 0.03 | X11: 0.2 | Y11: 0 | Z11: 0.51 | AA11: 0.05 | AB11: 18 | AC11: 0.43 | AD11: 0
B12: Carnes magras crudas y proteínas texturizada adultos y niños | D12: =(E12*4)+(F12*9)+(K12*4) -> 108.3 | E12: 19.1 | F12: 3.1 | G12: 0.92 | H12: 1.16 | I12: 0.53 | J12: 50 | K12: 1 | L12: 0.3 | M12: 22 | N12: 191 | O12: 1.5 | P12: 72 | Q12: 325 | R12: 28 | S12: 1.81 | T12: 0.11 | U12: 0.12 | V12: 7 | W12: 0.19 | X12: 0.18 | Y12: 5.6 | Z12: 0.78 | AA12: 0.35 | AB12: 15 | AC12: 2.39 | AD12: 1
B13: Carnes magras cocidas menores de 2 años | D13: =(E13*4)+(F13*9)+(K13*4) -> 49.2 | E13: 7.8 | F13: 2 | G13: 0.52 | H13: 0.84 | I13: 0.35 | J13: 21 | K13: 0 | L13: 0 | M13: 7 | N13: 74 | O13: 0.4 | P13: 19 | Q13: 108 | R13: 8 | S13: 0.55 | T13: 0.04 | U13: 0.09 | V13: 5 | W13: 0.1 | X13: 0.07 | Y13: 1.9 | Z13: 0.33 | AA13: 0.09 | AB13: 2 | AC13: 1 | AD13: 0
B14: Carnes crudas altas en lípidos adultos y niños | D14: =(E14*4)+(F14*9)+(K14*4) -> 138.7 | E14: 15.6 | F14: 7.9 | G14: 2.51 | H14: 3.3 | I14: 1.25 | J14: 137 | K14: 1.3 | L14: 0 | M14: 37 | N14: 186 | O14: 2.5 | P14: 101 | Q14: 234 | R14: 20 | S14: 1.87 | T14: 0.47 | U14: 0.09 | V14: 1515 | W14: 0.07 | X14: 0.53 | Y14: 4.4 | Z14: 1.67 | AA14: 0.27 | AB14: 87 | AC14: 10.58 | AD14: 6
B15: Carnes cocidas altas en lípidos menores de 2 años | D15: =(E15*4)+(F15*9)+(K15*4) -> 46.8 | E15: 6.9 | F15: 2 | G15: 0.78 | H15: 0.86 | I15: 0.31 | J15: 79 | K15: 0.3 | L15: 0 | M15: 3 | N15: 57 | O15: 3 | P15: 62 | Q15: 55 | R15: 6 | S15: 1.21 | T15: 0.25 | U15: 0.04 | V15: 620 | W15: 0.02 | X15: 0.29 | Y15: 1.1 | Z15: 0.55 | AA15: 0.09 | AB15: 39 | AC15: 4.29 | AD15: 2
B16: Leguminosas adultos | D16: =(E16*4)+(F16*9)+(K16*4) -> 158.1 | E16: 9.8 | F16: 1.7 | G16: 0.25 | H16: 0.32 | I16: 0.94 | J16: 0 | K16: 25.9 | L16: 7.9 | M16: 50 | N16: 167 | O16: 3.1 | P16: 10 | Q16: 534 | R16: 62 | S16: 1.22 | T16: 0.28 | U16: 0.6 | V16: 10 | W16: 0.2 | X16: 0.09 | Y16: 0.9 | Z16: 0.42 | AA16: 0.16 | AB16: 142 | AC16: 0 | AD16: 4
... B45: Leche materna toma/100ml | D45: =(E45*4)+(F45*9)+(K45*4) -> 71.2 | E45: 1 | F45: 4.4 | G45: 2.01 | H45: 1.66 | I45: 0.5 | J45: 14 | K45: 6.9 | L45: 0 | M45: 32 | N45: 14 | O45: 0 | P45: 17 | Q45: 51 | R45: 3 | S45: 0.17 | T45: 0.05 | U45: 0.03 | V45: 64 | W45: 0.01 | X45: 0.04 | Y45: 0.2 | Z45: 0.22 | AA45: 0.01 | AB45: 5 | AC45: 0.05 | AD45: 5
B46: Suplemento (Introduzca manualmente los nutrientes por porción)
B49: Grupo de alimentos | C49: Porciones | D49: Kcal | E49: Prot | F49: Grasa | G49: GS | H49: GM | I49: GP | J49: COL | K49: CHOS | L49: FD | M49: Calcio (mg) | N49: P (mg) | O49: Fe (mg) | P49: Na (mg) | Q49: K (mg) | R49: Mg (mg) | S49: Zn (mg) | T49: Cu (mg) | U49: Mn (mg) | V49: Vit A (ER) | W49: Tiamina (mg) | X49: Riboflavina (mg) | Y49: Niacina (mg) | Z49: Ac, Pantotenico (mg) | AA49: Priridox. (mg) | AB49: Acido Folico (ug) | AC49: Vit B12 (ug) | AD49: Vit BC (ug)
B50: Leches enteras frescas y fermentadas | C50: =C5 | D50: =(D5*C5) -> 0 | E50: =(E5*C5) -> 0 | F50: =(F5*C5) -> 0 | G50: =(G5*C5) -> 0 | H50: =(H5*C5) -> 0 | I50: =(I5*C5) -> 0 | J50: =(J5*C5) -> 0 | K50: =(K5*C5) -> 0 | L50: =(L5*C5) -> 0 | M50: =(M5*C5) -> 0 | N50: =(N5*C5) -> 0 | O50: =(O5*C5) -> 0 | P50: =(P5*C5) -> 0 | Q50: =(Q5*C5) -> 0 | R50: =(R5*C5) -> 0 | S50: =(S5*C5) -> 0 | T50: =(T5*C5) -> 0 | U50: =(U5*C5) -> 0 | V50: =(V5*C5) -> 0 | W50: =(W5*C5) -> 0 | X50: =(X5*C5) -> 0 | Y50: =(Y5*C5) -> 0 | Z50: =(Z5*C5) -> 0 | AA50: =(AA5*C5) -> 0 | AB50: =(AB5*C5) -> 0 | AC50: =(AC5*C5) -> 0 | AD50: =(AD5*C5) -> 0
B51: Leches semidescremadas frescas y fermentadas | C51: =C6 | D51: =(D6*C6) -> 0 | E51: =(E6*C6) -> 0 | F51: =(F6*C6) -> 0 | G51: =(G6*C6) -> 0 | H51: =(H6*C6) -> 0 | I51: =(I6*C6) -> 0 | J51: =(J6*C6) -> 0 | K51: =(K6*C6) -> 0 | L51: =(L6*C6) -> 0 | M51: =(M6*C6) -> 0 | N51: =(N6*C6) -> 0 | O51: =(O6*C6) -> 0 | P51: =(P6*C6) -> 0 | Q51: =(Q6*C6) -> 0 | R51: =(R6*C6) -> 0 | S51: =(S6*C6) -> 0 | T51: =(T6*C6) -> 0 | U51: =(U6*C6) -> 0 | V51: =(V6*C6) -> 0 | W51: =(W6*C6) -> 0 | X51: =(X6*C6) -> 0 | Y51: =(Y6*C6) -> 0 | Z51: =(Z6*C6) -> 0 | AA51: =(AA6*C6) -> 0 | AB51: =(AB6*C6) -> 0 | AC51: =(AC6*C6) -> 0 | AD51: =(AD6*C6) -> 0
B52: Leches descremadas frescas y fermentadas | C52: =C7 | D52: =(D7*C7) -> 0 | E52: =(E7*C7) -> 0 | F52: =(F7*C7) -> 0 | G52: =(G7*C7) -> 0 | H52: =(H7*C7) -> 0 | I52: =(I7*C7) -> 0 | J52: =(J7*C7) -> 0 | K52: =(K7*C7) -> 0 | L52: =(L7*C7) -> 0 | M52: =(M7*C7) -> 0 | N52: =(N7*C7) -> 0 | O52: =(O7*C7) -> 0 | P52: =(P7*C7) -> 0 | Q52: =(Q7*C7) -> 0 | R52: =(R7*C7) -> 0 | S52: =(S7*C7) -> 0 | T52: =(T7*C7) -> 0 | U52: =(U7*C7) -> 0 | V52: =(V7*C7) -> 0 | W52: =(W7*C7) -> 0 | X52: =(X7*C7) -> 0 | Y52: =(Y7*C7) -> 0 | Z52: =(Z7*C7) -> 0 | AA52: =(AA7*C7) -> 0 | AB52: =(AB7*C7) -> 0 | AC52: =(AC7*C7) -> 0 | AD52: =(AD7*C7) -> 0
B53: Leches frescas y fermentadas enteras altas en calorías y azucares | C53: =C8 | D53: =(D8*C8) -> 0 | E53: =(E8*C8) -> 0 | F53: =(F8*C8) -> 0 | G53: =(G8*C8) -> 0 | H53: =(H8*C8) -> 0 | I53: =(I8*C8) -> 0 | J53: =(J8*C8) -> 0 | K53: =(K8*C8) -> 0 | L53: =(L8*C8) -> 0 | M53: =(M8*C8) -> 0 | N53: =(N8*C8) -> 0 | O53: =(O8*C8) -> 0 | P53: =(P8*C8) -> 0 | Q53: =(Q8*C8) -> 0 | R53: =(R8*C8) -> 0 | S53: =(S8*C8) -> 0 | T53: =(T8*C8) -> 0 | U53: =(U8*C8) -> 0 | V53: =(V8*C8) -> 0 | W53: =(W8*C8) -> 0 | X53: =(X8*C8) -> 0 | Y53: =(Y8*C8) -> 0 | Z53: =(Z8*C8) -> 0 | AA53: =(AA8*C8) -> 0 | AB53: =(AB8*C8) -> 0 | AC53: =(AC8*C8) -> 0 | AD53: =(AD8*C8) -> 0
B54: Leches frescas, fermentadas y productos lácteos menores de 2 años | C54: =C9 | D54: =(D9*C9) -> 0 | E54: =(E9*C9) -> 0 | F54: =(F9*C9) -> 0 | G54: =(G9*C9) -> 0 | H54: =(H9*C9) -> 0 | I54: =(I9*C9) -> 0 | J54: =(J9*C9) -> 0 | K54: =(K9*C9) -> 0 | L54: =(L9*C9) -> 0 | M54: =(M9*C9) -> 0 | N54: =(N9*C9) -> 0 | O54: =(O9*C9) -> 0 | P54: =(P9*C9) -> 0 | Q54: =(Q9*C9) -> 0 | R54: =(R9*C9) -> 0 | S54: =(S9*C9) -> 0 | T54: =(T9*C9) -> 0 | U54: =(U9*C9) -> 0 | V54: =(V9*C9) -> 0 | W54: =(W9*C9) -> 0 | X54: =(X9*C9) -> 0 | Y54: =(Y9*C9) -> 0 | Z54: =(Z9*C9) -> 0 | AA54: =(AA9*C9) -> 0 | AB54: =(AB9*C9) -> 0 | AC54: =(AC9*C9) -> 0 | AD54: =(AD9*C9) -> 0
B55: Sustitutos | C55: =C10 | D55: =(D10*C10) -> 0 | E55: =(E10*C10) -> 0 | F55: =(F10*C10) -> 0 | G55: =(G10*C10) -> 0 | H55: =(H10*C10) -> 0 | I55: =(I10*C10) -> 0 | J55: =(J10*C10) -> 0 | K55: =(K10*C10) -> 0 | L55: =(L10*C10) -> 0 | M55: =(M10*C10) -> 0 | N55: =(N10*C10) -> 0 | O55: =(O10*C10) -> 0 | P55: =(P10*C10) -> 0 | Q55: =(Q10*C10) -> 0 | R55: =(R10*C10) -> 0 | S55: =(S10*C10) -> 0 | T55: =(T10*C10) -> 0 | U55: =(U10*C10) -> 0 | V55: =(V10*C10) -> 0 | W55: =(W10*C10) -> 0 | X55: =(X10*C10) -> 0 | Y55: =(Y10*C10) -> 0 | Z55: =(Z10*C10) -> 0 | AA55: =(AA10*C10) -> 0 | AB55: =(AB10*C10) -> 0 | AC55: =(AC10*C10) -> 0 | AD55: =(AD10*C10) -> 0
B56: Huevo menores de 2 años | C56: =C11 | D56: =(D11*C11) -> 0 | E56: =(E11*C11) -> 0 | F56: =(F11*C11) -> 0 | G56: =(G11*C11) -> 0 | H56: =(H11*C11) -> 0 | I56: =(I11*C11) -> 0 | J56: =(J11*C11) -> 0 | K56: =(K11*C11) -> 0 | L56: =(L11*C11) -> 0 | M56: =(M11*C11) -> 0 | N56: =(N11*C11) -> 0 | O56: =(O11*C11) -> 0 | P56: =(P11*C11) -> 0 | Q56: =(Q11*C11) -> 0 | R56: =(R11*C11) -> 0 | S56: =(S11*C11) -> 0 | T56: =(T11*C11) -> 0 | U56: =(U11*C11) -> 0 | V56: =(V11*C11) -> 0 | W56: =(W11*C11) -> 0 | X56: =(X11*C11) -> 0 | Y56: =(Y11*C11) -> 0 | Z56: =(Z11*C11) -> 0 | AA56: =(AA11*C11) -> 0 | AB56: =(AB11*C11) -> 0 | AC56: =(AC11*C11) -> 0 | AD56: =(AD11*C11) -> 0
B57: Carnes magras crudas y proteínas texturizada adultos y niños | C57: =C12 | D57: =(D12*C12) -> 0 | E57: =(E12*C12) -> 0 | F57: =(F12*C12) -> 0 | G57: =(G12*C12) -> 0 | H57: =(H12*C12) -> 0 | I57: =(I12*C12) -> 0 | J57: =(J12*C12) -> 0 | K57: =(K12*C12) -> 0 | L57: =(L12*C12) -> 0 | M57: =(M12*C12) -> 0 | N57: =(N12*C12) -> 0 | O57: =(O12*C12) -> 0 | P57: =(P12*C12) -> 0 | Q57: =(Q12*C12) -> 0 | R57: =(R12*C12) -> 0 | S57: =(S12*C12) -> 0 | T57: =(T12*C12) -> 0 | U57: =(U12*C12) -> 0 | V57: =(V12*C12) -> 0 | W57: =(W12*C12) -> 0 | X57: =(X12*C12) -> 0 | Y57: =(Y12*C12) -> 0 | Z57: =(Z12*C12) -> 0 | AA57: =(AA12*C12) -> 0 | AB57: =(AB12*C12) -> 0 | AC57: =(AC12*C12) -> 0 | AD57: =(AD12*C12) -> 0
B58: Carnes magras cocidas menores de 2 años | C58: =C13 | D58: =(D13*C13) -> 0 | E58: =(E13*C13) -> 0 | F58: =(F13*C13) -> 0 | G58: =(G13*C13) -> 0 | H58: =(H13*C13) -> 0 | I58: =(I13*C13) -> 0 | J58: =(J13*C13) -> 0 | K58: =(K13*C13) -> 0 | L58: =(L13*C13) -> 0 | M58: =(M13*C13) -> 0 | N58: =(N13*C13) -> 0 | O58: =(O13*C13) -> 0 | P58: =(P13*C13) -> 0 | Q58: =(Q13*C13) -> 0 | R58: =(R13*C13) -> 0 | S58: =(S13*C13) -> 0 | T58: =(T13*C13) -> 0 | U58: =(U13*C13) -> 0 | V58: =(V13*C13) -> 0 | W58: =(W13*C13) -> 0 | X58: =(X13*C13) -> 0 | Y58: =(Y13*C13) -> 0 | Z58: =(Z13*C13) -> 0 | AA58: =(AA13*C13) -> 0 | AB58: =(AB13*C13) -> 0 | AC58: =(AC13*C13) -> 0 | AD58: =(AD13*C13) -> 0
B59: Carnes crudas altas en lípidos adultos y niños | C59: =C14 | D59: =(D14*C14) -> 0 | E59: =(E14*C14) -> 0 | F59: =(F14*C14) -> 0 | G59: =(G14*C14) -> 0 | H59: =(H14*C14) -> 0 | I59: =(I14*C14) -> 0 | J59: =(J14*C14) -> 0 | K59: =(K14*C14) -> 0 | L59: =(L14*C14) -> 0 | M59: =(M14*C14) -> 0 | N59: =(N14*C14) -> 0 | O59: =(O14*C14) -> 0 | P59: =(P14*C14) -> 0 | Q59: =(Q14*C14) -> 0 | R59: =(R14*C14) -> 0 | S59: =(S14*C14) -> 0 | T59: =(T14*C14) -> 0 | U59: =(U14*C14) -> 0 | V59: =(V14*C14) -> 0 | W59: =(W14*C14) -> 0 | X59: =(X14*C14) -> 0 | Y59: =(Y14*C14) -> 0 | Z59: =(Z14*C14) -> 0 | AA59: =(AA14*C14) -> 0 | AB59: =(AB14*C14) -> 0 | AC59: =(AC14*C14) -> 0 | AD59: =(AD14*C14) -> 0
B60: Carnes cocidas altas en lípidos menores de 2 años | C60: =C15 | D60: =(D15*C15) -> 0 | E60: =(E15*C15) -> 0 | F60: =(F15*C15) -> 0 | G60: =(G15*C15) -> 0 | H60: =(H15*C15) -> 0 | I60: =(I15*C15) -> 0 | J60: =(J15*C15) -> 0 | K60: =(K15*C15) -> 0 | L60: =(L15*C15) -> 0 | M60: =(M15*C15) -> 0 | N60: =(N15*C15) -> 0 | O60: =(O15*C15) -> 0 | P60: =(P15*C15) -> 0 | Q60: =(Q15*C15) -> 0 | R60: =(R15*C15) -> 0 | S60: =(S15*C15) -> 0 | T60: =(T15*C15) -> 0 | U60: =(U15*C15) -> 0 | V60: =(V15*C15) -> 0 | W60: =(W15*C15) -> 0 | X60: =(X15*C15) -> 0 | Y60: =(Y15*C15) -> 0 | Z60: =(Z15*C15) -> 0 | AA60: =(AA15*C15) -> 0 | AB60: =(AB15*C15) -> 0 | AC60: =(AC15*C15) -> 0 | AD60: =(AD15*C15) -> 0
B61: Leguminosas adultos | C61: =C16 | D61: =(D16*C16) -> 0 | E61: =(E16*C16) -> 0 | F61: =(F16*C16) -> 0 | G61: =(G16*C16) -> 0 | H61: =(H16*C16) -> 0 | I61: =(I16*C16) -> 0 | J61: =(J16*C16) -> 0 | K61: =(K16*C16) -> 0 | L61: =(L16*C16) -> 0 | M61: =(M16*C16) -> 0 | N61: =(N16*C16) -> 0 | O61: =(O16*C16) -> 0 | P61: =(P16*C16) -> 0 | Q61: =(Q16*C16) -> 0 | R61: =(R16*C16) -> 0 | S61: =(S16*C16) -> 0 | T61: =(T16*C16) -> 0 | U61: =(U16*C16) -> 0 | V61: =(V16*C16) -> 0 | W61: =(W16*C16) -> 0 | X61: =(X16*C16) -> 0 | Y61: =(Y16*C16) -> 0 | Z61: =(Z16*C16) -> 0 | AA61: =(AA16*C16) -> 0 | AB61: =(AB16*C16) -> 0 | AC61: =(AC16*C16) -> 0 | AD61: =(AD16*C16) -> 0
... B91: Suplemento | C91: =C46 | D91: =(D46*C46) -> 0 | E91: =(E46*C46) -> 0 | F91: =(F46*C46) -> 0 | G91: =(G46*C46) -> 0 | H91: =(H46*C46) -> 0 | I91: =(I46*C46) -> 0 | J91: =(J46*C46) -> 0 | K91: =(K46*C46) -> 0 | L91: =(L46*C46) -> 0 | M91: =(M46*C46) -> 0 | N91: =(N46*C46) -> 0 | O91: =(O46*C46) -> 0 | P91: =(P46*C46) -> 0 | Q91: =(Q46*C46) -> 0 | R91: =(R46*C46) -> 0 | S91: =(S46*C46) -> 0 | T91: =(T46*C46) -> 0 | U91: =(U46*C46) -> 0 | V91: =(V46*C46) -> 0 | W91: =(W46*C46) -> 0 | X91: =(X46*C46) -> 0 | Y91: =(Y46*C46) -> 0 | Z91: =(Z46*C46) -> 0 | AA91: =(AA46*C46) -> 0 | AB91: =(AB46*C46) -> 0 | AC91: =(AC46*C46) -> 0 | AD91: =(AD46*C46) -> 0
C92: TOTAL | D92: =SUM(D50:D91) -> 0 | E92: =SUM(E50:E91) -> 0 | F92: =SUM(F50:F91) -> 0 | G92: =SUM(G50:G91) -> 0 | H92: =SUM(H50:H91) -> 0 | I92: =SUM(I50:I91) -> 0 | J92: =SUM(J50:J91) -> 0 | K92: =SUM(K50:K91) -> 0 | ... AD92: =SUM(AD50:AD91) -> 0
C93: REQUERIDO
C94: %ADECUACI | D94: =((100/D93)*D92) -> #DIV/0! | E94: =((100/E93)*E92) -> #DIV/0! | F94: =((100/F93)*F92) -> #DIV/0! | G94: =((100/G93)*G92) -> #DIV/0! | H94: =((100/H93)*H92) -> #DIV/0! | I94: =((100/I93)*I92) -> #DIV/0! | J94: =((100/J93)*J92) -> #DIV/0! | K94: =((100/K93)*K92) -> #DIV/0! | ... AD94: =((100/AD93)*AD92) -> #DIV/0!
D95: Kcal | E95: Prot | F95: Grasa | G95: GS | H95: GM | I95: GP | J95: COL | K95: CHOS | L95: FD | M95: Calcio (mg) | N95: P (mg) | O95: Fe (mg) | P95: Na (mg) | Q95: K (mg) | R95: Mg (mg) | S95: Zn (mg) | T95: Cu (mg) | U95: Mn (mg) | V95: Vit A (ER) | W95: Tiamina (mg) | X95: Riboflavina (mg) | Y95: Niacina (mg) | Z95: Ac, Pantotenico (mg) | AA95: Priridox. (mg) | AB95: Acido Folico (ug) | AC95: Vit B12 (ug) | AD95: Vit C (ug)
B97: FÓRMULA SINTÉTICA PLANEADA FINAL
D99: FÓRMULA SINTÉTICA PLANEADA FINAL | J99: Recomendaciones RIEN | N99: Respaldo calórico no proteico
D100: Nutrientes | E100: Gramos | F100: Calorías | G100: % AMDR | H100: Otros | J100: Proteínas | L100: 14-20% | N100: Gramos N | P100: =E101/6.25 -> 0
D101: Proteínas | E101: =(E92) -> 0 | F101: =(E101*4) -> 0 | G101: =((100/F113)*F101) -> #DIV/0! | H101: g AVB | I101: =SUM(E50:E60,E90) -> 0 | J101: Prote g/kg/peso | L101: 1,11-1,16 | N101: Calorías no proteicas | P101: =F104+F111 -> 0
H102: % AVB | I102: =((100/E101)*I101) -> #DIV/0! | J102: Prote AVB | L102: 60-80% | N102: Respaldo calórico | P102: =P101/P100 -> #DIV/0!
H103: g/kg/peso | I103: =(E101/E114) -> #DIV/0! | J103: Carbohidratos totales | L103: 50-65% | N103: Clasificación | P103: =IF(P102>180,"Adecuado","Inadecuado") -> #DIV/0!
D104: Grasas | E104: =(F92) -> 0 | F104: =(E104*9) -> 0 | G104: =((100/F113)*F104) -> #DIV/0! | H104: g GS | I104: =(G92) -> 0 | J104: Carbohidratos simples | L104: <10%
H105: %AMDR GS | I105: =((100/F113)*(I104*9)) -> #DIV/0! | J105: Grasa total | L105: 20-35%
H106: g GM | I106: =(H92) -> 0 | J106: G saturada | L106: <10%
H107: %AMDR GM | I107: =((100/F113)*(I106*9)) -> #DIV/0! | J107: G mono | L107: GS-GM
H108: g GP | I108: =(I92) -> 0 | J108: G poli | L108: 5-10%
H109: %AMDR GP | I109: =((100/F113)*(I108*9)) -> #DIV/0! | J109: G trans | L109: <1%
H110: Colesterol | I110: =(J92) -> 0 | J110: Colesterol | L110: <300mg
D111: CHOs | E111: =(K92) -> 0 | F111: =(E111*4) -> 0 | G111: =((100/F113)*F111) -> #DIV/0! | H111: g Concent | I111: =SUM(K79:K80) -> 0 | J111: Colesterol enf.card | L111: <200mg
H112: %AMDR | I112: =((100/F113)*(I111*4)) -> #DIV/0! | J112: Fibra | L112: 14/1000cal
D113: Total: | F113: =SUM(F101:F112) -> 0 | G113: =SUM(G101:G112) -> #DIV/0! | H113: Fibra | I113: =L92 -> 0 | J113: Sodio | L113: <2300mg
D114: Kg Ref | J114: Sodio hipertensos | L114: <1500mg
B116: MINUTA PATRÓN
B118: Grupo de alimentos | C118: Porciones | D118: D | E118: MM | F118: A | G118: MT | H118: C | I118: ME
B119: Leches enteras frescas y fermentadas | C119: =C50 | K119: D: Desayuno
B120: Leches semidescremadas frescas y fermentadas | C120: =C51 | K120: MM: Media Mañana
B121: Leches descremadas frescas y fermentadas | C121: =C52 | K121: A: Almuerzo
B122: Leches frescas y fermentadas enteras altas en calorías y azucares | C122: =C53 | K122: MT: Media Tarde
B123: Leches frescas, fermentadas y productos lácteos menores de 2 años | C123: =C54 | K123: C: Cena
B124: Sustitutos | C124: =C55 | K124: ME: Merienda
B125: Huevo menores de 2 años | C125: =C56
B126: Carnes magras crudas y proteínas texturizada adultos y niños | C126: =C57
B127: Carnes magras cocidas menores de 2 años | C127: =C58
B128: Carnes crudas altas en lípidos adultos y niños | C128: =C59
B129: Carnes cocidas altas en lípidos menores de 2 años | C129: =C60
B130: Leguminosas adultos | C130: =C61
B131: Leguminosas niños | C131: =C62
B132: Leguminosas menores de 2 años | C132: =C63
B133: Cereales adultos | C133: =C64
B134: Cereales niños | C134: =C65
B135: Cereales menores de 2 años | C135: =C66
B136: Raíces, tubérculos y plátanos adultos | C136: =C67
... B160: Suplemento | C160: =C91
B162: EJEMPLO DE MENÚ
C164: Desayuno | E164: Media mañana | G164: Almuerzo | I164: Media tarde | K164: Cena | M164: Merienda

Sheet Otros
B2: JACKSON Y POLLOCK
B4: FORMULAS JACKSON Y POLLOCK GENERALES | H4: NUEVAS FORMULAS JACKSON Y POLLOCK 17 - 35 años
B5: HOMBRES | E5: MUJERES | H5: HOMBRES | K5: MUJERES
B6: PLIEGUE mm | C6: VALOR | E6: PLIEGUE mm | F6: VALOR | H6: PLIEGUE mm | I6: VALOR | K6: PLIEGUE mm | L6: VALOR
B7: Edad | E7: Edad | H7: Pecho | K7: Triceps
B8: Pecho | E8: Triceps | H8: Abdomen | K8: Suprailiaco
B9: Abdomen | E9: Suprailiaco | H9: Muslo | K9: Muslo
B10: Muslo | E10: Muslo | H10: M | I10: =SUM(I7:I9) -> 0 | K10: F | L10: =SUM(L7:L9) -> 0
B11: Sumatoria | C11: =SUM(C8:C10) -> 0 | E11: Sumatoria | F11: =SUM(F8:F10) -> 0 | H11: %Grasa | I11: =(0.2568*I10)-(0.0004*(I10*I10))+5.5458 -> 5.5458 | K11: %Grasa | L11: =(0.4446*L10)-(0.0012*(L10*L10))+6.7066 -> 6.7066
B12: Densidad | C12: =1.10938-(0.0008267*C11)+(0.0000016*(C11*C11))-(0.0002574*C7) -> 1.10938 | E12: Densidad | F12: =1.099421-(0.0009929*F11)+(0.0000023*(F11*F11))-(0.0001392*F7) -> 1.099421
B13: %Grasa Siri | C13: =((495/C12)-450) -> -3.8048279 | E13: %Grasa Siri | F13: =((495/F12)-450) -> 0.23698838
B15: DURNIN Y WOMERSLEY
B17: ANTIGUA DyM | I17: NUEVAS FÓRMULAS DyM HISPANOS
B18: PLIEGUE mm | C18: VALOR | I18: HOMBRES | K18: MUJERES
B19: Biceps | E19: Para esta fórmula por favor ingrese el valor de C y M correspondiente según el sexo y la edad de la persona, en la tabla que se encuentra en la parte inferior | I19: VARIABLE | J19: VALOR | K19: VARIABLE | L19: VALOR
B20: Triceps | I20: Edad años | K20: Edad años
B21: Subescapular | I21: Peso kg | K21: Peso kg
B22: Ileocrestal | I22: Altura cm | K22: Altura cm
B23: Sumatoria | C23: =SUM(C19:C22) -> 0 | I23: Abdomen cm | K23: Abdomen cm
B24: C | I24: Biceps mm | K24: Biceps mm
B25: M | I25: Triceps mm | K25: Triceps mm
I26: Subescapular mm | K26: Subescapular mm
B27: Densidad | C27: =C24-(C25*LOG10(C23)) -> #NUM! | I27: Ileocrestal mm | K27: Ileocrestal mm
B28: %Grasa Siri | C28: =((495/C27)-450) -> #NUM! | I28: Sumatoria | J28: =SUM(J24:J27) -> 0 | K28: Sumatoria | L28: =SUM(L24:L27) -> 0
I29: % Grasa | J29: =((23.66*(LOG10(J28)))+(0.04*J20)-(0.036*J21)-(0.109*J22)+(0.272*J23)-26.41) -> #NUM! | K29: % Grasa | L29: =((23.871*(LOG10(L28)))+(0.019*L20)-(0.022*L21)-(0.118*L22)+(0.249*L23)-16.782) -> #NUM!
I30: NUEVAS FÓRMULAS DyM AFROAMERICANOS
B31: Hombres | C31: 17-19 | D31: 20-29 | E31: 30-39 | F31: 40-49 | G31: 50+ | I31: HOMBRES | K31: MUJERES
B32: C | C32: 1.162 | D32: 1.1631 | E32: 1.1422 | F32: 1.162 | G32: 1.1715 | I32: VARIABLE | J32: VALOR | K32: VARIABLE | L32: VALOR
B33: M | C33: 0.063 | D33: 0.0632 | E33: 0.0544 | F33: 0.07 | G33: 0.0779 | I33: Edad años | K33: Edad años
I34: Peso kg | K34: Peso kg
B35: Mujeres | C35: 17-19 | D35: 20-29 | E35: 30-39 | F35: 40-49 | G35: 50+ | I35: Altura cm | K35: Altura cm
B36: C | C36: 1.1549 | D36: 1.1599 | E36: 1.1423 | F36: 1.1333 | G36: 1.1339 | I36: Abdomen cm | K36: Abdomen cm
B37: M | C37: 0.0678 | D37: 0.0717 | E37: 0.0632 | F37: 0.0612 | G37: 0.0645 | I37: Biceps mm | K37: Biceps mm
I38: Triceps mm | K38: Triceps mm
B39: CLASIFICACIÓN SEEDO | I39: Subescapular mm | K39: Subescapular mm
C40: HOMBRES | D40: MUJERES | I40: Ileocrestal mm | K40: Ileocrestal mm
B41: Normopeso | C41: 12-20 | D41: 20-30 | I41: Sumatoria | J41: =SUM(J37:J40) -> 0 | K41: Sumatoria | L41: =SUM(L37:L40) -> 0
B42: Limite | C42: 21-25 | D42: 31-33 | I42: % Grasa | J42: =(22.702*(LOG10(J41)))+(0.065*J33)+(0.043*J34)-(0.08*J35)+(0.156*J36)-26.806 -> #NUM! | K42: % Grasa | L42: =(20.867*(LOG10(L41)))+(0.052*L33)+(0.14*L34)-(0.152*L35)+(0.149*L36)-8.227 -> #NUM!
B43: Obesidad | C43: >25 | D43: >33
B45: FÓRMULA SINTÉTICA DE CONSUMO
B47: Nutrientes | C47: Gramos | D47: Calorías | E47: % AMDR | F47: Otros
B48: Proteínas | D48: =(C48*4) -> 0 | E48: =((100/D60)*D48) -> #DIV/0! | F48: g AVB
F49: % AVB | G49: =((100/C48)*G48) -> #DIV/0!
F50: g/kg/peso | G50: =(C48/C61) -> #DIV/0!
B51: Grasas | D51: =(C51*9) -> 0 | E51: =((100/D60)*D51) -> #DIV/0! | F51: g GS
F52: %AMDR GS | G52: =((100/D60)*(G51*9)) -> #DIV/0!
F53: g GM
F54: %AMDR GM | G54: =((100/D60)*(G53*9)) -> #DIV/0!
F55: g GP
F56: %AMDR GP | G56: =((100/D60)*(G55*9)) -> #DIV/0!
F57: Colesterol
B58: CHOs | D58: =(C58*4) -> 0 | E58: =((100/D60)*D58) -> #DIV/0! | F58: g Concent
F59: %AMDR | G59: =((100/D60)*(G58*4)) -> #DIV/0!
B60: Total: | D60: =SUM(D48:D59) -> 0 | E60: =SUM(E48:E59) -> #DIV/0! | F60: Fibra
B61: Kg Ref
B63: REFERENCIAS
B65: 1. | C65: Durnin JVGA, Womersley J. Body fat assessed from total body density and its estimation from skinfold thickness: measurements on 481 men and women aged from 16 to 72 Years. British Journal of Nutrition. 1974;32(1):77-97.
B66: 2. | C66: Jackson AS, Pollock ML. Practical assessment of body composition. The physician and sport medicine. 1985;13(5):76-90.
B67: 3. | C67: Davidson LE, Wang J, Thornton JC, Kaleem Z, Silva-Palacios F, Pierson RN, et al. Predicting fat percent by skinfolds in racial groups: Durnin and Womersley revisited. Medicine and science in sports and exercise. 2011;43(3):542-9.
B68: 4. | C68: Jackson AS, Ellis KJ, McFarlin BK, Sailors MH, Bray MS. Cross-validation of generalised body composition equations with diverse young men and women: the Training Intervention and Genetics of Exercise Response (TIGER) Study. Br J Nutr. 2009;101(6):871-8.
B69: 5. | C69: SEEDO. Consenso Sociedad Española para el Estudio de la Obesidad 2000 para la evaluación del sobrepeso y la obesidad y el establecimiento de criterios de intervención terapéutica. Barcelona: 2000 (115). p. 587-597.

Sheet Notas
B2: NOTAS
C7: R/.
